Workbook

Sheet Sommaire
A1: Plans repas — 9 semaines indépendantes — 24 recettes — Chronodrive Compiègne, retrait le dimanche — budget midi + soir ≤ 55 €
A2: Modèle : dimanche soir pizza ; lundi → vendredi soir 5 recettes cuisinées en double portion (midi du lendemain) ; samedi soir + dimanche midi = 1 plat surgelé 900 g coupé en deux. 2 articles au congélateur maximum. Chaque recette au plus 2 fois sur 9 semaines, jamais 2 semaines de suite. Placard/bases comptés au PRIX PLEIN. S1 = inchangée (panier déjà fait). Prix Chronodrive relevés les 01-02/09/2026 ; pesto vert et sauce tomate-basilic estimés (relevés Carrefour Bomerée du 12/10 en note).
A4: Semaine | B4: Recettes (lundi → vendredi) | C4: Plat week-end | D4: Pizza | E4: Courses recettes (formats entiers) € | F4: Placard / bases prix plein € | G4: Week-end € | H4: TOTAL € | I4: Marge vs 55 € | J4: Gâchis estimé € | K4: Stock sec € | L4: kcal moyen / portion | M4: Prot moy. g | N4: Gluc moy. g | O4: Lip moy. g
A5: S1 | B5: 10. Côtes d'échine à la moutarde et à la crème + spaghetti · 16. « Couscous » étudiant poulet, carottes, pois chiches · 5. Pâtes à la « carbonara » à la française · 9. Riz au chorizo et poivrons (façon paella express) · 15. Saucisses-lentilles express (lentilles en conserve) | C5: Auchan Poulet basquaise et riz 900 g | D5: Auchan Pizza royale jambon-fromage-olives 400 g | E5: 28.03 | F5: 12.73 | G5: 6.9 | H5: 47.66 | I5: 7.34 | J5: 2.1451274 | K5: 6.7834284 | L5: =ROUND(AVERAGE(Nutrition!H71,Nutrition!H135,Nutrition!H148,Nutrition!H235,Nutrition!H253),0) -> 813 | M5: =AVERAGE(Nutrition!I71,Nutrition!I135,Nutrition!I148,Nutrition!I235,Nutrition!I253) -> 35.598 | N5: =AVERAGE(Nutrition!J71,Nutrition!J135,Nutrition!J148,Nutrition!J235,Nutrition!J253) -> 78.371 | O5: =AVERAGE(Nutrition!K71,Nutrition!K135,Nutrition!K148,Nutrition!K235,Nutrition!K253) -> 38.627
A6: S2 | B6: 3. Croque-monsieur express · 2. Gnocchis aux épinards, crème et lardons · 22. Frittata d'été aux courgettes et mozzarella filante (+ pain) · 21. Risotto de coquillettes au jambon, petits pois et parmesan · 24. Pâtes sauce tomate-basilic, mozzarella fondante & parmesan | C6: Auchan Penne poulet-champignons 900 g | D6: Ristorante 4 fromages 340 g | E6: 29.93 | F6: 7.62 | G6: 7.54 | H6: 45.09 | I6: 9.91 | J6: 2.2685738 | K6: 5.1177186 | L6: =ROUND(AVERAGE(Nutrition!H29,Nutrition!H41,Nutrition!H339,Nutrition!H356,Nutrition!H382),0) -> 771 | M6: =AVERAGE(Nutrition!I29,Nutrition!I41,Nutrition!I339,Nutrition!I356,Nutrition!I382) -> 36.252 | N6: =AVERAGE(Nutrition!J29,Nutrition!J41,Nutrition!J339,Nutrition!J356,Nutrition!J382) -> 82.123 | O6: =AVERAGE(Nutrition!K29,Nutrition!K41,Nutrition!K339,Nutrition!K356,Nutrition!K382) -> 31.778
A7: S3 | B7: 10. Côtes d'échine à la moutarde et à la crème + spaghetti · 12. Ravioli poêlés à la tomate et mozzarella · 23. Pâtes pesto caprese (boule de mozzarella, tomates cerises) · 1. Poulet au curry, lait de coco et noix de cajou + riz · 7. Quesadillas chorizo-emmental & avocat (version éco) | C7: Marie Lasagnes à la bolognaise 1 kg | D7: Auchan Pizza au chèvre 390 g | E7: 32.22 | F7: 14.63 | G7: 8.28 | H7: 55.13 | I7: -0.13 | J7: 2.4149003 | K7: 4.5582145 | L7: =ROUND(AVERAGE(Nutrition!H15,Nutrition!H105,Nutrition!H148,Nutrition!H186,Nutrition!H369),0) -> 933 | M7: =AVERAGE(Nutrition!I15,Nutrition!I105,Nutrition!I148,Nutrition!I186,Nutrition!I369) -> 40.96 | N7: =AVERAGE(Nutrition!J15,Nutrition!J105,Nutrition!J148,Nutrition!J186,Nutrition!J369) -> 77.294 | O7: =AVERAGE(Nutrition!K15,Nutrition!K105,Nutrition!K148,Nutrition!K186,Nutrition!K369) -> 49.991
A8: S4 | B8: 16. « Couscous » étudiant poulet, carottes, pois chiches · 24. Pâtes sauce tomate-basilic, mozzarella fondante & parmesan · 9. Riz au chorizo et poivrons (façon paella express) · 19. Pâtes crémeuses au chèvre, miel et lardons · 15. Saucisses-lentilles express (lentilles en conserve) | C8: Auchan Torsades à la carbonara 900 g | D8: Auchan Pizza bolognaise 390 g | E8: 27.13 | F8: 14.92 | G8: 7 | H8: 49.05 | I8: 5.95 | J8: 2.6259318 | K8: 5.8723765 | L8: =ROUND(AVERAGE(Nutrition!H135,Nutrition!H235,Nutrition!H253,Nutrition!H304,Nutrition!H382),0) -> 799 | M8: =AVERAGE(Nutrition!I135,Nutrition!I235,Nutrition!I253,Nutrition!I304,Nutrition!I382) -> 35.179 | N8: =AVERAGE(Nutrition!J135,Nutrition!J235,Nutrition!J253,Nutrition!J304,Nutrition!J382) -> 83.754 | O8: =AVERAGE(Nutrition!K135,Nutrition!K235,Nutrition!K253,Nutrition!K304,Nutrition!K382) -> 34.877
A9: S5 | B9: 13. Tortellini aux champignons, sauce crème-parmesan · 21. Risotto de coquillettes au jambon, petits pois et parmesan · 5. Pâtes à la « carbonara » à la française · 14. Risotto aux lardons et champignons · 20. One pot pasta chorizo-basilic | C9: Auchan Riz cantonais 900 g | D9: Auchan Les Italiennes 4 fromages 340 g | E9: 30.64 | F9: 12.78 | G9: 7.2 | H9: 50.62 | I9: 4.38 | J9: 3.1223049 | K9: 6.8326637 | L9: =ROUND(AVERAGE(Nutrition!H71,Nutrition!H204,Nutrition!H221,Nutrition!H321,Nutrition!H339),0) -> 878 | M9: =AVERAGE(Nutrition!I71,Nutrition!I204,Nutrition!I221,Nutrition!I321,Nutrition!I339) -> 33.655 | N9: =AVERAGE(Nutrition!J71,Nutrition!J204,Nutrition!J221,Nutrition!J321,Nutrition!J339) -> 98.615 | O9: =AVERAGE(Nutrition!K71,Nutrition!K204,Nutrition!K221,Nutrition!K321,Nutrition!K339) -> 37.593
A10: S6 | B10: 3. Croque-monsieur express · 8. Pâtes au pesto rosso et au poulet (+ parmesan) · 12. Ravioli poêlés à la tomate et mozzarella · 22. Frittata d'été aux courgettes et mozzarella filante (+ pain) · 1. Poulet au curry, lait de coco et noix de cajou + riz | C10: Auchan Paëlla poulet-crevettes-chorizo 900 g | D10: Auchan Pizza chorizo-poivrons 390 g | E10: 34.38 | F10: 12.42 | G10: 8.04 | H10: 54.84 | I10: 0.16 | J10: 3.7117794 | K10: 4.5979572 | L10: =ROUND(AVERAGE(Nutrition!H15,Nutrition!H41,Nutrition!H119,Nutrition!H186,Nutrition!H356),0) -> 843 | M10: =AVERAGE(Nutrition!I15,Nutrition!I41,Nutrition!I119,Nutrition!I186,Nutrition!I356) -> 42.508 | N10: =AVERAGE(Nutrition!J15,Nutrition!J41,Nutrition!J119,Nutrition!J186,Nutrition!J356) -> 76.049 | O10: =AVERAGE(Nutrition!K15,Nutrition!K41,Nutrition!K119,Nutrition!K186,Nutrition!K356) -> 39.597
A11: S7 | B11: 11. Raviolis frais à la sauce tomate-crème (poivron, épices) · 13. Tortellini aux champignons, sauce crème-parmesan · 18. Chakchouka au chèvre frais & pains pita · 14. Risotto aux lardons et champignons · 20. One pot pasta chorizo-basilic | C11: Bonduelle Poêlée gnocchi-épinards 750 g | D11: Ristorante margherita 355 g | E11: 34.04 | F11: 25.62 | G11: 7.04 | H11: 66.7 | I11: -11.7 | J11: 4.6653826 | K11: 5.2749642 | L11: =ROUND(AVERAGE(Nutrition!H171,Nutrition!H204,Nutrition!H221,Nutrition!H289,Nutrition!H321),0) -> 893 | M11: =AVERAGE(Nutrition!I171,Nutrition!I204,Nutrition!I221,Nutrition!I289,Nutrition!I321) -> 33.821 | N11: =AVERAGE(Nutrition!J171,Nutrition!J204,Nutrition!J221,Nutrition!J289,Nutrition!J321) -> 94.804 | O11: =AVERAGE(Nutrition!K171,Nutrition!K204,Nutrition!K221,Nutrition!K289,Nutrition!K321) -> 40.819
A12: S8 | B12: 4. Hachis parmentier rapide (purée en flocons) · 2. Gnocchis aux épinards, crème et lardons · 8. Pâtes au pesto rosso et au poulet (+ parmesan) · 23. Pâtes pesto caprese (boule de mozzarella, tomates cerises) · 7. Quesadillas chorizo-emmental & avocat (version éco) | C12: Auchan Poêlée campagnarde 900 g | D12: Auchan Pizza poulet barbecue 390 g | E12: 39.93 | F12: 5.64 | G12: 7.94 | H12: 53.51 | I12: 1.49 | J12: 4.9297466 | K12: 6.6022277 | L12: =ROUND(AVERAGE(Nutrition!H29,Nutrition!H58,Nutrition!H105,Nutrition!H119,Nutrition!H369),0) -> 903 | M12: =AVERAGE(Nutrition!I29,Nutrition!I58,Nutrition!I105,Nutrition!I119,Nutrition!I369) -> 40.615 | N12: =AVERAGE(Nutrition!J29,Nutrition!J58,Nutrition!J105,Nutrition!J119,Nutrition!J369) -> 77.009 | O12: =AVERAGE(Nutrition!K29,Nutrition!K58,Nutrition!K105,Nutrition!K119,Nutrition!K369) -> 47.476
A13: S9 | B13: 6. Poulet à la crème et aux champignons + spaghetti · 11. Raviolis frais à la sauce tomate-crème (poivron, épices) · 17. Poulet basquaise et son riz · 18. Chakchouka au chèvre frais & pains pita · 19. Pâtes crémeuses au chèvre, miel et lardons | C13: Bonduelle Poêlée gnocchi-tomate 750 g | D13: Auchan Pizza royale jambon-fromage-olives 400 g | E13: 37.18 | F13: 25.92 | G13: 6.14 | H13: 69.24 | I13: -14.24 | J13: 6.1870251 | K13: 6.5531786 | L13: =ROUND(AVERAGE(Nutrition!H90,Nutrition!H171,Nutrition!H271,Nutrition!H289,Nutrition!H304),0) -> 810 | M13: =AVERAGE(Nutrition!I90,Nutrition!I171,Nutrition!I271,Nutrition!I289,Nutrition!I304) -> 39.574 | N13: =AVERAGE(Nutrition!J90,Nutrition!J171,Nutrition!J271,Nutrition!J289,Nutrition!J304) -> 89.92 | O13: =AVERAGE(Nutrition!K90,Nutrition!K171,Nutrition!K271,Nutrition!K289,Nutrition!K304) -> 31.424

Sheet Étapes (2 portions)
A1: Étapes complètes des 24 recettes — QUANTITÉS POUR 2 PORTIONS — substitutions éco intégrées
A3: 1. Poulet au curry, lait de coco et noix de cajou + riz
A4: Source | B4: Marmiton — https://www.marmiton.org/recettes/recette_poulet-au-curry-lait-de-coco-et-noix-de-cajou_37398.aspx
A5: Temps | B5: 25 min (10 + 15)
A6: Ustensiles | B6: Sauteuse + casserole
A7: Substitutions | B7: aucune
A8: Ingrédients (2 portions) | B8: Qté | C8: Unité | D8: Équivalent | E8: Produit Chronodrive | F8: Origine
A9: Filet de poulet | B9: 260 | C9: g | D9: 1 filet | E9: Filets de poulet | F9: recette
A10: Lait de coco | B10: 200 | C10: ml | D10: ½ brique de 20 cl | E10: Lait de coco | F10: recette
A11: Curry en poudre | B11: 4 | C11: g | D11: 1 cc rase | E11: Curry en poudre Ducros 47 g | F11: placard
A12: Sauce soja | B12: 10 | C12: ml | D12: 1 cc | E12: Sauce soja | F12: recette
A13: Noix de cajou grillées salées | B13: 40 | C13: g | D13: 1 petite poignée | E13: Noix de cajou | F13: recette
A14: Maïzena | B14: 10 | C14: g | D14: 1 cc bombée | E14: Farine T45 | F14: placard
A15: Huile | B15: 30 | C15: ml | D15: 1 cs | E15: Huile de tournesol | F15: placard
A16: Riz long cru | B16: 160 | C16: g | D16: ½ verre | E16: Riz long | F16: ajout
A17: Sel | B17: 2 | C17: g | D17: 1 pincée | E17: Sel / poivre | F17: placard
A18: Poivre | B18: 1 | C18: g | D18: 1 tour de moulin | E18: Sel / poivre | F18: placard
A19: Étape | B19: Consigne (2 portions)
A20: 1 | B20: Riz : verser 160 g de riz long dans une casserole avec 240 ml d'eau et 1 pincée de sel. Porter à ébullition, couvrir, baisser à feu doux, cuire 11 min sans soulever le couvercle, puis couper le feu et laisser reposer 5 min à couvert.
A21: 2 | B21: Concasser 40 g de noix de cajou (fond d'un verre dans une assiette creuse) : moitié poudre, moitié petits morceaux.
A22: 3 | B22: Couper 260 g de filet de poulet en cubes de 1-2 cm. Les mettre dans un bol avec 10 g de farine (2 cc) et mélanger pour les enrober.
A23: 4 | B23: Chauffer 30 ml d'huile (2 cs) dans une sauteuse à feu moyen-vif. Ajouter 4 g de curry (2 cc) et laisser chauffer 30 s jusqu'à ce que ça sente.
A24: 5 | B24: Ajouter le poulet, faire dorer 5 min en remuant.
A25: 6 | B25: Verser 10 ml de sauce soja (2 cc) puis 200 ml de lait de coco (1 brique). Mélanger, baisser à feu doux, laisser cuire 10 min : la sauce épaissit grâce à la farine.
A26: 7 | B26: 5 min avant la fin, ajouter les noix de cajou. Saler légèrement, poivrer.
A27: 8 | B27: Servir la moitié sur la moitié du riz. Laisser refroidir l'autre moitié (riz et sauce séparés) avant de mettre en boîte au frigo pour le lendemain midi.
A29: 2. Gnocchis aux épinards, crème et lardons
A30: Source | B30: Marmiton — https://www.marmiton.org/recettes/recette_gnocchi-aux-epinards-creme-et-lardons_537272.aspx
A31: Temps | B31: 12 min (5 + 7)
A32: Ustensiles | B32: Casserole + poêle
A33: Substitutions | B33: aucune
A34: Ingrédients (2 portions) | B34: Qté | C34: Unité | D34: Équivalent | E34: Produit Chronodrive | F34: Origine
A35: Gnocchis (frais, à poêler ou à pocher) | B35: 500 | C35: g | D35: ½ paquet de 500 g | E35: Gnocchis à poêler | F35: recette
A36: Oignon | B36: 100 | C36: g | D36: ½ oignon moyen | E36: Oignons jaunes | F36: recette
A37: Lardons fumés | B37: 120 | C37: g | D37: ½ sachet de 100 g + un peu | E37: Lardons fumés | F37: recette
A38: Parmesan râpé (ou emmental) | B38: 40 | C38: g | D38: 2 cs | E38: Emmental râpé | F38: recette
A39: Crème liquide | B39: 200 | C39: ml | D39: ½ brique de 20 cl | E39: Crème liquide UHT | F39: recette
A40: Pousses d'épinards | B40: 100 | C40: g | D40: 2 grosses poignées | E40: Pousses d'épinard | F40: recette
A41: Sel | B41: 2 | C41: g | D41: 1 pincée | E41: Sel / poivre | F41: placard
A42: Poivre | B42: 1 | C42: g | E42: Sel / poivre | F42: placard
A43: Étape | B43: Consigne (2 portions)
A44: 1 | B44: Porter une casserole d'eau salée à ébullition. Y plonger 500 g de gnocchis 2-3 min : dès qu'ils remontent à la surface, égoutter et réserver.
A45: 2 | B45: Émincer 100 g d'oignon (1 oignon) en petits dés.
A46: 3 | B46: Dans une grande poêle, faire revenir l'oignon avec 120 g de lardons 3 min à feu moyen, sans matière grasse, jusqu'à coloration.
A47: 4 | B47: Verser 200 ml de crème fluide (1 brique) et 40 g de grana padano râpé. Laisser réduire d'un quart, 3-4 min à petits bouillons.
A48: 5 | B48: Ajouter 100 g de pousses d'épinard et les gnocchis. Mélanger, laisser mijoter 4 min : les épinards tombent, la sauce nappe.
A49: 6 | B49: Poivrer généreusement, saler très peu (lardons + fromage salent déjà). Servir la moitié ; l'autre moitié en boîte au frigo, réchauffer 3 min à la poêle avec 1 cs d'eau.
A51: 3. Croque-monsieur express
A52: Source | B52: Marmiton — https://www.marmiton.org/recettes/recette_croque-monsieur-express_19367.aspx
A53: Temps | B53: 25 min (5 + 20)
A54: Ustensiles | B54: Four (ou poêle couverte)
A55: Substitutions | B55: aucune
A56: Ingrédients (2 portions) | B56: Qté | C56: Unité | D56: Équivalent | E56: Produit Chronodrive | F56: Origine
A57: Pain de mie (tranches carrées) | B57: 320 | C57: g | D57: 4 tranches (≈ 40 g/tranche) = 2 croques | E57: Pain de mie | F57: recette
A58: Crème fraîche épaisse | B58: 120 | C58: g | D58: 3 cs | E58: Crème fraîche épaisse 15 % | F58: recette
A59: Gruyère / emmental râpé | B59: 100 | C59: g | D59: 1 grosse poignée | E59: Emmental râpé | F59: recette
A60: Jambon blanc | B60: 140 | C60: g | D60: 2 tranches | E60: Jambon blanc | F60: recette
A61: Sel | B61: 1 | C61: g | D61: 1 pincée | E61: Sel / poivre | F61: placard
A62: Poivre | B62: 1 | C62: g | E62: Sel / poivre | F62: placard
A63: Étape | B63: Consigne (2 portions)
A64: 1 | B64: Préchauffer le four à 210 °C (thermostat 7). Sans four : prévoir une grande poêle avec couvercle.
A65: 2 | B65: Dans un bol, mélanger 120 g de crème fraîche épaisse (6 cs) et 100 g d'emmental râpé. Saler une pincée, poivrer.
A66: 3 | B66: Poser 4 tranches de pain de mie. Étaler le mélange crème-fromage sur chacune. Poser 1 tranche de jambon pliée (140 g au total = 4 tranches) sur chaque tranche de pain.
A67: 4 | B67: Refermer chaque croque avec une 5e-8e tranche de pain, elle aussi tartinée du mélange côté intérieur. Étaler le reste du mélange sur le dessus des 4 croques.
A68: 5 | B68: Four : 20 min à mi-hauteur, jusqu'à ce que le dessus soit doré. Poêle : 1 noix de beurre, feu moyen, couvercle, 4 min par face.
A69: 6 | B69: Manger 2 croques chauds. Les 2 autres : les monter mais ne les cuire que le lendemain midi (8 min à la poêle couverte), c'est bien meilleur que réchauffé.
A71: 4. Hachis parmentier rapide (purée en flocons)
A72: Source | B72: Marmiton — https://www.marmiton.org/recettes/recette_hzchis-parmentier-classique-rapide_87515.aspx
A73: Temps | B73: 30 min (10 + 20)
A74: Ustensiles | B74: Poêle + plat à four (ou poêle couverte)
A75: Substitutions | B75: Lait → eau + crème pour la purée.
A76: Ingrédients (2 portions) | B76: Qté | C76: Unité | D76: Équivalent | E76: Produit Chronodrive | F76: Origine
A77: Steak haché / viande hachée de bœuf | B77: 300 | C77: g | D77: 1 steak + un peu (ou 1 gros) | E77: Haché bovin 15 % | F77: recette
A78: Oignon | B78: 140 | C78: g | D78: ⅔ d'oignon moyen | E78: Oignons jaunes | F78: recette
A79: Tomate | B79: 80 | C79: g | D79: ⅓ de tomate | E79: Pulpe de tomate | F79: recette
A80: Huile d'olive | B80: 20 | C80: ml | D80: 2 cc | E80: Huile de tournesol | F80: recette
A81: Purée en flocons (sèche) | B81: 120 | C81: g | D81: ½ sachet de 125 g | E81: Purée en flocons | F81: recette
A82: Lait | B82: 200 | C82: ml | D82: ½ verre | E82: Eau | F82: recette
A83: Eau | B83: 400 | C83: ml | D83: 1 verre | E83: Eau | F83: recette
A84: Fromage râpé | B84: 50 | C84: g | D84: 2 cs | E84: Emmental râpé | F84: recette
A85: Persillade (ail + persil séchés) | B85: 4 | C85: g | D85: 1 cc | E85: Persillade Ducros ≈ 20 g | F85: placard
A86: Sel | B86: 2 | C86: g | E86: Sel / poivre | F86: placard
A87: Poivre | B87: 1 | C87: g | E87: Sel / poivre | F87: placard
A88: Étape | B88: Consigne (2 portions)
A89: 1 | B89: Éplucher et émincer finement 140 g d'oignon (1 gros). Faire revenir dans 10 ml d'huile à feu moyen 5 min.
A90: 2 | B90: Ajouter 300 g de haché bovin, l'émietter à la spatule, cuire 6-7 min jusqu'à ce qu'il soit bien cuit.
A91: 3 | B91: Ajouter 80 g de pulpe de tomate (ou 1 petite tomate pelée en dés), 4 g de persillade, sel, poivre. Mélanger 2 min. Réserver.
A92: 4 | B92: Purée : porter 400 ml d'eau + 100 ml de crème épaisse (ou 200 ml de lait si tu en as) à ébullition avec 1 pincée de sel. Hors du feu, verser 120 g de flocons de purée (1 sachet de 125 g) en pluie et fouetter 1 min. Ajouter 20 g de beurre.
A93: 5 | B93: Dans un plat allant au four (ou dans la poêle si tu n'as pas de four) : étaler la viande au fond, couvrir de purée, tasser.
A94: 6 | B94: Parsemer de 50 g d'emmental râpé, tasser légèrement.
A95: 7 | B95: Four à 180 °C : 10 min, jusqu'à ce que le fromage gratine. Sans four : couvercle sur la poêle, 5 min à feu doux pour faire fondre.
A96: 8 | B96: Servir la moitié. L'autre moitié en boîte au frigo, réchauffer 3 min au micro-ondes ou 15 min au four.
A98: 5. Pâtes à la « carbonara » à la française
A99: Source | B99: Marmiton — https://www.marmiton.org/recettes/recette_pates-a-la-carbonara_80453.aspx
A100: Temps | B100: 20 min (5 + 15)
A101: Ustensiles | B101: Casserole + poêle
A102: Substitutions | B102: aucune
A103: Ingrédients (2 portions) | B103: Qté | C103: Unité | D103: Équivalent | E103: Produit Chronodrive | F103: Origine
A104: Pâtes sèches (spaghetti, penne…) | B104: 250 | C104: g | D104: 1 grosse poignée | E104: Spaghetti / pâtes courtes | F104: recette
A105: Crème fraîche (liquide ou épaisse) | B105: 250 | C105: ml | D105: ⅔ de brique de 20 cl | E105: Crème liquide UHT | F105: recette
...

Sheet Nutrition
A1: Nutrition — estimation ingrédient par ingrédient, 1 PORTION (Ciqual / étiquettes pour 100 g ou 100 ml). Colonnes bleues = données saisies.
A3: 1. Poulet au curry, lait de coco et noix de cajou + riz
A4: Ingrédient | B4: Qté / portion | C4: Unité | D4: kcal/100 | E4: Prot/100 | F4: Gluc/100 | G4: Lip/100 | H4: kcal | I4: Protéines g | J4: Glucides g | K4: Lipides g | L4: Contrôle
A5: Filet de poulet | B5: 130 | C5: g | D5: 110 | E5: 23 | F5: 0 | G5: 2 | H5: =B5*D5/100 -> 143 | I5: =B5*E5/100 -> 29.9 | J5: =B5*F5/100 -> 0 | K5: =B5*G5/100 -> 2.6
A6: Lait de coco | B6: 100 | C6: ml | D6: 180 | E6: 1.5 | F6: 3 | G6: 18 | H6: =B6*D6/100 -> 180 | I6: =B6*E6/100 -> 1.5 | J6: =B6*F6/100 -> 3 | K6: =B6*G6/100 -> 18
A7: Curry en poudre | B7: 2 | C7: g | D7: 330 | E7: 12 | F7: 40 | G7: 12 | H7: =B7*D7/100 -> 6.6 | I7: =B7*E7/100 -> 0.24 | J7: =B7*F7/100 -> 0.8 | K7: =B7*G7/100 -> 0.24
A8: Sauce soja | B8: 5 | C8: ml | D8: 60 | E8: 6 | F8: 6 | G8: 0 | H8: =B8*D8/100 -> 3 | I8: =B8*E8/100 -> 0.3 | J8: =B8*F8/100 -> 0.3 | K8: =B8*G8/100 -> 0
A9: Noix de cajou grillées salées | B9: 20 | C9: g | D9: 600 | E9: 18 | F9: 22 | G9: 48 | H9: =B9*D9/100 -> 120 | I9: =B9*E9/100 -> 3.6 | J9: =B9*F9/100 -> 4.4 | K9: =B9*G9/100 -> 9.6
A10: Maïzena | B10: 5 | C10: g | D10: 350 | E10: 10 | F10: 72 | G10: 1 | H10: =B10*D10/100 -> 17.5 | I10: =B10*E10/100 -> 0.5 | J10: =B10*F10/100 -> 3.6 | K10: =B10*G10/100 -> 0.05
A11: Huile | B11: 15 | C11: ml | D11: 900 | E11: 0 | F11: 0 | G11: 100 | H11: =B11*D11/100 -> 135 | I11: =B11*E11/100 -> 0 | J11: =B11*F11/100 -> 0 | K11: =B11*G11/100 -> 15
A12: Riz long cru | B12: 80 | C12: g | D12: 350 | E12: 7 | F12: 78 | G12: 0.6 | H12: =B12*D12/100 -> 280 | I12: =B12*E12/100 -> 5.6 | J12: =B12*F12/100 -> 62.4 | K12: =B12*G12/100 -> 0.48
A13: Sel | B13: 1 | C13: g | D13: 0 | E13: 0 | F13: 0 | G13: 0 | H13: =B13*D13/100 -> 0 | I13: =B13*E13/100 -> 0 | J13: =B13*F13/100 -> 0 | K13: =B13*G13/100 -> 0
A14: Poivre | B14: 0.5 | C14: g | D14: 0 | E14: 0 | F14: 0 | G14: 0 | H14: =B14*D14/100 -> 0 | I14: =B14*E14/100 -> 0 | J14: =B14*F14/100 -> 0 | K14: =B14*G14/100 -> 0
A15: TOTAL 1 PORTION | H15: =SUM(H5:H14) -> 885.1 | I15: =SUM(I5:I14) -> 41.64 | J15: =SUM(J5:J14) -> 74.5 | K15: =SUM(K5:K14) -> 45.97 | L15: =IF(H15>=700,"≥ 700 kcal OK","< 700 kcal") -> ≥ 700 kcal OK
A16: x2 (dîner + midi lendemain) | H16: =H15*2 -> 1770.2 | I16: =I15*2 -> 83.28 | J16: =J15*2 -> 149 | K16: =K15*2 -> 91.94
A17: % de l'énergie (P / G / L) | I17: =I15*4/H15 -> 0.18818213 | J17: =J15*4/H15 -> 0.33668512 | K17: =K15*9/H15 -> 0.46743871
A19: 2. Gnocchis aux épinards, crème et lardons
A20: Ingrédient | B20: Qté / portion | C20: Unité | D20: kcal/100 | E20: Prot/100 | F20: Gluc/100 | G20: Lip/100 | H20: kcal | I20: Protéines g | J20: Glucides g | K20: Lipides g | L20: Contrôle
A21: Gnocchis (frais, à poêler ou à pocher) | B21: 250 | C21: g | D21: 150 | E21: 4 | F21: 31 | G21: 1.5 | H21: =B21*D21/100 -> 375 | I21: =B21*E21/100 -> 10 | J21: =B21*F21/100 -> 77.5 | K21: =B21*G21/100 -> 3.75
A22: Oignon | B22: 50 | C22: g | D22: 40 | E22: 1 | F22: 8 | G22: 0 | H22: =B22*D22/100 -> 20 | I22: =B22*E22/100 -> 0.5 | J22: =B22*F22/100 -> 4 | K22: =B22*G22/100 -> 0
A23: Lardons fumés | B23: 60 | C23: g | D23: 300 | E23: 15 | F23: 1 | G23: 27 | H23: =B23*D23/100 -> 180 | I23: =B23*E23/100 -> 9 | J23: =B23*F23/100 -> 0.6 | K23: =B23*G23/100 -> 16.2
A24: Parmesan râpé (ou emmental) | B24: 20 | C24: g | D24: 380 | E24: 28 | F24: 0.5 | G24: 30 | H24: =B24*D24/100 -> 76 | I24: =B24*E24/100 -> 5.6 | J24: =B24*F24/100 -> 0.1 | K24: =B24*G24/100 -> 6
A25: Crème liquide | B25: 100 | C25: ml | D25: 165 | E25: 2.5 | F25: 4 | G25: 15 | H25: =B25*D25/100 -> 165 | I25: =B25*E25/100 -> 2.5 | J25: =B25*F25/100 -> 4 | K25: =B25*G25/100 -> 15
A26: Pousses d'épinards | B26: 50 | C26: g | D26: 20 | E26: 2.5 | F26: 1 | G26: 0.4 | H26: =B26*D26/100 -> 10 | I26: =B26*E26/100 -> 1.25 | J26: =B26*F26/100 -> 0.5 | K26: =B26*G26/100 -> 0.2
A27: Sel | B27: 1 | C27: g | D27: 0 | E27: 0 | F27: 0 | G27: 0 | H27: =B27*D27/100 -> 0 | I27: =B27*E27/100 -> 0 | J27: =B27*F27/100 -> 0 | K27: =B27*G27/100 -> 0
A28: Poivre | B28: 0.5 | C28: g | D28: 0 | E28: 0 | F28: 0 | G28: 0 | H28: =B28*D28/100 -> 0 | I28: =B28*E28/100 -> 0 | J28: =B28*F28/100 -> 0 | K28: =B28*G28/100 -> 0
A29: TOTAL 1 PORTION | H29: =SUM(H21:H28) -> 826 | I29: =SUM(I21:I28) -> 28.85 | J29: =SUM(J21:J28) -> 86.7 | K29: =SUM(K21:K28) -> 41.15 | L29: =IF(H29>=700,"≥ 700 kcal OK","< 700 kcal") -> ≥ 700 kcal OK
A30: x2 (dîner + midi lendemain) | H30: =H29*2 -> 1652 | I30: =I29*2 -> 57.7 | J30: =J29*2 -> 173.4 | K30: =K29*2 -> 82.3
A31: % de l'énergie (P / G / L) | I31: =I29*4/H29 -> 0.13970944 | J31: =J29*4/H29 -> 0.41985472 | K31: =K29*9/H29 -> 0.44836562
A33: 3. Croque-monsieur express
A34: Ingrédient | B34: Qté / portion | C34: Unité | D34: kcal/100 | E34: Prot/100 | F34: Gluc/100 | G34: Lip/100 | H34: kcal | I34: Protéines g | J34: Glucides g | K34: Lipides g | L34: Contrôle
A35: Pain de mie (tranches carrées) | B35: 160 | C35: g | D35: 250 | E35: 9 | F35: 42 | G35: 4 | H35: =B35*D35/100 -> 400 | I35: =B35*E35/100 -> 14.4 | J35: =B35*F35/100 -> 67.2 | K35: =B35*G35/100 -> 6.4
A36: Crème fraîche épaisse | B36: 60 | C36: g | D36: 165 | E36: 2.5 | F36: 4 | G36: 15 | H36: =B36*D36/100 -> 99 | I36: =B36*E36/100 -> 1.5 | J36: =B36*F36/100 -> 2.4 | K36: =B36*G36/100 -> 9
A37: Gruyère / emmental râpé | B37: 50 | C37: g | D37: 380 | E37: 28 | F37: 0.5 | G37: 30 | H37: =B37*D37/100 -> 190 | I37: =B37*E37/100 -> 14 | J37: =B37*F37/100 -> 0.25 | K37: =B37*G37/100 -> 15
A38: Jambon blanc | B38: 70 | C38: g | D38: 110 | E38: 20 | F38: 1 | G38: 3 | H38: =B38*D38/100 -> 77 | I38: =B38*E38/100 -> 14 | J38: =B38*F38/100 -> 0.7 | K38: =B38*G38/100 -> 2.1
A39: Sel | B39: 0.5 | C39: g | D39: 0 | E39: 0 | F39: 0 | G39: 0 | H39: =B39*D39/100 -> 0 | I39: =B39*E39/100 -> 0 | J39: =B39*F39/100 -> 0 | K39: =B39*G39/100 -> 0
A40: Poivre | B40: 0.5 | C40: g | D40: 0 | E40: 0 | F40: 0 | G40: 0 | H40: =B40*D40/100 -> 0 | I40: =B40*E40/100 -> 0 | J40: =B40*F40/100 -> 0 | K40: =B40*G40/100 -> 0
A41: TOTAL 1 PORTION | H41: =SUM(H35:H40) -> 766 | I41: =SUM(I35:I40) -> 43.9 | J41: =SUM(J35:J40) -> 70.55 | K41: =SUM(K35:K40) -> 32.5 | L41: =IF(H41>=700,"≥ 700 kcal OK","< 700 kcal") -> ≥ 700 kcal OK
A42: x2 (dîner + midi lendemain) | H42: =H41*2 -> 1532 | I42: =I41*2 -> 87.8 | J42: =J41*2 -> 141.1 | K42: =K41*2 -> 65
A43: % de l'énergie (P / G / L) | I43: =I41*4/H41 -> 0.22924282 | J43: =J41*4/H41 -> 0.36840731 | K43: =K41*9/H41 -> 0.38185379
A45: 4. Hachis parmentier rapide (purée en flocons)
A46: Ingrédient | B46: Qté / portion | C46: Unité | D46: kcal/100 | E46: Prot/100 | F46: Gluc/100 | G46: Lip/100 | H46: kcal | I46: Protéines g | J46: Glucides g | K46: Lipides g | L46: Contrôle
A47: Steak haché / viande hachée de bœuf | B47: 150 | C47: g | D47: 200 | E47: 18 | F47: 2 | G47: 14 | H47: =B47*D47/100 -> 300 | I47: =B47*E47/100 -> 27 | J47: =B47*F47/100 -> 3 | K47: =B47*G47/100 -> 21
A48: Oignon | B48: 70 | C48: g | D48: 40 | E48: 1 | F48: 8 | G48: 0 | H48: =B48*D48/100 -> 28 | I48: =B48*E48/100 -> 0.7 | J48: =B48*F48/100 -> 5.6 | K48: =B48*G48/100 -> 0
A49: Tomate | B49: 40 | C49: g | D49: 22 | E49: 1 | F49: 4 | G49: 0.2 | H49: =B49*D49/100 -> 8.8 | I49: =B49*E49/100 -> 0.4 | J49: =B49*F49/100 -> 1.6 | K49: =B49*G49/100 -> 0.08
A50: Huile d'olive | B50: 10 | C50: ml | D50: 900 | E50: 0 | F50: 0 | G50: 100 | H50: =B50*D50/100 -> 90 | I50: =B50*E50/100 -> 0 | J50: =B50*F50/100 -> 0 | K50: =B50*G50/100 -> 10
A51: Purée en flocons (sèche) | B51: 60 | C51: g | D51: 350 | E51: 8 | F51: 78 | G51: 1 | H51: =B51*D51/100 -> 210 | I51: =B51*E51/100 -> 4.8 | J51: =B51*F51/100 -> 46.8 | K51: =B51*G51/100 -> 0.6
A52: Lait | B52: 100 | C52: ml | D52: 0 | E52: 0 | F52: 0 | G52: 0 | H52: =B52*D52/100 -> 0 | I52: =B52*E52/100 -> 0 | J52: =B52*F52/100 -> 0 | K52: =B52*G52/100 -> 0
A53: Eau | B53: 200 | C53: ml | D53: 0 | E53: 0 | F53: 0 | G53: 0 | H53: =B53*D53/100 -> 0 | I53: =B53*E53/100 -> 0 | J53: =B53*F53/100 -> 0 | K53: =B53*G53/100 -> 0
A54: Fromage râpé | B54: 25 | C54: g | D54: 380 | E54: 28 | F54: 0.5 | G54: 30 | H54: =B54*D54/100 -> 95 | I54: =B54*E54/100 -> 7 | J54: =B54*F54/100 -> 0.125 | K54: =B54*G54/100 -> 7.5
A55: Persillade (ail + persil séchés) | B55: 2 | C55: g | D55: 280 | E55: 20 | F55: 40 | G55: 5 | H55: =B55*D55/100 -> 5.6 | I55: =B55*E55/100 -> 0.4 | J55: =B55*F55/100 -> 0.8 | K55: =B55*G55/100 -> 0.1
A56: Sel | B56: 1 | C56: g | D56: 0 | E56: 0 | F56: 0 | G56: 0 | H56: =B56*D56/100 -> 0 | I56: =B56*E56/100 -> 0 | J56: =B56*F56/100 -> 0 | K56: =B56*G56/100 -> 0
A57: Poivre | B57: 0.5 | C57: g | D57: 0 | E57: 0 | F57: 0 | G57: 0 | H57: =B57*D57/100 -> 0 | I57: =B57*E57/100 -> 0 | J57: =B57*F57/100 -> 0 | K57: =B57*G57/100 -> 0
A58: TOTAL 1 PORTION | H58: =SUM(H47:H57) -> 737.4 | I58: =SUM(I47:I57) -> 40.3 | J58: =SUM(J47:J57) -> 57.925 | K58: =SUM(K47:K57) -> 39.28 | L58: =IF(H58>=700,"≥ 700 kcal OK","< 700 kcal") -> ≥ 700 kcal OK
A59: x2 (dîner + midi lendemain) | H59: =H58*2 -> 1474.8 | I59: =I58*2 -> 80.6 | J59: =J58*2 -> 115.85 | K59: =K58*2 -> 78.56
A60: % de l'énergie (P / G / L) | I60: =I58*4/H58 -> 0.21860591 | J60: =J58*4/H58 -> 0.3142121 | K60: =K58*9/H58 -> 0.47941416
A62: 5. Pâtes à la « carbonara » à la française
A63: Ingrédient | B63: Qté / portion | C63: Unité | D63: kcal/100 | E63: Prot/100 | F63: Gluc/100 | G63: Lip/100 | H63: kcal | I63: Protéines g | J63: Glucides g | K63: Lipides g | L63: Contrôle
A64: Pâtes sèches (spaghetti, penne…) | B64: 125 | C64: g | D64: 355 | E64: 12 | F64: 72 | G64: 1.5 | H64: =B64*D64/100 -> 443.75 | I64: =B64*E64/100 -> 15 | J64: =B64*F64/100 -> 90 | K64: =B64*G64/100 -> 1.875
A65: Crème fraîche (liquide ou épaisse) | B65: 125 | C65: ml | D65: 165 | E65: 2.5 | F65: 4 | G65: 15 | H65: =B65*D65/100 -> 206.25 | I65: =B65*E65/100 -> 3.125 | J65: =B65*F65/100 -> 5 | K65: =B65*G65/100 -> 18.75
A66: Jaune d'œuf | B66: 18 | C66: g | D66: 145 | E66: 12.5 | F66: 1 | G66: 10 | H66: =B66*D66/100 -> 26.1 | I66: =B66*E66/100 -> 2.25 | J66: =B66*F66/100 -> 0.18 | K66: =B66*G66/100 -> 1.8
A67: Lardons fumés | B67: 60 | C67: g | D67: 300 | E67: 15 | F67: 1 | G67: 27 | H67: =B67*D67/100 -> 180 | I67: =B67*E67/100 -> 9 | J67: =B67*F67/100 -> 0.6 | K67: =B67*G67/100 -> 16.2
A68: Oignon | B68: 50 | C68: g | D68: 40 | E68: 1 | F68: 8 | G68: 0 | H68: =B68*D68/100 -> 20 | I68: =B68*E68/100 -> 0.5 | J68: =B68*F68/100 -> 4 | K68: =B68*G68/100 -> 0
A69: Sel | B69: 1 | C69: g | D69: 0 | E69: 0 | F69: 0 | G69: 0 | H69: =B69*D69/100 -> 0 | I69: =B69*E69/100 -> 0 | J69: =B69*F69/100 -> 0 | K69: =B69*G69/100 -> 0
A70: Poivre | B70: 1 | C70: g | D70: 0 | E70: 0 | F70: 0 | G70: 0 | H70: =B70*D70/100 -> 0 | I70: =B70*E70/100 -> 0 | J70: =B70*F70/100 -> 0 | K70: =B70*G70/100 -> 0
A71: TOTAL 1 PORTION | H71: =SUM(H64:H70) -> 876.1 | I71: =SUM(I64:I70) -> 29.875 | J71: =SUM(J64:J70) -> 99.78 | K71: =SUM(K64:K70) -> 38.625 | L71: =IF(H71>=700,"≥ 700 kcal OK","< 700 kcal") -> ≥ 700 kcal OK
A72: x2 (dîner + midi lendemain) | H72: =H71*2 -> 1752.2 | I72: =I71*2 -> 59.75 | J72: =J71*2 -> 199.56 | K72: =K71*2 -> 77.25
A73: % de l'énergie (P / G / L) | I73: =I71*4/H71 -> 0.13639995 | J73: =J71*4/H71 -> 0.45556443 | K73: =K71*9/H71 -> 0.3967869
A75: 6. Poulet à la crème et aux champignons + spaghetti
A76: Ingrédient | B76: Qté / portion | C76: Unité | D76: kcal/100 | E76: Prot/100 | F76: Gluc/100 | G76: Lip/100 | H76: kcal | I76: Protéines g | J76: Glucides g | K76: Lipides g | L76: Contrôle
A77: Cuisse de poulet (ou 150 g de filet) | B77: 150 | C77: g | D77: 110 | E77: 23 | F77: 0 | G77: 2 | H77: =B77*D77/100 -> 165 | I77: =B77*E77/100 -> 34.5 | J77: =B77*F77/100 -> 0 | K77: =B77*G77/100 -> 3
A78: Oignon | B78: 30 | C78: g | D78: 40 | E78: 1 | F78: 8 | G78: 0 | H78: =B78*D78/100 -> 12 | I78: =B78*E78/100 -> 0.3 | J78: =B78*F78/100 -> 2.4 | K78: =B78*G78/100 -> 0
A79: Ail | B79: 3 | C79: g | D79: 330 | E79: 17 | F79: 70 | G79: 1 | H79: =B79*D79/100 -> 9.9 | I79: =B79*E79/100 -> 0.51 | J79: =B79*F79/100 -> 2.1 | K79: =B79*G79/100 -> 0.03
A80: Crème fraîche épaisse | B80: 60 | C80: g | D80: 165 | E80: 2.5 | F80: 4 | G80: 15 | H80: =B80*D80/100 -> 99 | I80: =B80*E80/100 -> 1.5 | J80: =B80*F80/100 -> 2.4 | K80: =B80*G80/100 -> 9
A81: Champignons de Paris en boîte (égouttés, jus gardé) | B81: 60 | C81: g | D81: 20 | E81: 2 | F81: 1 | G81: 0.3 | H81: =B81*D81/100 -> 12 | I81: =B81*E81/100 -> 1.2 | J81: =B81*F81/100 -> 0.6 | K81: =B81*G81/100 -> 0.18
A82: Farine | B82: 5 | C82: g | D82: 350 | E82: 10 | F82: 72 | G82: 1 | H82: =B82*D82/100 -> 17.5 | I82: =B82*E82/100 -> 0.5 | J82: =B82*F82/100 -> 3.6 | K82: =B82*G82/100 -> 0.05
A83: Fond de volaille déshydraté (ou ½ cube) | B83: 5 | C83: g | D83: 150 | E83: 10 | F83: 15 | G83: 8 | H83: =B83*D83/100 -> 7.5 | I83: =B83*E83/100 -> 0.5 | J83: =B83*F83/100 -> 0.75 | K83: =B83*G83/100 -> 0.4
A84: Persil (frais ou séché) | B84: 1 | C84: g | D84: 280 | E84: 20 | F84: 40 | G84: 5 | H84: =B84*D84/100 -> 2.8 | I84: =B84*E84/100 -> 0.2 | J84: =B84*F84/100 -> 0.4 | K84: =B84*G84/100 -> 0.05
A85: Eau | B85: 100 | C85: ml | D85: 0 | E85: 0 | F85: 0 | G85: 0 | H85: =B85*D85/100 -> 0 | I85: =B85*E85/100 -> 0 | J85: =B85*F85/100 -> 0 | K85: =B85*G85/100 -> 0
A86: Huile | B86: 10 | C86: ml | D86: 900 | E86: 0 | F86: 0 | G86: 100 | H86: =B86*D86/100 -> 90 | I86: =B86*E86/100 -> 0 | J86: =B86*F86/100 -> 0 | K86: =B86*G86/100 -> 10
A87: Spaghetti (remplace les tagliatelles) | B87: 100 | C87: g | D87: 355 | E87: 12 | F87: 72 | G87: 1.5 | H87: =B87*D87/100 -> 355 | I87: =B87*E87/100 -> 12 | J87: =B87*F87/100 -> 72 | K87: =B87*G87/100 -> 1.5
A88: Sel | B88: 1 | C88: g | D88: 0 | E88: 0 | F88: 0 | G88: 0 | H88: =B88*D88/100 -> 0 | I88: =B88*E88/100 -> 0 | J88: =B88*F88/100 -> 0 | K88: =B88*G88/100 -> 0
A89: Poivre | B89: 0.5 | C89: g | D89: 0 | E89: 0 | F89: 0 | G89: 0 | H89: =B89*D89/100 -> 0 | I89: =B89*E89/100 -> 0 | J89: =B89*F89/100 -> 0 | K89: =B89*G89/100 -> 0
A90: TOTAL 1 PORTION | H90: =SUM(H77:H89) -> 770.7 | I90: =SUM(I77:I89) -> 51.21 | J90: =SUM(J77:J89) -> 84.25 | K90: =SUM(K77:K89) -> 24.21 | L90: =IF(H90>=700,"≥ 700 kcal OK","< 700 kcal") -> ≥ 700 kcal OK
A91: x2 (dîner + midi lendemain) | H91: =H90*2 -> 1541.4 | I91: =I90*2 -> 102.42 | J91: =J90*2 -> 168.5 | K91: =K90*2 -> 48.42
A92: % de l'énergie (P / G / L) | I92: =I90*4/H90 -> 0.26578435 | J92: =J90*4/H90 -> 0.43726482 | K92: =K90*9/H90 -> 0.28271701
A94: 7. Quesadillas chorizo-emmental & avocat (version éco)
A95: Ingrédient | B95: Qté / portion | C95: Unité | D95: kcal/100 | E95: Prot/100 | F95: Gluc/100 | G95: Lip/100 | H95: kcal | I95: Protéines g | J95: Glucides g | K95: Lipides g | L95: Contrôle
A96: Dés de chorizo | B96: 50 | C96: g | D96: 450 | E96: 22 | F96: 2 | G96: 40 | H96: =B96*D96/100 -> 225 | I96: =B96*E96/100 -> 11 | J96: =B96*F96/100 -> 1 | K96: =B96*G96/100 -> 20
A97: Tortillas de blé | B97: 80 | C97: g | D97: 300 | E97: 8 | F97: 50 | G97: 7 | H97: =B97*D97/100 -> 240 | I97: =B97*E97/100 -> 6.4 | J97: =B97*F97/100 -> 40 | K97: =B97*G97/100 -> 5.6
A98: Emmental râpé (remplace cheddar + gouda) | B98: 60 | C98: g | D98: 380 | E98: 28 | F98: 0.5 | G98: 30 | H98: =B98*D98/100 -> 228 | I98: =B98*E98/100 -> 16.8 | J98: =B98*F98/100 -> 0.3 | K98: =B98*G98/100 -> 18
A99: Avocat | B99: 75 | C99: g | D99: 160 | E99: 2 | F99: 2 | G99: 15 | H99: =B99*D99/100 -> 120 | I99: =B99*E99/100 -> 1.5 | J99: =B99*F99/100 -> 1.5 | K99: =B99*G99/100 -> 11.25
A100: Crème fraîche épaisse | B100: 50 | C100: g | D100: 165 | E100: 2.5 | F100: 4 | G100: 15 | H100: =B100*D100/100 -> 82.5 | I100: =B100*E100/100 -> 1.25 | J100: =B100*F100/100 -> 2 | K100: =B100*G100/100 -> 7.5
A101: Huile d'olive | B101: 7 | C101: ml | D101: 900 | E101: 0 | F101: 0 | G101: 100 | H101: =B101*D101/100 -> 63 | I101: =B101*E101/100 -> 0 | J101: =B101*F101/100 -> 0 | K101: =B101*G101/100 -> 7
A102: Vinaigre (balsamique blanc, riz ou cidre) | B102: 2 | C102: ml | D102: 20 | E102: 0 | F102: 1 | G102: 0 | H102: =B102*D102/100 -> 0.4 | I102: =B102*E102/100 -> 0 | J102: =B102*F102/100 -> 0.02 | K102: =B102*G102/100 -> 0
A103: Sel | B103: 0.5 | C103: g | D103: 0 | E103: 0 | F103: 0 | G103: 0 | H103: =B103*D103/100 -> 0 | I103: =B103*E103/100 -> 0 | J103: =B103*F103/100 -> 0 | K103: =B103*G103/100 -> 0
A104: Poivre | B104: 0.5 | C104: g | D104: 0 | E104: 0 | F104: 0 | G104: 0 | H104: =B104*D104/100 -> 0 | I104: =B104*E104/100 -> 0 | J104: =B104*F104/100 -> 0 | K104: =B104*G104/100 -> 0
A105: TOTAL 1 PORTION | H105: =SUM(H96:H104) -> 958.9 | I105: =SUM(I96:I104) -> 36.95 | J105: =SUM(J96:J104) -> 44.82 | K105: =SUM(K96:K104) -> 69.35 | L105: =IF(H105>=700,"≥ 700 kcal OK","< 700 kcal") -> ≥ 700 kcal OK
A106: x2 (dîner + midi lendemain) | H106: =H105*2 -> 1917.8 | I106: =I105*2 -> 73.9 | J106: =J105*2 -> 89.64 | K106: =K105*2 -> 138.7
A107: % de l'énergie (P / G / L) | I107: =I105*4/H105 -> 0.15413495 | J107: =J105*4/H105 -> 0.18696423 | K107: =K105*9/H105 -> 0.65090208
...

Sheet Recettes v3 (1 pers)
A1: Fiches 1 personne (x2 pour dîner + midi) — substitutions éco appliquées
A3: # recette | B3: Recette | C3: Ingrédient | D3: Qté / portion | E3: Unité | F3: Équivalent | G3: Produit Chronodrive | H3: Origine | I3: Note de substitution
A4: 1 | B4: Poulet au curry, lait de coco et noix de cajou + riz | C4: Filet de poulet | D4: 130 | E4: g | F4: 1 filet | G4: Filets de poulet | H4: recette
A5: 1 | B5: Poulet au curry, lait de coco et noix de cajou + riz | C5: Lait de coco | D5: 100 | E5: ml | F5: ½ brique de 20 cl | G5: Lait de coco | H5: recette
A6: 1 | B6: Poulet au curry, lait de coco et noix de cajou + riz | C6: Curry en poudre | D6: 2 | E6: g | F6: 1 cc rase | G6: Curry en poudre Ducros 47 g | H6: placard
A7: 1 | B7: Poulet au curry, lait de coco et noix de cajou + riz | C7: Sauce soja | D7: 5 | E7: ml | F7: 1 cc | G7: Sauce soja | H7: recette
A8: 1 | B8: Poulet au curry, lait de coco et noix de cajou + riz | C8: Noix de cajou grillées salées | D8: 20 | E8: g | F8: 1 petite poignée | G8: Noix de cajou | H8: recette
A9: 1 | B9: Poulet au curry, lait de coco et noix de cajou + riz | C9: Maïzena | D9: 5 | E9: g | F9: 1 cc bombée | G9: Farine T45 | H9: placard
A10: 1 | B10: Poulet au curry, lait de coco et noix de cajou + riz | C10: Huile | D10: 15 | E10: ml | F10: 1 cs | G10: Huile de tournesol | H10: placard
A11: 1 | B11: Poulet au curry, lait de coco et noix de cajou + riz | C11: Riz long cru | D11: 80 | E11: g | F11: ½ verre | G11: Riz long | H11: ajout
A12: 1 | B12: Poulet au curry, lait de coco et noix de cajou + riz | C12: Sel | D12: 1 | E12: g | F12: 1 pincée | G12: Sel / poivre | H12: placard
A13: 1 | B13: Poulet au curry, lait de coco et noix de cajou + riz | C13: Poivre | D13: 0.5 | E13: g | F13: 1 tour de moulin | G13: Sel / poivre | H13: placard
A14: 2 | B14: Gnocchis aux épinards, crème et lardons | C14: Gnocchis (frais, à poêler ou à pocher) | D14: 250 | E14: g | F14: ½ paquet de 500 g | G14: Gnocchis à poêler | H14: recette
A15: 2 | B15: Gnocchis aux épinards, crème et lardons | C15: Oignon | D15: 50 | E15: g | F15: ½ oignon moyen | G15: Oignons jaunes | H15: recette
... A20: 2 | B20: Gnocchis aux épinards, crème et lardons | C20: Sel | D20: 1 | E20: g | F20: 1 pincée | G20: Sel / poivre | H20: placard
A21: 2 | B21: Gnocchis aux épinards, crème et lardons | C21: Poivre | D21: 0.5 | E21: g | G21: Sel / poivre | H21: placard
A22: 3 | B22: Croque-monsieur express | C22: Pain de mie (tranches carrées) | D22: 160 | E22: g | F22: 4 tranches (≈ 40 g/tranche) = 2 croques | G22: Pain de mie | H22: recette
A23: 3 | B23: Croque-monsieur express | C23: Crème fraîche épaisse | D23: 60 | E23: g | F23: 3 cs | G23: Crème fraîche épaisse 15 % | H23: recette
A24: 3 | B24: Croque-monsieur express | C24: Gruyère / emmental râpé | D24: 50 | E24: g | F24: 1 grosse poignée | G24: Emmental râpé | H24: recette
A25: 3 | B25: Croque-monsieur express | C25: Jambon blanc | D25: 70 | E25: g | F25: 2 tranches | G25: Jambon blanc | H25: recette
A26: 3 | B26: Croque-monsieur express | C26: Sel | D26: 0.5 | E26: g | F26: 1 pincée | G26: Sel / poivre | H26: placard
A27: 3 | B27: Croque-monsieur express | C27: Poivre | D27: 0.5 | E27: g | G27: Sel / poivre | H27: placard
A28: 4 | B28: Hachis parmentier rapide (purée en flocons) | C28: Steak haché / viande hachée de bœuf | D28: 150 | E28: g | F28: 1 steak + un peu (ou 1 gros) | G28: Haché bovin 15 % | H28: recette | I28: Lait → eau + crème pour la purée.
A29: 4 | B29: Hachis parmentier rapide (purée en flocons) | C29: Oignon | D29: 70 | E29: g | F29: ⅔ d'oignon moyen | G29: Oignons jaunes | H29: recette | I29: Lait → eau + crème pour la purée.
A30: 4 | B30: Hachis parmentier rapide (purée en flocons) | C30: Tomate | D30: 40 | E30: g | F30: ⅓ de tomate | G30: Pulpe de tomate | H30: recette | I30: Lait → eau + crème pour la purée.
A31: 4 | B31: Hachis parmentier rapide (purée en flocons) | C31: Huile d'olive | D31: 10 | E31: ml | F31: 2 cc | G31: Huile de tournesol | H31: recette | I31: Lait → eau + crème pour la purée.
A32: 4 | B32: Hachis parmentier rapide (purée en flocons) | C32: Purée en flocons (sèche) | D32: 60 | E32: g | F32: ½ sachet de 125 g | G32: Purée en flocons | H32: recette | I32: Lait → eau + crème pour la purée.
A33: 4 | B33: Hachis parmentier rapide (purée en flocons) | C33: Lait | D33: 100 | E33: ml | F33: ½ verre | G33: Eau | H33: recette | I33: Lait → eau + crème pour la purée.
A34: 4 | B34: Hachis parmentier rapide (purée en flocons) | C34: Eau | D34: 200 | E34: ml | F34: 1 verre | G34: Eau | H34: recette | I34: Lait → eau + crème pour la purée.
A35: 4 | B35: Hachis parmentier rapide (purée en flocons) | C35: Fromage râpé | D35: 25 | E35: g | F35: 2 cs | G35: Emmental râpé | H35: recette | I35: Lait → eau + crème pour la purée.
A36: 4 | B36: Hachis parmentier rapide (purée en flocons) | C36: Persillade (ail + persil séchés) | D36: 2 | E36: g | F36: 1 cc | G36: Persillade Ducros ≈ 20 g | H36: placard | I36: Lait → eau + crème pour la purée.
A37: 4 | B37: Hachis parmentier rapide (purée en flocons) | C37: Sel | D37: 1 | E37: g | G37: Sel / poivre | H37: placard | I37: Lait → eau + crème pour la purée.
A38: 4 | B38: Hachis parmentier rapide (purée en flocons) | C38: Poivre | D38: 0.5 | E38: g | G38: Sel / poivre | H38: placard | I38: Lait → eau + crème pour la purée.
A39: 5 | B39: Pâtes à la « carbonara » à la française | C39: Pâtes sèches (spaghetti, penne…) | D39: 125 | E39: g | F39: 1 grosse poignée | G39: Spaghetti / pâtes courtes | H39: recette
A40: 5 | B40: Pâtes à la « carbonara » à la française | C40: Crème fraîche (liquide ou épaisse) | D40: 125 | E40: ml | F40: ⅔ de brique de 20 cl | G40: Crème liquide UHT | H40: recette
A41: 5 | B41: Pâtes à la « carbonara » à la française | C41: Jaune d'œuf | D41: 18 | E41: g | F41: 1 jaune (¾ dans la source) | G41: Œufs | H41: recette
A42: 5 | B42: Pâtes à la « carbonara » à la française | C42: Lardons fumés | D42: 60 | E42: g | F42: ½ sachet de 100 g + un peu | G42: Lardons fumés | H42: recette
A43: 5 | B43: Pâtes à la « carbonara » à la française | C43: Oignon | D43: 50 | E43: g | F43: ½ oignon | G43: Oignons jaunes | H43: recette
A44: 5 | B44: Pâtes à la « carbonara » à la française | C44: Sel | D44: 1 | E44: g | F44: 1 pincée | G44: Sel / poivre | H44: placard
A45: 5 | B45: Pâtes à la « carbonara » à la française | C45: Poivre | D45: 1 | E45: g | F45: généreux | G45: Sel / poivre | H45: placard
A46: 6 | B46: Poulet à la crème et aux champignons + spaghetti | C46: Cuisse de poulet (ou 150 g de filet) | D46: 150 | E46: g | F46: 1 cuisse désossée ou 1 filet | G46: Filets de poulet | H46: recette | I46: Tagliatelles → spaghetti (même rôle, 3 x moins cher). Filet ou cuisse : filet.
A47: 6 | B47: Poulet à la crème et aux champignons + spaghetti | C47: Oignon | D47: 30 | E47: g | F47: ⅓ d'oignon | G47: Oignons jaunes | H47: recette | I47: Tagliatelles → spaghetti (même rôle, 3 x moins cher). Filet ou cuisse : filet.
A48: 6 | B48: Poulet à la crème et aux champignons + spaghetti | C48: Ail | D48: 3 | E48: g | F48: ½ gousse ou ½ cc d'ail semoule | G48: Ail semoule | H48: recette | I48: Tagliatelles → spaghetti (même rôle, 3 x moins cher). Filet ou cuisse : filet.
A49: 6 | B49: Poulet à la crème et aux champignons + spaghetti | C49: Crème fraîche épaisse | D49: 60 | E49: g | F49: 3 cs | G49: Crème fraîche épaisse 15 % | H49: recette | I49: Tagliatelles → spaghetti (même rôle, 3 x moins cher). Filet ou cuisse : filet.
A50: 6 | B50: Poulet à la crème et aux champignons + spaghetti | C50: Champignons de Paris en boîte (égouttés, jus gardé) | D50: 60 | E50: g | F50: ¼ de petite boîte | G50: Champignons de Paris | H50: recette | I50: Tagliatelles → spaghetti (même rôle, 3 x moins cher). Filet ou cuisse : filet.
A51: 6 | B51: Poulet à la crème et aux champignons + spaghetti | C51: Farine | D51: 5 | E51: g | F51: 1 cc | G51: Farine T45 | H51: placard | I51: Tagliatelles → spaghetti (même rôle, 3 x moins cher). Filet ou cuisse : filet.
A52: 6 | B52: Poulet à la crème et aux champignons + spaghetti | C52: Fond de volaille déshydraté (ou ½ cube) | D52: 5 | E52: g | F52: 1 cc / ½ cube | G52: Bouillon cube | H52: recette | I52: Tagliatelles → spaghetti (même rôle, 3 x moins cher). Filet ou cuisse : filet.
A53: 6 | B53: Poulet à la crème et aux champignons + spaghetti | C53: Persil (frais ou séché) | D53: 1 | E53: g | F53: 1 pincée | G53: Persillade Ducros ≈ 20 g | H53: placard | I53: Tagliatelles → spaghetti (même rôle, 3 x moins cher). Filet ou cuisse : filet.
A54: 6 | B54: Poulet à la crème et aux champignons + spaghetti | C54: Eau | D54: 100 | E54: ml | F54: ½ verre | G54: Eau | H54: recette | I54: Tagliatelles → spaghetti (même rôle, 3 x moins cher). Filet ou cuisse : filet.
A55: 6 | B55: Poulet à la crème et aux champignons + spaghetti | C55: Huile | D55: 10 | E55: ml | F55: 2 cc | G55: Huile de tournesol | H55: placard | I55: Tagliatelles → spaghetti (même rôle, 3 x moins cher). Filet ou cuisse : filet.
A56: 6 | B56: Poulet à la crème et aux champignons + spaghetti | C56: Spaghetti (remplace les tagliatelles) | D56: 100 | E56: g | F56: 1 nid et demi | G56: Spaghetti / pâtes courtes | H56: ajout | I56: Tagliatelles → spaghetti (même rôle, 3 x moins cher). Filet ou cuisse : filet.
A57: 6 | B57: Poulet à la crème et aux champignons + spaghetti | C57: Sel | D57: 1 | E57: g | G57: Sel / poivre | H57: placard | I57: Tagliatelles → spaghetti (même rôle, 3 x moins cher). Filet ou cuisse : filet.
A58: 6 | B58: Poulet à la crème et aux champignons + spaghetti | C58: Poivre | D58: 0.5 | E58: g | G58: Sel / poivre | H58: placard | I58: Tagliatelles → spaghetti (même rôle, 3 x moins cher). Filet ou cuisse : filet.
A59: 7 | B59: Quesadillas chorizo-emmental & avocat (version éco) | C59: Dés de chorizo | D59: 50 | E59: g | F59: ½ sachet | G59: Chorizo doux | H59: recette | I59: Version éco : cheddar + gouda → 60 g d'emmental ; ½ avocat (75 g) ; cuisson poêle.
A60: 7 | B60: Quesadillas chorizo-emmental & avocat (version éco) | C60: Tortillas de blé | D60: 80 | E60: g | F60: 2 tortillas | G60: Tortillas | H60: recette | I60: Version éco : cheddar + gouda → 60 g d'emmental ; ½ avocat (75 g) ; cuisson poêle.
A61: 7 | B61: Quesadillas chorizo-emmental & avocat (version éco) | C61: Emmental râpé (remplace cheddar + gouda) | D61: 60 | E61: g | F61: 1 poignée | G61: Emmental râpé | H61: recette | I61: Version éco : cheddar + gouda → 60 g d'emmental ; ½ avocat (75 g) ; cuisson poêle.
A62: 7 | B62: Quesadillas chorizo-emmental & avocat (version éco) | C62: Avocat | D62: 75 | E62: g | F62: ½ avocat | G62: Avocat | H62: recette | I62: Version éco : cheddar + gouda → 60 g d'emmental ; ½ avocat (75 g) ; cuisson poêle.
A63: 7 | B63: Quesadillas chorizo-emmental & avocat (version éco) | C63: Crème fraîche épaisse | D63: 50 | E63: g | F63: ½ pot / 2 cs | G63: Crème fraîche épaisse 15 % | H63: recette | I63: Version éco : cheddar + gouda → 60 g d'emmental ; ½ avocat (75 g) ; cuisson poêle.
A64: 7 | B64: Quesadillas chorizo-emmental & avocat (version éco) | C64: Huile d'olive | D64: 7 | E64: ml | F64: ½ cs | G64: Huile de tournesol | H64: placard | I64: Version éco : cheddar + gouda → 60 g d'emmental ; ½ avocat (75 g) ; cuisson poêle.
A65: 7 | B65: Quesadillas chorizo-emmental & avocat (version éco) | C65: Vinaigre (balsamique blanc, riz ou cidre) | D65: 2 | E65: ml | F65: ½ cc | G65: Vinaigre de cidre | H65: placard | I65: Version éco : cheddar + gouda → 60 g d'emmental ; ½ avocat (75 g) ; cuisson poêle.
A66: 7 | B66: Quesadillas chorizo-emmental & avocat (version éco) | C66: Sel | D66: 0.5 | E66: g | G66: Sel / poivre | H66: placard | I66: Version éco : cheddar + gouda → 60 g d'emmental ; ½ avocat (75 g) ; cuisson poêle.
A67: 7 | B67: Quesadillas chorizo-emmental & avocat (version éco) | C67: Poivre | D67: 0.5 | E67: g | G67: Sel / poivre | H67: placard | I67: Version éco : cheddar + gouda → 60 g d'emmental ; ½ avocat (75 g) ; cuisson poêle.
A68: 8 | B68: Pâtes au pesto rosso et au poulet (+ parmesan) | C68: Farfalle (ou autres pâtes courtes) | D68: 125 | E68: g | F68: 1 grosse poignée | G68: Spaghetti / pâtes courtes | H68: recette
A69: 8 | B69: Pâtes au pesto rosso et au poulet (+ parmesan) | C69: Filet de poulet | D69: 100 | E69: g | F69: ¾ de filet (source : 75 à 150 g pour 4) | G69: Filets de poulet | H69: recette
A70: 8 | B70: Pâtes au pesto rosso et au poulet (+ parmesan) | C70: Crème fraîche | D70: 15 | E70: ml | F70: 1 cs | G70: Crème fraîche épaisse 15 % | H70: recette
A71: 8 | B71: Pâtes au pesto rosso et au poulet (+ parmesan) | C71: Pesto rosso (pot) | D71: 50 | E71: ml | F71: 3 cs bombées | G71: Pesto rosso | H71: recette
A72: 8 | B72: Pâtes au pesto rosso et au poulet (+ parmesan) | C72: Parmesan râpé | D72: 30 | E72: g | F72: 3 cs (ton ajout) | G72: Grana padano râpé | H72: ajout
A73: 8 | B73: Pâtes au pesto rosso et au poulet (+ parmesan) | C73: Huile | D73: 5 | E73: ml | F73: 1 cc | G73: Huile de tournesol | H73: placard
A74: 8 | B74: Pâtes au pesto rosso et au poulet (+ parmesan) | C74: Sel | D74: 1 | E74: g | F74: eau des pâtes | G74: Sel / poivre | H74: placard
A75: 8 | B75: Pâtes au pesto rosso et au poulet (+ parmesan) | C75: Poivre | D75: 0.5 | E75: g | G75: Sel / poivre | H75: placard
A76: 9 | B76: Riz au chorizo et poivrons (façon paella express) | C76: Chorizo (doux ou fort) | D76: 60 | E76: g | F76: ⅓ d'un petit chorizo / 6 rondelles | G76: Chorizo doux | H76: recette | I76: Olives supprimées (facultatives, 2 € le bocal).
A77: 9 | B77: Riz au chorizo et poivrons (façon paella express) | C77: Poivron vert | D77: 25 | E77: g | F77: ⅛ de poivron | G77: Poivron rouge | H77: recette | I77: Olives supprimées (facultatives, 2 € le bocal).
A78: 9 | B78: Riz au chorizo et poivrons (façon paella express) | C78: Poivron rouge | D78: 25 | E78: g | F78: ⅛ de poivron | G78: Poivron rouge | H78: recette | I78: Olives supprimées (facultatives, 2 € le bocal).
A79: 9 | B79: Riz au chorizo et poivrons (façon paella express) | C79: Oignon | D79: 40 | E79: g | F79: ⅓ d'oignon | G79: Oignons jaunes | H79: recette | I79: Olives supprimées (facultatives, 2 € le bocal).
A80: 9 | B80: Riz au chorizo et poivrons (façon paella express) | C80: Riz long cru | D80: 90 | E80: g | F80: ½ verre bombé | G80: Riz long | H80: recette | I80: Olives supprimées (facultatives, 2 € le bocal).
A81: 9 | B81: Riz au chorizo et poivrons (façon paella express) | C81: Cube de bouillon de volaille | D81: 3 | E81: g | F81: ¼ de cube | G81: Bouillon cube | H81: recette | I81: Olives supprimées (facultatives, 2 € le bocal).
A82: 9 | B82: Riz au chorizo et poivrons (façon paella express) | C82: Eau | D82: 200 | E82: ml | F82: 1 verre | G82: Eau | H82: recette | I82: Olives supprimées (facultatives, 2 € le bocal).
A83: 9 | B83: Riz au chorizo et poivrons (façon paella express) | C83: Huile | D83: 10 | E83: ml | F83: 2 cc | G83: Huile de tournesol | H83: placard | I83: Olives supprimées (facultatives, 2 € le bocal).
A84: 9 | B84: Riz au chorizo et poivrons (façon paella express) | C84: Sel | D84: 0.5 | E84: g | F84: léger, le cube sale déjà | G84: Sel / poivre | H84: placard | I84: Olives supprimées (facultatives, 2 € le bocal).
A85: 9 | B85: Riz au chorizo et poivrons (façon paella express) | C85: Poivre | D85: 0.5 | E85: g | G85: Sel / poivre | H85: placard | I85: Olives supprimées (facultatives, 2 € le bocal).
A86: 10 | B86: Côtes d'échine à la moutarde et à la crème + spaghetti | C86: Côtes d'échine de porc sans os | D86: 150 | E86: g | F86: 1 côte de 150 g | G86: Côtes d'échine de porc sans os | H86: recette | I86: Filet mignon (18,30 €/kg) → côtes d'échine sans os (11,63 €/kg), même sauce moutarde-crème ; tagliatelles → spaghetti.
A87: 10 | B87: Côtes d'échine à la moutarde et à la crème + spaghetti | C87: Moutarde de Dijon | D87: 15 | E87: g | F87: 1 cs | G87: Moutarde de Dijon | H87: recette | I87: Filet mignon (18,30 €/kg) → côtes d'échine sans os (11,63 €/kg), même sauce moutarde-crème ; tagliatelles → spaghetti.
A88: 10 | B88: Côtes d'échine à la moutarde et à la crème + spaghetti | C88: Crème fraîche épaisse | D88: 40 | E88: g | F88: 2 cs bombées (source : 1 cs) | G88: Crème fraîche épaisse 15 % | H88: recette | I88: Filet mignon (18,30 €/kg) → côtes d'échine sans os (11,63 €/kg), même sauce moutarde-crème ; tagliatelles → spaghetti.
A89: 10 | B89: Côtes d'échine à la moutarde et à la crème + spaghetti | C89: Beurre (ou margarine) | D89: 10 | E89: g | F89: 1 noix | G89: Beurre | H89: recette | I89: Filet mignon (18,30 €/kg) → côtes d'échine sans os (11,63 €/kg), même sauce moutarde-crème ; tagliatelles → spaghetti.
A90: 10 | B90: Côtes d'échine à la moutarde et à la crème + spaghetti | C90: Spaghetti (remplace les tagliatelles) | D90: 100 | E90: g | F90: source : « avec des tagliatelles fraîches » | G90: Spaghetti / pâtes courtes | H90: ajout | I90: Filet mignon (18,30 €/kg) → côtes d'échine sans os (11,63 €/kg), même sauce moutarde-crème ; tagliatelles → spaghetti.
A91: 10 | B91: Côtes d'échine à la moutarde et à la crème + spaghetti | C91: Poivre | D91: 1 | E91: g | G91: Sel / poivre | H91: placard | I91: Filet mignon (18,30 €/kg) → côtes d'échine sans os (11,63 €/kg), même sauce moutarde-crème ; tagliatelles → spaghetti.
A92: 10 | B92: Côtes d'échine à la moutarde et à la crème + spaghetti | C92: Sel | D92: 0 | E92: g | F92: aucun : la moutarde sale déjà (source) | G92: Sel / poivre | H92: placard | I92: Filet mignon (18,30 €/kg) → côtes d'échine sans os (11,63 €/kg), même sauce moutarde-crème ; tagliatelles → spaghetti.
A93: 11 | B93: Raviolis frais à la sauce tomate-crème (poivron, épices) | C93: Raviolis frais (3 fromages ou ricotta-épinards) | D93: 250 | E93: g | F93: 1 barquette de 250 g | G93: Ravioli frais aux fromages | H93: recette | I93: Coulis/pulpe → pulpe concassée Auchan.
A94: 11 | B94: Raviolis frais à la sauce tomate-crème (poivron, épices) | C94: Oignon (ou échalote) | D94: 30 | E94: g | F94: ⅓ d'oignon | G94: Oignons jaunes | H94: recette | I94: Coulis/pulpe → pulpe concassée Auchan.
A95: 11 | B95: Raviolis frais à la sauce tomate-crème (poivron, épices) | C95: Huile d'olive | D95: 10 | E95: ml | F95: 2 cc | G95: Huile de tournesol | H95: recette | I95: Coulis/pulpe → pulpe concassée Auchan.
A96: 11 | B96: Raviolis frais à la sauce tomate-crème (poivron, épices) | C96: Poivron vert (ou rouge) | D96: 40 | E96: g | F96: ¼ de poivron | G96: Poivron rouge | H96: recette | I96: Coulis/pulpe → pulpe concassée Auchan.
A97: 11 | B97: Raviolis frais à la sauce tomate-crème (poivron, épices) | C97: Pulpe de tomate (boîte) | D97: 100 | E97: g | F97: ¼ de boîte de 400 g | G97: Pulpe de tomate | H97: recette | I97: Coulis/pulpe → pulpe concassée Auchan.
A98: 11 | B98: Raviolis frais à la sauce tomate-crème (poivron, épices) | C98: Ail | D98: 3 | E98: g | F98: ½ gousse ou ½ cc d'ail semoule | G98: Ail semoule | H98: recette | I98: Coulis/pulpe → pulpe concassée Auchan.
A99: 11 | B99: Raviolis frais à la sauce tomate-crème (poivron, épices) | C99: Persil (frais ou séché) | D99: 1 | E99: g | F99: 1 pincée | G99: Persillade Ducros ≈ 20 g | H99: placard | I99: Coulis/pulpe → pulpe concassée Auchan.
A100: 11 | B100: Raviolis frais à la sauce tomate-crème (poivron, épices) | C100: Paprika doux | D100: 1 | E100: g | F100: ¼ cc | G100: Paprika doux Ducros 40 g | H100: placard | I100: Coulis/pulpe → pulpe concassée Auchan.
A101: 11 | B101: Raviolis frais à la sauce tomate-crème (poivron, épices) | C101: Coriandre en poudre | D101: 1 | E101: g | F101: ¼ cc | G101: Coriandre moulue Ducros ≈ 30 g | H101: placard | I101: Coulis/pulpe → pulpe concassée Auchan.
A102: 11 | B102: Raviolis frais à la sauce tomate-crème (poivron, épices) | C102: Basilic (frais ou séché) | D102: 1 | E102: g | F102: ¼ cc | G102: Basilic séché Ducros ≈ 12 g | H102: placard | I102: Coulis/pulpe → pulpe concassée Auchan.
A103: 11 | B103: Raviolis frais à la sauce tomate-crème (poivron, épices) | C103: Thym | D103: 0.5 | E103: g | F103: 1 pincée | G103: Thym Ducros ≈ 15 g | H103: placard | I103: Coulis/pulpe → pulpe concassée Auchan.
... A107: 11 | B107: Raviolis frais à la sauce tomate-crème (poivron, épices) | C107: Parmesan râpé (finition) | D107: 15 | E107: g | F107: 1 cs bombée | G107: Grana padano râpé | H107: recette | I107: Coulis/pulpe → pulpe concassée Auchan.
A108: 11 | B108: Raviolis frais à la sauce tomate-crème (poivron, épices) | C108: Sel | D108: 1 | E108: g | G108: Sel / poivre | H108: placard | I108: Coulis/pulpe → pulpe concassée Auchan.
...

Sheet S1
A1: Semaine 1 — total 47.66 € (marge 7.34 €) — retrait Chronodrive le dimanche
A3: PLANNING
A4: Jour | B4: Midi | C4: Soir | D4: kcal / portion (soir) | E4: À cuisiner ce jour | F4: Note | G4: Macros / portion (P / G / L en g)
A5: Dimanche (retrait) | B5: libre / reste | C5: Pizza : Auchan Pizza royale jambon-fromage-olives 400 g | D5: ≈ 900 | E5: Four 12 min | F5: Retrait du drive le matin
A6: Lundi | B6: Portion 2 de la pizza / reste | C6: 10. Côtes d'échine à la moutarde et à la crème + spaghetti | D6: =ROUND(Nutrition!H148,0) -> 864 | E6: 30 min (5 + 25) — 2 portions | F6: Filet mignon (18,30 €/kg) → côtes d'échine sans os (11,63 €/kg), même sauce moutarde-crème ; tagliatelles → spaghetti. | G6: =ROUND(Nutrition!I148,0)&" / "&ROUND(Nutrition!J148,0)&" / "&ROUND(Nutrition!K148,0) -> 39 / 75 / 44
A7: Mardi | B7: Portion 2 de : Côtes d'échine à la moutarde et à la crème + spaghetti | C7: 16. « Couscous » étudiant poulet, carottes, pois chiches | D7: =ROUND(Nutrition!H253,0) -> 838 | E7: 30 min (annoncé) — mijotage 20-25 min — 2 portions | F7: Semoule montée à 100 g pour passer 700 kcal ; ras el hanout du placard. | G7: =ROUND(Nutrition!I253,0)&" / "&ROUND(Nutrition!J253,0)&" / "&ROUND(Nutrition!K253,0) -> 50 / 105 / 23
A8: Mercredi | B8: Portion 2 de : « Couscous » étudiant poulet, carottes, pois chiches | C8: 5. Pâtes à la « carbonara » à la française | D8: =ROUND(Nutrition!H71,0) -> 876 | E8: 20 min (5 + 15) — 2 portions | G8: =ROUND(Nutrition!I71,0)&" / "&ROUND(Nutrition!J71,0)&" / "&ROUND(Nutrition!K71,0) -> 30 / 100 / 39
A9: Jeudi | B9: Portion 2 de : Pâtes à la « carbonara » à la française | C9: 9. Riz au chorizo et poivrons (façon paella express) | D9: =ROUND(Nutrition!H135,0) -> 708 | E9: 30 min (10 + 20) — 2 portions | F9: Olives supprimées (facultatives, 2 € le bocal). | G9: =ROUND(Nutrition!I135,0)&" / "&ROUND(Nutrition!J135,0)&" / "&ROUND(Nutrition!K135,0) -> 21 / 77 / 35
A10: Vendredi | B10: Portion 2 de : Riz au chorizo et poivrons (façon paella express) | C10: 15. Saucisses-lentilles express (lentilles en conserve) | D10: =ROUND(Nutrition!H235,0) -> 780 | E10: 15 min — 2 portions | G10: =ROUND(Nutrition!I235,0)&" / "&ROUND(Nutrition!J235,0)&" / "&ROUND(Nutrition!K235,0) -> 38 / 36 / 52
A11: Samedi | B11: Portion 2 de : Saucisses-lentilles express (lentilles en conserve) | C11: ½ Auchan Poulet basquaise et riz 900 g | D11: ≈ 900-1 000 | E11: Poêle / micro-ondes | F11: Sachet coupé en 2 (congélateur)
A12: Dimanche midi | B12: ½ Auchan Poulet basquaise et riz 900 g | C12: → pizza de la semaine suivante
A14: LISTE DE COURSES CHRONODRIVE — formats entiers
A15: Produit exact (Chronodrive) | B15: Rayon | C15: Qté à acheter | D15: Prix unitaire € | E15: Total € | F15: Besoin semaine (2 portions x 5) | G15: Acheté | H15: Unité | I15: Reste après la semaine | J15: dont gâchis estimé € | K15: dont stock (se garde) € | L15: Sert aux recettes
A16: Auchan chorizo doux 24 tranches 120 g | B16: Charcuterie | C16: 1 | D16: 1.85 | E16: =C16*D16 -> 1.85 | F16: 120 | G16: 120 | H16: g | I16: 0 | J16: 0 | K16: 0 | L16: 9
A17: Auchan lardons fumés 2 x 100 g | B17: Charcuterie | C17: 1 | D17: 2.09 | E17: =C17*D17 -> 2.09 | F17: 200 | G17: 200 | H17: g | I17: 0 | J17: 0 | K17: 0 | L17: 5, 15
A18: Auchan Knacks 10 pièces 350 g | B18: Charcuterie | C18: 1 | D18: 1.75 | E18: =C18*D18 -> 1.75 | F18: 280 | G18: 350 | H18: g | I18: 70 | J18: 0.175 | K18: 0.175 | L18: 15
A19: Auchan crème épaisse légère 15 % 20 cl | B19: Crèmerie | C19: 1 | D19: 0.75 | E19: =C19*D19 -> 0.75 | F19: 80 | G19: 200 | H19: ml | I19: 120 | J19: 0.135 | K19: 0.315 | L19: 10
A20: Auchan Essentiel crème fluide légère 15 % 20 cl | B20: Crèmerie | C20: 2 | D20: 0.69 | E20: =C20*D20 -> 1.38 | F20: 250 | G20: 400 | H20: ml | I20: 150 | J20: 0 | K20: 0.5175 | L20: 5
A21: Auchan œufs plein air x6 | B21: Crèmerie | C21: 1 | D21: 1.69 | E21: =C21*D21 -> 1.69 | F21: 36 | G21: 330 | H21: g | I21: 294 | J21: 0 | K21: 1.5056364 | L21: 5
A22: Carottes zéro résidu 750 g | B22: Fruits & légumes | C22: 1 | D22: 2.29 | E22: =C22*D22 -> 2.29 | F22: 300 | G22: 750 | H22: g | I22: 450 | J22: 0.687 | K22: 0.687 | L22: 15, 16
A23: Oignon jaune 1 kg | B23: Fruits & légumes | C23: 1 | D23: 2.69 | E23: =C23*D23 -> 2.69 | F23: 320 | G23: 1000 | H23: g | I23: 680 | J23: 0.36584 | K23: 1.46336 | L23: 5, 9, 15, 16
A24: Poivron rouge 1 pièce | B24: Fruits & légumes | C24: 1 | D24: 0.99 | E24: =C24*D24 -> 0.99 | F24: 100 | G24: 150 | H24: g | I24: 50 | J24: 0.33 | K24: 0 | L24: 9
A25: Porc côtes échines sans os LR 2 pièces 300 g | B25: Viande | C25: 1 | D25: 3.49 | E25: =C25*D25 -> 3.49 | F25: 300 | G25: 300 | H25: g | I25: 0 | J25: 0 | K25: 0 | L25: 10
A26: Auchan filets de poulet blanc 260 g | B26: Viande | C26: 1 | D26: 3.89 | E26: =C26*D26 -> 3.89 | F26: 240 | G26: 260 | H26: g | I26: 20 | J26: 0.29923077 | K26: 0 | L26: 16
A27: Auchan lentilles préparées 530 g | B27: Épicerie | C27: 1 | D27: 1.29 | E27: =C27*D27 -> 1.29 | F27: 400 | G27: 530 | H27: g | I27: 130 | J27: 0.094924528 | K27: 0.22149057 | L27: 15
... A31: Auchan spaghetti 500 g | B31: Épicerie | C31: 1 | D31: 0.75 | E31: =C31*D31 -> 0.75 | F31: 450 | G31: 500 | H31: g | I31: 50 | J31: 0 | K31: 0.075 | L31: 5, 10
A32: TOTAL COURSES RECETTES | E32: =SUM(E16:E31) -> 28.03 | J32: =SUM(J16:J31) -> 2.1451274 | K32: =SUM(K16:K31) -> 6.7834284
A33: Auchan Poulet basquaise et riz 900 g | B33: Surgelé (week-end) | C33: 1 | D33: 4.75 | E33: =C33*D33 -> 4.75 | L33: Samedi soir + dimanche midi
A34: Auchan Pizza royale jambon-fromage-olives 400 g | B34: Surgelé (week-end) | C34: 1 | D34: 2.15 | E34: =C34*D34 -> 2.15 | L34: Dimanche soir
A35: TOTAL PANIER (recettes + week-end) | E35: =E32+E33+E34 -> 34.93
A37: PLACARD / BASES utilisées cette semaine — comptées au PRIX PLEIN du format
A38: Produit exact | B38: Rayon | C38: Qté | D38: Prix format € | E38: Total € | F38: Qté utilisée cette semaine | G38: Contenu format | H38: Unité | I38: Reste (stock) | K38: Valeur du reste € | L38: Sert aux recettes
A39: Beurre | B39: Placard | C39: 1 | D39: 2.45 | E39: =C39*D39 -> 2.45 | F39: 30 | G39: 250 | H39: g | I39: 220 | K39: =D39*I39/G39 -> 2.156 | L39: 10, 15
A40: Bouillon cube | B40: Placard | C40: 1 | D40: 1.79 | E40: =C40*D40 -> 1.79 | F40: 16 | G40: 180 | H40: g | I40: 164 | K40: =D40*I40/G40 -> 1.6308889 | L40: 9, 16
A41: Huile de tournesol | B41: Placard | C41: 1 | D41: 2.15 | E41: =C41*D41 -> 2.15 | F41: 50 | G41: 1000 | H41: ml | I41: 950 | K41: =D41*I41/G41 -> 2.0425 | L41: 9, 16
A42: Moutarde de Dijon | B42: Placard | C42: 1 | D42: 1.85 | E42: =C42*D42 -> 1.85 | F42: 30 | G42: 430 | H42: g | I42: 400 | K42: =D42*I42/G42 -> 1.7209302 | L42: 10
A43: Ras el hanout La Conquête des Saveurs 240 g | B43: Placard | C43: 1 | D43: 3.99 | E43: =C43*D43 -> 3.99 | F43: 14 | G43: 240 | H43: g | I43: 226 | K43: =D43*I43/G43 -> 3.75725 | L43: 16
A44: Sel / poivre | B44: Placard | C44: 1 | D44: 0.5 | E44: =C44*D44 -> 0.5 | F44: 12 | G44: 100 | H44: g | I44: 88 | K44: =D44*I44/G44 -> 0.44 | L44: 5, 9, 10, 15, 16
A45: TOTAL placard (prix plein) | E45: =SUM(E39:E44) -> 12.73
A47: BUDGET
A48: Panier recettes + week-end | E48: =E35 -> 34.93
A49: + placard / bases au prix plein | E49: =E45 -> 12.73
A50: TOTAL PANIER CHRONODRIVE DE LA SEMAINE | E50: =E35+E45 -> 47.66
A51: Budget max | E51: 55
A52: Marge | E52: =E51-E50 -> 7.34
A53: Gâchis estimé (périssable non consommé) | E53: =J32 -> 2.1451274
A54: Gâchis en % du panier | E54: =J32/E35 -> 0.061412178
A55: Reste non périssable (stock) | E55: =K32 -> 6.7834284
A56: Coût par portion (14 repas) | E56: =(E35+E45)/14 -> 3.4042857
A57: Si le placard est déjà plein chez toi, le panier réel redescend à | E57: =E35 -> 34.93
A60: ÉTAPES DES 5 RECETTES DE LA SEMAINE (2 portions chacune)
A61: Lundi — 10. Côtes d'échine à la moutarde et à la crème + spaghetti — 30 min (5 + 25)
A62: Ingrédients (2 portions) | B62: Côtes d'échine de porc sans os : 300 g ; Moutarde de Dijon : 30 g ; Crème fraîche épaisse : 80 g ; Beurre (ou margarine) : 20 g ; Spaghetti (remplace les tagliatelles) : 200 g ; Poivre : 2 g ; Sel : 0 g
A63: Étape 1 | B63: Sortir 2 côtes d'échine sans os (300 g). Les saler légèrement (la moutarde sale déjà) et poivrer.
A64: Étape 2 | B64: Faire fondre 20 g de beurre dans une poêle à feu moyen-vif. Saisir les côtes 3 min par face jusqu'à belle coloration.
A65: Étape 3 | B65: Tartiner chaque côte de 15 g de moutarde de Dijon (1 cs chacune). Baisser à feu doux, déglacer le fond avec 15 g de crème épaisse (1 cs).
A66: Étape 4 | B66: Couvrir et laisser cuire 12-15 min à feu doux (l'échine doit être cuite à cœur mais rester juteuse).
A67: Étape 5 | B67: Pendant ce temps, cuire 200 g de spaghetti dans l'eau bouillante salée.
A68: Étape 6 | B68: Retirer les côtes sur une assiette. Dans la poêle, ajouter 65 g de crème épaisse (le reste des 80 g), gratter les sucs, mélanger avec la moutarde 1 min pour obtenir une sauce lisse. Rallonger avec 1-2 cs d'eau des pâtes si trop épais. Poivrer.
A69: Étape 7 | B69: Servir 1 côte avec la moitié des spaghetti nappés de sauce. L'autre côte + pâtes + sauce en boîte au frigo ; réchauffer à couvert 3 min à la poêle avec 1 cs d'eau.
A71: Mardi — 16. « Couscous » étudiant poulet, carottes, pois chiches — 30 min (annoncé) — mijotage 20-25 min
A72: Ingrédients (2 portions) | B72: Blanc de poulet : 240 g ; Carotte : 200 g ; Pois chiches cuits (boîte, égouttés) : 200 g ; Oignon : 60 g ; Ras el hanout (ou curry + cumin) : 14 g ; Cube de bouillon de légumes : 10 g ; Eau (pour le mijotage) : 200 ml ; Huile d'olive : 30 ml ; Semoule de couscous (sèche) : 200 g ; Eau bouillante (pour la semoule) : 240 ml ; Poivre : 1 g ; Sel : 1 g
A73: Étape 1 | B73: Couper 240 g de filet de poulet en gros dés. Émincer 60 g d'oignon. Éplucher 200 g de carotte, couper en rondelles puis en quarts.
A74: Étape 2 | B74: Chauffer 30 ml d'huile dans une poêle avec couvercle. Faire revenir l'oignon 3 min, ajouter le poulet et 14 g de ras el hanout (1 cs rase). Faire dorer le poulet sur chaque face, 4-5 min.
A75: Étape 3 | B75: Ajouter les carottes, mélanger. Émietter 1 cube de bouillon (10 g), verser 200 ml d'eau.
A76: Étape 4 | B76: Couvrir, laisser mijoter à feu doux jusqu'à ce que les carottes soient tendres : 20-25 min. Rajouter un peu d'eau si ça accroche. Saler, poivrer.
A77: Étape 5 | B77: Ajouter 200 g de pois chiches égouttés (¾ de boîte), poursuivre 3-5 min à découvert.
A78: Étape 6 | B78: Semoule : dans un saladier, verser 200 g de semoule, 1 pincée de sel, 10 ml d'huile. Verser 240 ml d'eau bouillante, couvrir d'une assiette 5 min, puis égrainer à la fourchette.
A79: Étape 7 | B79: Servir la moitié de la garniture et de sa sauce sur la moitié de la semoule. L'autre moitié en boîte (semoule et garniture ensemble) ; réchauffer 3 min au micro-ondes avec 2 cs d'eau.
A81: Mercredi — 5. Pâtes à la « carbonara » à la française — 20 min (5 + 15)
A82: Ingrédients (2 portions) | B82: Pâtes sèches (spaghetti, penne…) : 250 g ; Crème fraîche (liquide ou épaisse) : 250 ml ; Jaune d'œuf : 36 g ; Lardons fumés : 120 g ; Oignon : 100 g ; Sel : 2 g ; Poivre : 2 g
A83: Étape 1 | B83: Porter une grande casserole d'eau salée à ébullition. Cuire 250 g de spaghetti (temps du paquet, al dente).
A84: Étape 2 | B84: Émincer 100 g d'oignon (1 oignon). Le faire revenir 4 min dans une poêle sans matière grasse à feu moyen. Quand il est doré, ajouter 120 g de lardons et cuire 4 min jusqu'à coloration.
A85: Étape 3 | B85: Dans un bol, mélanger 250 ml de crème fluide, 2 jaunes d'œufs (garder les blancs pour une omelette), 1 pincée de sel et beaucoup de poivre.
A86: Étape 4 | B86: Retirer la poêle du feu et verser les lardons-oignon dans le bol de crème. Mélanger.
A87: Étape 5 | B87: Égoutter les pâtes (garder 1 louche d'eau de cuisson). Les remettre dans la casserole hors du feu, verser la crème aux lardons, mélanger 1 min. Si trop épais, détendre avec un peu d'eau de cuisson. Ne pas faire bouillir (les jaunes cuiraient).
A88: Étape 6 | B88: Servir la moitié aussitôt. L'autre moitié en boîte au frigo ; réchauffer à la poêle 3 min avec 2 cs d'eau.
A90: Jeudi — 9. Riz au chorizo et poivrons (façon paella express) — 30 min (10 + 20)
A91: Ingrédients (2 portions) | B91: Chorizo (doux ou fort) : 120 g ; Poivron vert : 50 g ; Poivron rouge : 50 g ; Oignon : 80 g ; Riz long cru : 180 g ; Cube de bouillon de volaille : 6 g ; Eau : 400 ml ; Huile : 20 ml ; Sel : 1 g ; Poivre : 1 g
A92: Étape 1 | B92: Couper 120 g de chorizo en rondelles (ou 120 g de tranches). Les faire frire 2 min dans une sauteuse sans matière grasse. Réserver le chorizo, garder le gras rouge dans la sauteuse.
A93: Étape 2 | B93: Émincer 80 g d'oignon et 100 g de poivron (rouge et/ou vert) en lanières.
A94: Étape 3 | B94: Dans le gras du chorizo + 20 ml d'huile, faire dorer l'oignon 3 min, puis ajouter les poivrons et faire revenir 5 min.
A95: Étape 4 | B95: Émietter ½ cube de bouillon (5 g), verser 400 ml d'eau. Porter à ébullition, verser 180 g de riz long. Mélanger, saler légèrement, poivrer.
A96: Étape 5 | B96: Couvrir, cuire à feu doux ≈ 15 min jusqu'à absorption complète (remuer une fois à mi-cuisson).
A97: Étape 6 | B97: 5 min avant la fin, remettre le chorizo (et son huile). Mélanger, laisser finir à couvert.
A98: Étape 7 | B98: Servir la moitié. L'autre moitié en boîte au frigo ; réchauffer 3 min à la poêle avec 2 cs d'eau.
A100: Vendredi — 15. Saucisses-lentilles express (lentilles en conserve) — 15 min
A101: Ingrédients (2 portions) | B101: Saucisses (Knacki ; ou 2 chipolatas) : 280 g ; Lentilles en conserve (poids égoutté) : 400 g ; Oignon : 80 g ; Carotte : 100 g ; Lardons fumés (ou allumettes de bacon) : 80 g ; Beurre ou huile : 10 g ; Poivre : 1 g ; Sel : 1 g
A102: Étape 1 | B102: Cuire 8 Knacki : plonger 3 min dans une casserole d'eau frémissante (ne pas faire bouillir, elles éclatent). Égoutter, réserver.
A103: Étape 2 | B103: Émincer 80 g d'oignon. Éplucher et couper 100 g de carotte en fines rondelles.
A104: Étape 3 | B104: Dans la casserole rincée, chauffer 10 g de beurre ou 10 ml d'huile. Faire suer l'oignon 3 min.
A105: Étape 4 | B105: Ajouter les carottes et 80 g de lardons. Faire revenir 5-10 min selon la tendreté voulue des carottes.
A106: Étape 5 | B106: Verser 400 g de lentilles en conserve (égouttées, en gardant 4 cs de jus). Laisser mijoter 5 min doucement en remuant.
A107: Étape 6 | B107: Ajouter les Knacki (entières ou en tronçons), réchauffer 2 min. Poivrer, saler seulement si besoin.
A108: Étape 7 | B108: Servir la moitié. L'autre moitié en boîte au frigo ; réchauffer 3 min à la casserole ou au micro-ondes.

Sheet S2
A1: Semaine 2 — total 45.09 € (marge 9.91 €) — retrait Chronodrive le dimanche
A3: PLANNING
A4: Jour | B4: Midi | C4: Soir | D4: kcal / portion (soir) | E4: À cuisiner ce jour | F4: Note | G4: Macros / portion (P / G / L en g)
A5: Dimanche (retrait) | B5: libre / reste | C5: Pizza : Ristorante 4 fromages 340 g | D5: ≈ 900 | E5: Four 12 min | F5: Retrait du drive le matin
A6: Lundi | B6: Portion 2 de la pizza / reste | C6: 3. Croque-monsieur express | D6: =ROUND(Nutrition!H41,0) -> 766 | E6: 25 min (5 + 20) — 2 portions | G6: =ROUND(Nutrition!I41,0)&" / "&ROUND(Nutrition!J41,0)&" / "&ROUND(Nutrition!K41,0) -> 44 / 71 / 33
A7: Mardi | B7: Portion 2 de : Croque-monsieur express | C7: 2. Gnocchis aux épinards, crème et lardons | D7: =ROUND(Nutrition!H29,0) -> 826 | E7: 12 min (5 + 7) — 2 portions | G7: =ROUND(Nutrition!I29,0)&" / "&ROUND(Nutrition!J29,0)&" / "&ROUND(Nutrition!K29,0) -> 29 / 87 / 41
A8: Mercredi | B8: Portion 2 de : Gnocchis aux épinards, crème et lardons | C8: 22. Frittata d'été aux courgettes et mozzarella filante (+ pain) | D8: =ROUND(Nutrition!H356,0) -> 716 | E8: 20 min — 2 portions | F8: Tomate → tomates cerises 125 g ; pain = ½ mini-baguette précuite x2 (80 g). | G8: =ROUND(Nutrition!I356,0)&" / "&ROUND(Nutrition!J356,0)&" / "&ROUND(Nutrition!K356,0) -> 36 / 45 / 42
A9: Jeudi | B9: Portion 2 de : Frittata d'été aux courgettes et mozzarella filante (+ pain) | C9: 21. Risotto de coquillettes au jambon, petits pois et parmesan | D9: =ROUND(Nutrition!H339,0) -> 738 | E9: 25 min (5 + 20) — 2 portions | F9: Mascarpone → crème épaisse. | G9: =ROUND(Nutrition!I339,0)&" / "&ROUND(Nutrition!J339,0)&" / "&ROUND(Nutrition!K339,0) -> 39 / 103 / 18
A10: Vendredi | B10: Portion 2 de : Risotto de coquillettes au jambon, petits pois et parmesan | C10: 24. Pâtes sauce tomate-basilic, mozzarella fondante & parmesan | D10: =ROUND(Nutrition!H382,0) -> 807 | E10: 15 min (3 + 12) — 2 portions | F10: Sans oignon ni tomates cerises (ton choix) ; sauce du commerce mijotée 5 min ; 1 boule de mozzarella pour 2 portions ; parmesan ajouté. | G10: =ROUND(Nutrition!I382,0)&" / "&ROUND(Nutrition!J382,0)&" / "&ROUND(Nutrition!K382,0) -> 34 / 105 / 26
A11: Samedi | B11: Portion 2 de : Pâtes sauce tomate-basilic, mozzarella fondante & parmesan | C11: ½ Auchan Penne poulet-champignons 900 g | D11: ≈ 900-1 000 | E11: Poêle / micro-ondes | F11: Sachet coupé en 2 (congélateur)
A12: Dimanche midi | B12: ½ Auchan Penne poulet-champignons 900 g | C12: → pizza de la semaine suivante
A14: LISTE DE COURSES CHRONODRIVE — formats entiers
A15: Produit exact (Chronodrive) | B15: Rayon | C15: Qté à acheter | D15: Prix unitaire € | E15: Total € | F15: Besoin semaine (2 portions x 5) | G15: Acheté | H15: Unité | I15: Reste après la semaine | J15: dont gâchis estimé € | K15: dont stock (se garde) € | L15: Sert aux recettes
A16: Auchan Jambon de Paris 8 tranches 280 g | B16: Charcuterie | C16: 1 | D16: 3.25 | E16: =C16*D16 -> 3.25 | F16: 280 | G16: 280 | H16: g | I16: 0 | J16: 0 | K16: 0 | L16: 3, 21
A17: Auchan lardons fumés 2 x 100 g | B17: Charcuterie | C17: 1 | D17: 2.09 | E17: =C17*D17 -> 2.09 | F17: 120 | G17: 200 | H17: g | I17: 80 | J17: 0.418 | K17: 0.418 | L17: 2
A18: Auchan crème épaisse légère 15 % 20 cl | B18: Crèmerie | C18: 1 | D18: 0.75 | E18: =C18*D18 -> 0.75 | F18: 170 | G18: 200 | H18: ml | I18: 30 | J18: 0.03375 | K18: 0.07875 | L18: 3, 21
A19: Auchan Essentiel crème fluide légère 15 % 20 cl | B19: Crèmerie | C19: 1 | D19: 0.69 | E19: =C19*D19 -> 0.69 | F19: 200 | G19: 200 | H19: ml | I19: 0 | J19: 0 | K19: 0 | L19: 2
A20: Auchan emmental râpé 3 x 70 g | B20: Crèmerie | C20: 1 | D20: 2.09 | E20: =C20*D20 -> 2.09 | F20: 140 | G20: 210 | H20: g | I20: 70 | J20: 0.13933333 | K20: 0.55733333 | L20: 2, 3
A21: Auchan Tavola grana padano râpé 60 g | B21: Crèmerie | C21: 1 | D21: 1.19 | E21: =C21*D21 -> 1.19 | F21: 60 | G21: 60 | H21: g | I21: 0 | J21: 0 | K21: 0 | L21: 21, 24
A22: Casa Azzurra mozzarella 125 g | B22: Crèmerie | C22: 2 | D22: 1.15 | E22: =C22*D22 -> 2.3 | F22: 248 | G22: 250 | H22: g | I22: 2 | J22: 0.0184 | K22: 0 | L22: 22, 24
A23: Auchan œufs plein air x6 | B23: Crèmerie | C23: 1 | D23: 1.69 | E23: =C23*D23 -> 1.69 | F23: 220 | G23: 330 | H23: g | I23: 110 | J23: 0 | K23: 0.56333333 | L23: 22
A24: Auchan gnocchi de pomme de terre à poêler 500 g | B24: Frais | C24: 1 | D24: 1.85 | E24: =C24*D24 -> 1.85 | F24: 500 | G24: 500 | H24: g | I24: 0 | J24: 0 | K24: 0 | L24: 2
A25: Citron jaune 1 pièce | B25: Fruits & légumes | C25: 1 | D25: 0.85 | E25: =C25*D25 -> 0.85 | F25: 50 | G25: 100 | H25: g | I25: 50 | J25: 0.2125 | K25: 0.2125 | L25: 22
A26: Courgette 1 pièce | B26: Fruits & légumes | C26: 2 | D26: 0.99 | E26: =C26*D26 -> 1.98 | F26: 350 | G26: 500 | H26: g | I26: 150 | J26: 0.594 | K26: 0 | L26: 22
A27: Oignon jaune 1 kg | B27: Fruits & légumes | C27: 1 | D27: 2.69 | E27: =C27*D27 -> 2.69 | F27: 200 | G27: 1000 | H27: g | I27: 800 | J27: 0.4304 | K27: 1.7216 | L27: 2, 21
... A34: Auchan spaghetti 500 g | B34: Épicerie | C34: 1 | D34: 0.75 | E34: =C34*D34 -> 0.75 | F34: 250 | G34: 500 | H34: g | I34: 250 | J34: 0 | K34: 0.375 | L34: 24
A35: TOTAL COURSES RECETTES | E35: =SUM(E16:E34) -> 29.93 | J35: =SUM(J16:J34) -> 2.2685738 | K35: =SUM(K16:K34) -> 5.1177186
A36: Auchan Penne poulet-champignons 900 g | B36: Surgelé (week-end) | C36: 1 | D36: 4.65 | E36: =C36*D36 -> 4.65 | L36: Samedi soir + dimanche midi
A37: Ristorante 4 fromages 340 g | B37: Surgelé (week-end) | C37: 1 | D37: 2.89 | E37: =C37*D37 -> 2.89 | L37: Dimanche soir
A38: TOTAL PANIER (recettes + week-end) | E38: =E35+E36+E37 -> 37.47
A40: PLACARD / BASES utilisées cette semaine — comptées au PRIX PLEIN du format
A41: Produit exact | B41: Rayon | C41: Qté | D41: Prix format € | E41: Total € | F41: Qté utilisée cette semaine | G41: Contenu format | H41: Unité | I41: Reste (stock) | K41: Valeur du reste € | L41: Sert aux recettes
A42: Ail semoule | B42: Placard | C42: 1 | D42: 1.29 | E42: =C42*D42 -> 1.29 | F42: 12 | G42: 55 | H42: g | I42: 43 | K42: =D42*I42/G42 -> 1.0085455 | L42: 21, 22
A43: Bouillon cube | B43: Placard | C43: 1 | D43: 1.79 | E43: =C43*D43 -> 1.79 | F43: 10 | G43: 180 | H43: g | I43: 170 | K43: =D43*I43/G43 -> 1.6905556 | L43: 21
A44: Huile de tournesol | B44: Placard | C44: 1 | D44: 2.15 | E44: =C44*D44 -> 2.15 | F44: 50 | G44: 1000 | H44: ml | I44: 950 | K44: =D44*I44/G44 -> 2.0425 | L44: 21, 22, 24
A45: Origan Ducros 12 g | B45: Placard | C45: 1 | D45: 1.89 | E45: =C45*D45 -> 1.89 | F45: 1 | G45: 12 | H45: g | I45: 11 | K45: =D45*I45/G45 -> 1.7325 | L45: 22
A46: Sel / poivre | B46: Placard | C46: 1 | D46: 0.5 | E46: =C46*D46 -> 0.5 | F46: 11 | G46: 100 | H46: g | I46: 89 | K46: =D46*I46/G46 -> 0.445 | L46: 2, 3, 21, 22, 24
A47: TOTAL placard (prix plein) | E47: =SUM(E42:E46) -> 7.62
A49: BUDGET
A50: Panier recettes + week-end | E50: =E38 -> 37.47
A51: + placard / bases au prix plein | E51: =E47 -> 7.62
A52: TOTAL PANIER CHRONODRIVE DE LA SEMAINE | E52: =E38+E47 -> 45.09
A53: Budget max | E53: 55
A54: Marge | E54: =E53-E52 -> 9.91
A55: Gâchis estimé (périssable non consommé) | E55: =J35 -> 2.2685738
A56: Gâchis en % du panier | E56: =J35/E38 -> 0.060543735
A57: Reste non périssable (stock) | E57: =K35 -> 5.1177186
A58: Coût par portion (14 repas) | E58: =(E38+E47)/14 -> 3.2207143
A59: Si le placard est déjà plein chez toi, le panier réel redescend à | E59: =E38 -> 37.47
A62: ÉTAPES DES 5 RECETTES DE LA SEMAINE (2 portions chacune)
A63: Lundi — 3. Croque-monsieur express — 25 min (5 + 20)
A64: Ingrédients (2 portions) | B64: Pain de mie (tranches carrées) : 320 g ; Crème fraîche épaisse : 120 g ; Gruyère / emmental râpé : 100 g ; Jambon blanc : 140 g ; Sel : 1 g ; Poivre : 1 g
A65: Étape 1 | B65: Préchauffer le four à 210 °C (thermostat 7). Sans four : prévoir une grande poêle avec couvercle.
A66: Étape 2 | B66: Dans un bol, mélanger 120 g de crème fraîche épaisse (6 cs) et 100 g d'emmental râpé. Saler une pincée, poivrer.
A67: Étape 3 | B67: Poser 4 tranches de pain de mie. Étaler le mélange crème-fromage sur chacune. Poser 1 tranche de jambon pliée (140 g au total = 4 tranches) sur chaque tranche de pain.
A68: Étape 4 | B68: Refermer chaque croque avec une 5e-8e tranche de pain, elle aussi tartinée du mélange côté intérieur. Étaler le reste du mélange sur le dessus des 4 croques.
A69: Étape 5 | B69: Four : 20 min à mi-hauteur, jusqu'à ce que le dessus soit doré. Poêle : 1 noix de beurre, feu moyen, couvercle, 4 min par face.
A70: Étape 6 | B70: Manger 2 croques chauds. Les 2 autres : les monter mais ne les cuire que le lendemain midi (8 min à la poêle couverte), c'est bien meilleur que réchauffé.
A72: Mardi — 2. Gnocchis aux épinards, crème et lardons — 12 min (5 + 7)
A73: Ingrédients (2 portions) | B73: Gnocchis (frais, à poêler ou à pocher) : 500 g ; Oignon : 100 g ; Lardons fumés : 120 g ; Parmesan râpé (ou emmental) : 40 g ; Crème liquide : 200 ml ; Pousses d'épinards : 100 g ; Sel : 2 g ; Poivre : 1 g
A74: Étape 1 | B74: Porter une casserole d'eau salée à ébullition. Y plonger 500 g de gnocchis 2-3 min : dès qu'ils remontent à la surface, égoutter et réserver.
A75: Étape 2 | B75: Émincer 100 g d'oignon (1 oignon) en petits dés.
A76: Étape 3 | B76: Dans une grande poêle, faire revenir l'oignon avec 120 g de lardons 3 min à feu moyen, sans matière grasse, jusqu'à coloration.
A77: Étape 4 | B77: Verser 200 ml de crème fluide (1 brique) et 40 g de grana padano râpé. Laisser réduire d'un quart, 3-4 min à petits bouillons.
A78: Étape 5 | B78: Ajouter 100 g de pousses d'épinard et les gnocchis. Mélanger, laisser mijoter 4 min : les épinards tombent, la sauce nappe.
A79: Étape 6 | B79: Poivrer généreusement, saler très peu (lardons + fromage salent déjà). Servir la moitié ; l'autre moitié en boîte au frigo, réchauffer 3 min à la poêle avec 1 cs d'eau.
A81: Mercredi — 22. Frittata d'été aux courgettes et mozzarella filante (+ pain) — 20 min
A82: Ingrédients (2 portions) | B82: Œufs : 220 g ; Courgette : 350 g ; Tomates cerises : 250 g ; Mozzarella (boule) : 124 g ; Ail : 6 g ; Citron (zeste) : 50 g ; Origan séché : 1 g ; Huile d'olive : 30 ml ; Pain (baguette ou pain de mie) : 160 g ; Sel : 1 g ; Poivre : 1 g
A83: Étape 1 | B83: Laver 350 g de courgette (1 grosse ou 2 petites), couper en fines rondelles. Couper 250 g de tomates cerises en deux. Hacher 1 gousse d'ail (ou 6 g de semoule).
A84: Étape 2 | B84: Dans une poêle de 24-26 cm avec couvercle, chauffer 30 ml d'huile à feu moyen-vif. Faire revenir les courgettes et l'ail 8 min en remuant, jusqu'à ce qu'elles soient tendres et dorées.
A85: Étape 3 | B85: Ajouter les tomates cerises et 1 g d'origan, faire dorer 2 min.
A86: Étape 4 | B86: Dans un saladier, battre 4 œufs avec 1 pincée de sel et du poivre.
A87: Étape 5 | B87: Baisser à feu doux, verser les œufs sur les légumes, répartir. Couvrir, cuire 8 min : le dessus doit être pris mais moelleux.
A88: Étape 6 | B88: En fin de cuisson, zester ½ citron sur la frittata (râpe fine).
A89: Étape 7 | B89: Faire glisser la frittata sur une assiette, déchirer 125 g de mozzarella dessus pour qu'elle fonde à la chaleur. Arroser d'un filet d'huile.
A90: Étape 8 | B90: Servir la moitié avec 1 mini-baguette (80 g, 8 min au grille-pain ou 5 min à la poêle couverte). L'autre moitié en boîte au frigo, se mange froide ou 1 min au micro-ondes, avec la 2e mini-baguette.
A92: Jeudi — 21. Risotto de coquillettes au jambon, petits pois et parmesan — 25 min (5 + 20)
A93: Ingrédients (2 portions) | B93: Coquillettes sèches : 250 g ; Oignon : 100 g ; Ail : 6 g ; Petits pois surgelés : 100 g ; Jambon blanc : 140 g ; Cube de bouillon de volaille : 10 g ; Eau : 700 ml ; Parmesan râpé : 30 g ; Mascarpone (ou crème épaisse) : 50 g ; Huile : 10 ml ; Poivre : 1 g ; Sel : 0 g
A94: Étape 1 | B94: Éplucher et émincer 100 g d'oignon. Hacher 1 gousse d'ail (ou 6 g de semoule).
A95: Étape 2 | B95: Chauffer 10 ml d'huile dans une sauteuse, faire suer l'oignon et l'ail 5 min à feu moyen.
A96: Étape 3 | B96: Ajouter 250 g de coquillettes crues, mélanger 1 min pour les enrober. Émietter 1 cube de bouillon (10 g) par-dessus.
A97: Étape 4 | B97: Verser de l'eau chaude juste à hauteur des pâtes (≈ 400 ml), ajouter 140 g de jambon (4 tranches) haché grossièrement. Cuire à feu moyen en mélangeant souvent, en rajoutant de l'eau au fur et à mesure qu'elle est absorbée (comme un risotto), ≈ 10 min.
A98: Étape 5 | B98: Ajouter 100 g de petits pois (égouttés), remettre 5 cl d'eau, poursuivre 3-4 min : les pâtes doivent être cuites et crémeuses, plus de liquide libre.
A99: Étape 6 | B99: Hors du feu, ajouter 50 g de crème épaisse et 30 g de grana padano râpé. Poivrer (pas de sel). Mélanger.
A100: Étape 7 | B100: Servir la moitié aussitôt. L'autre moitié en boîte ; réchauffer 3 min à la poêle avec 3 cs d'eau.
A102: Vendredi — 24. Pâtes sauce tomate-basilic, mozzarella fondante & parmesan — 15 min (3 + 12)
A103: Ingrédients (2 portions) | B103: Pâtes sèches (spaghetti ou courtes) : 250 g ; Sauce tomate-basilic (pot) : 420 ml ; Mozzarella (boule) : 124 g ; Parmesan râpé : 30 g ; Huile : 10 ml ; Sel : 2 g ; Poivre : 1 g
A104: Étape 1 | B104: Porter une grande casserole d'eau à ébullition, saler. Cuire 250 g de pâtes selon le paquet, moins 1 min (elles finissent dans la sauce).
A105: Étape 2 | B105: Dans une sauteuse, chauffer 10 ml d'huile à feu moyen. Verser le pot entier de sauce tomate-basilic (420 g), laisser mijoter 5 min à petits bouillons en remuant : la sauce se concentre et perd le goût de bocal. Option protéine : dorer 120 g de lardons ou de chorizo 3 min dans la sauteuse AVANT la sauce.
A106: Étape 3 | B106: Déchirer 1 boule de mozzarella (125 g) en morceaux.
A107: Étape 4 | B107: Égoutter les pâtes en gardant 1 louche d'eau. Les verser dans la sauce, mélanger 2 min à feu doux ; ajouter un peu d'eau de cuisson si ça accroche.
A108: Étape 5 | B108: Couper le feu. Répartir la mozzarella sur les pâtes, couvrir 2 min : elle fond et file sans cuire.
A109: Étape 6 | B109: Mélanger une seule fois, poivrer, parsemer 30 g de parmesan râpé. Servir la moitié.
A110: Étape 7 | B110: Portion du lendemain : en boîte au frigo, réchauffer 3 min à la poêle couverte ou 2 min au micro-ondes avec 1 cs d'eau (la mozzarella redevient filante).

Sheet S3
A1: Semaine 3 — total 55.13 € (marge -0.13 €) — retrait Chronodrive le dimanche
A3: PLANNING
A4: Jour | B4: Midi | C4: Soir | D4: kcal / portion (soir) | E4: À cuisiner ce jour | F4: Note | G4: Macros / portion (P / G / L en g)
A5: Dimanche (retrait) | B5: libre / reste | C5: Pizza : Auchan Pizza au chèvre 390 g | D5: ≈ 900 | E5: Four 12 min | F5: Retrait du drive le matin
A6: Lundi | B6: Portion 2 de la pizza / reste | C6: 10. Côtes d'échine à la moutarde et à la crème + spaghetti | D6: =ROUND(Nutrition!H148,0) -> 864 | E6: 30 min (5 + 25) — 2 portions | F6: Filet mignon (18,30 €/kg) → côtes d'échine sans os (11,63 €/kg), même sauce moutarde-crème ; tagliatelles → spaghetti. | G6: =ROUND(Nutrition!I148,0)&" / "&ROUND(Nutrition!J148,0)&" / "&ROUND(Nutrition!K148,0) -> 39 / 75 / 44
A7: Mardi | B7: Portion 2 de : Côtes d'échine à la moutarde et à la crème + spaghetti | C7: 12. Ravioli poêlés à la tomate et mozzarella | D7: =ROUND(Nutrition!H186,0) -> 908 | E7: 15 min — 2 portions | F7: Ravioles du Dauphiné (13,54 €/kg) → ravioli Auchan aux fromages (5,63 €/kg), même geste poêlé ; coulis → pulpe. | G7: =ROUND(Nutrition!I186,0)&" / "&ROUND(Nutrition!J186,0)&" / "&ROUND(Nutrition!K186,0) -> 41 / 94 / 40
A8: Mercredi | B8: Portion 2 de : Ravioli poêlés à la tomate et mozzarella | C8: 23. Pâtes pesto caprese (boule de mozzarella, tomates cerises) | D8: =ROUND(Nutrition!H369,0) -> 1050 | E8: 15 min (5 + 10) — 2 portions | F8: Version sans cuisson à part les pâtes ; 1 boule de mozzarella entière par portion (ton choix) ; lardons de la source supprimés. | G8: =ROUND(Nutrition!I369,0)&" / "&ROUND(Nutrition!J369,0)&" / "&ROUND(Nutrition!K369,0) -> 46 / 99 / 50
A9: Jeudi | B9: Portion 2 de : Pâtes pesto caprese (boule de mozzarella, tomates cerises) | C9: 1. Poulet au curry, lait de coco et noix de cajou + riz | D9: =ROUND(Nutrition!H15,0) -> 885 | E9: 25 min (10 + 15) — 2 portions | G9: =ROUND(Nutrition!I15,0)&" / "&ROUND(Nutrition!J15,0)&" / "&ROUND(Nutrition!K15,0) -> 42 / 75 / 46
A10: Vendredi | B10: Portion 2 de : Poulet au curry, lait de coco et noix de cajou + riz | C10: 7. Quesadillas chorizo-emmental & avocat (version éco) | D10: =ROUND(Nutrition!H105,0) -> 959 | E10: 20 min — 2 portions | F10: Version éco : cheddar + gouda → 60 g d'emmental ; ½ avocat (75 g) ; cuisson poêle. | G10: =ROUND(Nutrition!I105,0)&" / "&ROUND(Nutrition!J105,0)&" / "&ROUND(Nutrition!K105,0) -> 37 / 45 / 69
A11: Samedi | B11: Portion 2 de : Quesadillas chorizo-emmental & avocat (version éco) | C11: ½ Marie Lasagnes à la bolognaise 1 kg | D11: ≈ 900-1 000 | E11: Poêle / micro-ondes | F11: Sachet coupé en 2 (congélateur)
A12: Dimanche midi | B12: ½ Marie Lasagnes à la bolognaise 1 kg | C12: → pizza de la semaine suivante
A14: LISTE DE COURSES CHRONODRIVE — formats entiers
A15: Produit exact (Chronodrive) | B15: Rayon | C15: Qté à acheter | D15: Prix unitaire € | E15: Total € | F15: Besoin semaine (2 portions x 5) | G15: Acheté | H15: Unité | I15: Reste après la semaine | J15: dont gâchis estimé € | K15: dont stock (se garde) € | L15: Sert aux recettes
A16: Auchan chorizo doux 24 tranches 120 g | B16: Charcuterie | C16: 1 | D16: 1.85 | E16: =C16*D16 -> 1.85 | F16: 100 | G16: 120 | H16: g | I16: 20 | J16: 0.0925 | K16: 0.21583333 | L16: 7
A17: Auchan crème épaisse légère 15 % 20 cl | B17: Crèmerie | C17: 1 | D17: 0.75 | E17: =C17*D17 -> 0.75 | F17: 180 | G17: 200 | H17: ml | I17: 20 | J17: 0.0225 | K17: 0.0525 | L17: 7, 10
A18: Auchan emmental râpé 3 x 70 g | B18: Crèmerie | C18: 1 | D18: 2.09 | E18: =C18*D18 -> 2.09 | F18: 200 | G18: 210 | H18: g | I18: 10 | J18: 0.019904762 | K18: 0.079619048 | L18: 7, 12
A19: Auchan Tavola grana padano râpé 60 g | B19: Crèmerie | C19: 1 | D19: 1.19 | E19: =C19*D19 -> 1.19 | F19: 30 | G19: 60 | H19: g | I19: 30 | J19: 0 | K19: 0.595 | L19: 23
A20: Casa Azzurra mozzarella 125 g | B20: Crèmerie | C20: 2 | D20: 1.15 | E20: =C20*D20 -> 2.3 | F20: 250 | G20: 250 | H20: g | I20: 0 | J20: 0 | K20: 0 | L20: 23
A21: Auchan ravioli aux fromages 300 g | B21: Frais | C21: 2 | D21: 1.69 | E21: =C21*D21 -> 3.38 | F21: 500 | G21: 600 | H21: g | I21: 100 | J21: 0.56333333 | K21: 0 | L21: 12
A22: Avocat 1 pièce | B22: Fruits & légumes | C22: 1 | D22: 1.59 | E22: =C22*D22 -> 1.59 | F22: 150 | G22: 150 | H22: g | I22: 0 | J22: 0 | K22: 0 | L22: 7
A23: Tomates cerises 250 g | B23: Fruits & légumes | C23: 2 | D23: 0.99 | E23: =C23*D23 -> 1.98 | F23: 370 | G23: 500 | H23: g | I23: 130 | J23: 0.5148 | K23: 0 | L23: 12, 23
A24: Porc côtes échines sans os LR 2 pièces 300 g | B24: Viande | C24: 1 | D24: 3.49 | E24: =C24*D24 -> 3.49 | F24: 300 | G24: 300 | H24: g | I24: 0 | J24: 0 | K24: 0 | L24: 10
A25: Auchan filets de poulet blanc 260 g | B25: Viande | C25: 1 | D25: 3.89 | E25: =C25*D25 -> 3.89 | F25: 260 | G25: 260 | H25: g | I25: 0 | J25: 0 | K25: 0 | L25: 1
A26: Auchan Recette d'Asie lait de coco 20 cl | B26: Épicerie | C26: 1 | D26: 0.95 | E26: =C26*D26 -> 0.95 | F26: 200 | G26: 200 | H26: ml | I26: 0 | J26: 0 | K26: 0 | L26: 1
A27: Auchan Essentiel noix de cajou 125 g | B27: Épicerie | C27: 1 | D27: 1.39 | E27: =C27*D27 -> 1.39 | F27: 40 | G27: 125 | H27: g | I27: 85 | J27: 0 | K27: 0.9452 | L27: 1
... A32: Auchan tortillas de blé 8 pièces 320 g | B32: Épicerie | C32: 1 | D32: 2.05 | E32: =C32*D32 -> 2.05 | F32: 160 | G32: 320 | H32: g | I32: 160 | J32: 0.5125 | K32: 0.5125 | L32: 7
A33: TOTAL COURSES RECETTES | E33: =SUM(E16:E32) -> 32.22 | J33: =SUM(J16:J32) -> 2.4149003 | K33: =SUM(K16:K32) -> 4.5582145
A34: Marie Lasagnes à la bolognaise 1 kg | B34: Surgelé (week-end) | C34: 1 | D34: 5.79 | E34: =C34*D34 -> 5.79 | L34: Samedi soir + dimanche midi
A35: Auchan Pizza au chèvre 390 g | B35: Surgelé (week-end) | C35: 1 | D35: 2.49 | E35: =C35*D35 -> 2.49 | L35: Dimanche soir
A36: TOTAL PANIER (recettes + week-end) | E36: =E33+E34+E35 -> 40.5
A38: PLACARD / BASES utilisées cette semaine — comptées au PRIX PLEIN du format
A39: Produit exact | B39: Rayon | C39: Qté | D39: Prix format € | E39: Total € | F39: Qté utilisée cette semaine | G39: Contenu format | H39: Unité | I39: Reste (stock) | K39: Valeur du reste € | L39: Sert aux recettes
A40: Basilic séché Ducros ≈ 12 g | B40: Placard | C40: 1 | D40: 1.8 | E40: =C40*D40 -> 1.8 | F40: 4 | G40: 12 | H40: g | I40: 8 | K40: =D40*I40/G40 -> 1.2 | L40: 12
A41: Beurre | B41: Placard | C41: 1 | D41: 2.45 | E41: =C41*D41 -> 2.45 | F41: 20 | G41: 250 | H41: g | I41: 230 | K41: =D41*I41/G41 -> 2.254 | L41: 10
A42: Curry en poudre Ducros 47 g | B42: Placard | C42: 1 | D42: 2.15 | E42: =C42*D42 -> 2.15 | F42: 4 | G42: 47 | H42: g | I42: 43 | K42: =D42*I42/G42 -> 1.9670213 | L42: 1
A43: Farine T45 | B43: Placard | C43: 1 | D43: 0.95 | E43: =C43*D43 -> 0.95 | F43: 10 | G43: 1000 | H43: g | I43: 990 | K43: =D43*I43/G43 -> 0.9405 | L43: 1
A44: Huile de tournesol | B44: Placard | C44: 1 | D44: 2.15 | E44: =C44*D44 -> 2.15 | F44: 60 | G44: 1000 | H44: ml | I44: 940 | K44: =D44*I44/G44 -> 2.021 | L44: 1, 7, 12
A45: Moutarde de Dijon | B45: Placard | C45: 1 | D45: 1.85 | E45: =C45*D45 -> 1.85 | F45: 30 | G45: 430 | H45: g | I45: 400 | K45: =D45*I45/G45 -> 1.7209302 | L45: 10
A46: Sauce soja | B46: Placard | C46: 1 | D46: 1.69 | E46: =C46*D46 -> 1.69 | F46: 10 | G46: 150 | H46: ml | I46: 140 | K46: =D46*I46/G46 -> 1.5773333 | L46: 1
A47: Sel / poivre | B47: Placard | C47: 1 | D47: 0.5 | E47: =C47*D47 -> 0.5 | F47: 12 | G47: 100 | H47: g | I47: 88 | K47: =D47*I47/G47 -> 0.44 | L47: 1, 7, 10, 12, 23
A48: Vinaigre de cidre | B48: Placard | C48: 1 | D48: 1.09 | E48: =C48*D48 -> 1.09 | F48: 4 | G48: 750 | H48: ml | I48: 746 | K48: =D48*I48/G48 -> 1.0841867 | L48: 7
A49: TOTAL placard (prix plein) | E49: =SUM(E40:E48) -> 14.63
A51: BUDGET
A52: Panier recettes + week-end | E52: =E36 -> 40.5
A53: + placard / bases au prix plein | E53: =E49 -> 14.63
A54: TOTAL PANIER CHRONODRIVE DE LA SEMAINE | E54: =E36+E49 -> 55.13
A55: Budget max | E55: 55
A56: Marge | E56: =E55-E54 -> -0.13
A57: Gâchis estimé (périssable non consommé) | E57: =J33 -> 2.4149003
A58: Gâchis en % du panier | E58: =J33/E36 -> 0.059627167
A59: Reste non périssable (stock) | E59: =K33 -> 4.5582145
A60: Coût par portion (14 repas) | E60: =(E36+E49)/14 -> 3.9378571
A61: Si le placard est déjà plein chez toi, le panier réel redescend à | E61: =E36 -> 40.5
A64: ÉTAPES DES 5 RECETTES DE LA SEMAINE (2 portions chacune)
A65: Lundi — 10. Côtes d'échine à la moutarde et à la crème + spaghetti — 30 min (5 + 25)
A66: Ingrédients (2 portions) | B66: Côtes d'échine de porc sans os : 300 g ; Moutarde de Dijon : 30 g ; Crème fraîche épaisse : 80 g ; Beurre (ou margarine) : 20 g ; Spaghetti (remplace les tagliatelles) : 200 g ; Poivre : 2 g ; Sel : 0 g
A67: Étape 1 | B67: Sortir 2 côtes d'échine sans os (300 g). Les saler légèrement (la moutarde sale déjà) et poivrer.
A68: Étape 2 | B68: Faire fondre 20 g de beurre dans une poêle à feu moyen-vif. Saisir les côtes 3 min par face jusqu'à belle coloration.
A69: Étape 3 | B69: Tartiner chaque côte de 15 g de moutarde de Dijon (1 cs chacune). Baisser à feu doux, déglacer le fond avec 15 g de crème épaisse (1 cs).
A70: Étape 4 | B70: Couvrir et laisser cuire 12-15 min à feu doux (l'échine doit être cuite à cœur mais rester juteuse).
A71: Étape 5 | B71: Pendant ce temps, cuire 200 g de spaghetti dans l'eau bouillante salée.
A72: Étape 6 | B72: Retirer les côtes sur une assiette. Dans la poêle, ajouter 65 g de crème épaisse (le reste des 80 g), gratter les sucs, mélanger avec la moutarde 1 min pour obtenir une sauce lisse. Rallonger avec 1-2 cs d'eau des pâtes si trop épais. Poivrer.
A73: Étape 7 | B73: Servir 1 côte avec la moitié des spaghetti nappés de sauce. L'autre côte + pâtes + sauce en boîte au frigo ; réchauffer à couvert 3 min à la poêle avec 1 cs d'eau.
A75: Mardi — 12. Ravioli poêlés à la tomate et mozzarella — 15 min
A76: Ingrédients (2 portions) | B76: Ravioli frais aux fromages (remplace les ravioles) : 500 g ; Tomates cerises : 120 g ; Coulis de tomate : 160 ml ; Mozzarella râpée (ou emmental) : 80 g ; Basilic frais : 4 g ; Eau : 60 ml ; Huile d'olive : 16 ml ; Sel : 1 g ; Poivre : 1 g
A77: Étape 1 | B77: Effeuiller 4-5 feuilles de basilic (ou prévoir 2 g de basilic séché pour la fin). Couper 120 g de tomates cerises en deux.
A78: Étape 2 | B78: Chauffer 15 ml d'huile dans une grande poêle à feu moyen. Y verser 500 g de raviolis frais aux fromages CRUS (sans les cuire à l'eau : ils se séparent à la cuisson) avec les tomates cerises. Cuire 6-7 min en remuant régulièrement jusqu'à ce que les raviolis dorent ; baisser le feu si ça colore trop.
A79: Étape 3 | B79: Verser 160 g de pulpe de tomate et 60 ml d'eau. Saler, poivrer. Couvrir et cuire 5 min à feu doux : les raviolis finissent de cuire dans la sauce.
A80: Étape 4 | B80: Ôter le couvercle, parsemer 80 g de mozzarella (déchirée ou râpée). Couvrir de nouveau 2-3 min à feu doux pour la faire fondre.
A81: Étape 5 | B81: Servir la moitié parsemée de basilic. L'autre moitié en boîte au frigo ; réchauffer 3 min à la poêle couverte avec 1 cs d'eau.
A83: Mercredi — 23. Pâtes pesto caprese (boule de mozzarella, tomates cerises) — 15 min (5 + 10)
A84: Ingrédients (2 portions) | B84: Pâtes sèches (spaghetti ou courtes) : 250 g ; Pesto vert (pot) : 100 g ; Tomates cerises : 250 g ; Mozzarella (boule) : 250 g ; Parmesan râpé : 30 g ; Sel : 2 g ; Poivre : 1 g
A85: Étape 1 | B85: Porter une grande casserole d'eau à ébullition, saler. Cuire 250 g de pâtes selon le paquet (al dente).
A86: Étape 2 | B86: Pendant la cuisson : couper 250 g de tomates cerises en deux. Égoutter 2 boules de mozzarella (125 g chacune) et les déchirer à la main en morceaux de la taille d'une noix (pas au couteau : les bords irréguliers fondent mieux).
A87: Étape 3 | B87: Juste avant d'égoutter, prélever 1 louche d'eau de cuisson (≈ 100 ml). Égoutter les pâtes et les remettre aussitôt dans la casserole chaude, hors du feu.
A88: Étape 4 | B88: Ajouter 100 g de pesto vert et la moitié de l'eau de cuisson. Mélanger vigoureusement 30 s : le pesto devient une sauce crémeuse qui enrobe. Rajouter de l'eau si c'est sec.
A89: Étape 5 | B89: Ajouter les tomates et la mozzarella, mélanger 20 s seulement : la chaleur des pâtes tiédit les tomates et fait filer la mozzarella sans la cuire.
A90: Étape 6 | B90: Poivrer, parsemer 30 g de parmesan râpé. Servir la moitié aussitôt.
A91: Étape 7 | B91: Portion du lendemain : en boîte au frigo. Se mange froide (salade de pâtes de luxe) ou 2 min au micro-ondes avec 1 cs d'eau ; dans ce cas garder la 2e boule entière et la déchirer dessus après réchauffage.
A93: Jeudi — 1. Poulet au curry, lait de coco et noix de cajou + riz — 25 min (10 + 15)
A94: Ingrédients (2 portions) | B94: Filet de poulet : 260 g ; Lait de coco : 200 ml ; Curry en poudre : 4 g ; Sauce soja : 10 ml ; Noix de cajou grillées salées : 40 g ; Maïzena : 10 g ; Huile : 30 ml ; Riz long cru : 160 g ; Sel : 2 g ; Poivre : 1 g
A95: Étape 1 | B95: Riz : verser 160 g de riz long dans une casserole avec 240 ml d'eau et 1 pincée de sel. Porter à ébullition, couvrir, baisser à feu doux, cuire 11 min sans soulever le couvercle, puis couper le feu et laisser reposer 5 min à couvert.
A96: Étape 2 | B96: Concasser 40 g de noix de cajou (fond d'un verre dans une assiette creuse) : moitié poudre, moitié petits morceaux.
A97: Étape 3 | B97: Couper 260 g de filet de poulet en cubes de 1-2 cm. Les mettre dans un bol avec 10 g de farine (2 cc) et mélanger pour les enrober.
A98: Étape 4 | B98: Chauffer 30 ml d'huile (2 cs) dans une sauteuse à feu moyen-vif. Ajouter 4 g de curry (2 cc) et laisser chauffer 30 s jusqu'à ce que ça sente.
A99: Étape 5 | B99: Ajouter le poulet, faire dorer 5 min en remuant.
A100: Étape 6 | B100: Verser 10 ml de sauce soja (2 cc) puis 200 ml de lait de coco (1 brique). Mélanger, baisser à feu doux, laisser cuire 10 min : la sauce épaissit grâce à la farine.
A101: Étape 7 | B101: 5 min avant la fin, ajouter les noix de cajou. Saler légèrement, poivrer.
A102: Étape 8 | B102: Servir la moitié sur la moitié du riz. Laisser refroidir l'autre moitié (riz et sauce séparés) avant de mettre en boîte au frigo pour le lendemain midi.
A104: Vendredi — 7. Quesadillas chorizo-emmental & avocat (version éco) — 20 min
A105: Ingrédients (2 portions) | B105: Dés de chorizo : 100 g ; Tortillas de blé : 160 g ; Emmental râpé (remplace cheddar + gouda) : 120 g ; Avocat : 150 g ; Crème fraîche épaisse : 100 g ; Huile d'olive : 14 ml ; Vinaigre (balsamique blanc, riz ou cidre) : 4 ml ; Sel : 1 g ; Poivre : 1 g
A106: Étape 1 | B106: Couper 100 g de chorizo en petits dés (ou utiliser 100 g de chorizo en tranches coupées en 4).
A107: Étape 2 | B107: Chauffer une poêle à sec à feu moyen-vif. Griller le chorizo 3-4 min jusqu'à ce qu'il soit légèrement doré et rende son gras. Réserver.
A108: Étape 3 | B108: Poser 4 tortillas. Sur une moitié de chaque tortilla, répartir 120 g d'emmental râpé et le chorizo. Replier en deux et presser.
A109: Étape 4 | B109: Cuisson à la poêle (pas besoin de four) : avec 15 ml d'huile, feu moyen, 3 min par face en appuyant avec une spatule, jusqu'à ce que ce soit doré et que le fromage file. Faire en 2 fois.
A110: Étape 5 | B110: Guacamole express : couper 1 avocat en deux, retirer le noyau, prélever la chair à la cuillère, l'écraser à la fourchette avec 5 ml de vinaigre (1 cc), sel, poivre.
A111: Étape 6 | B111: Couper chaque quesadilla en 3 triangles. Servir 2 quesadillas avec la moitié du guacamole et 50 g de crème épaisse. Les 2 autres quesadillas se réchauffent 2 min à la poêle le lendemain ; le guacamole restant : filmer au contact avec un filet de citron ou de vinaigre.

Sheet S4
A1: Semaine 4 — total 49.05 € (marge 5.95 €) — retrait Chronodrive le dimanche
A3: PLANNING
A4: Jour | B4: Midi | C4: Soir | D4: kcal / portion (soir) | E4: À cuisiner ce jour | F4: Note | G4: Macros / portion (P / G / L en g)
A5: Dimanche (retrait) | B5: libre / reste | C5: Pizza : Auchan Pizza bolognaise 390 g | D5: ≈ 900 | E5: Four 12 min | F5: Retrait du drive le matin
A6: Lundi | B6: Portion 2 de la pizza / reste | C6: 16. « Couscous » étudiant poulet, carottes, pois chiches | D6: =ROUND(Nutrition!H253,0) -> 838 | E6: 30 min (annoncé) — mijotage 20-25 min — 2 portions | F6: Semoule montée à 100 g pour passer 700 kcal ; ras el hanout du placard. | G6: =ROUND(Nutrition!I253,0)&" / "&ROUND(Nutrition!J253,0)&" / "&ROUND(Nutrition!K253,0) -> 50 / 105 / 23
A7: Mardi | B7: Portion 2 de : « Couscous » étudiant poulet, carottes, pois chiches | C7: 24. Pâtes sauce tomate-basilic, mozzarella fondante & parmesan | D7: =ROUND(Nutrition!H382,0) -> 807 | E7: 15 min (3 + 12) — 2 portions | F7: Sans oignon ni tomates cerises (ton choix) ; sauce du commerce mijotée 5 min ; 1 boule de mozzarella pour 2 portions ; parmesan ajouté. | G7: =ROUND(Nutrition!I382,0)&" / "&ROUND(Nutrition!J382,0)&" / "&ROUND(Nutrition!K382,0) -> 34 / 105 / 26
A8: Mercredi | B8: Portion 2 de : Pâtes sauce tomate-basilic, mozzarella fondante & parmesan | C8: 9. Riz au chorizo et poivrons (façon paella express) | D8: =ROUND(Nutrition!H135,0) -> 708 | E8: 30 min (10 + 20) — 2 portions | F8: Olives supprimées (facultatives, 2 € le bocal). | G8: =ROUND(Nutrition!I135,0)&" / "&ROUND(Nutrition!J135,0)&" / "&ROUND(Nutrition!K135,0) -> 21 / 77 / 35
A9: Jeudi | B9: Portion 2 de : Riz au chorizo et poivrons (façon paella express) | C9: 19. Pâtes crémeuses au chèvre, miel et lardons | D9: =ROUND(Nutrition!H304,0) -> 863 | E9: 15 min — 2 portions | G9: =ROUND(Nutrition!I304,0)&" / "&ROUND(Nutrition!J304,0)&" / "&ROUND(Nutrition!K304,0) -> 33 / 96 / 38
A10: Vendredi | B10: Portion 2 de : Pâtes crémeuses au chèvre, miel et lardons | C10: 15. Saucisses-lentilles express (lentilles en conserve) | D10: =ROUND(Nutrition!H235,0) -> 780 | E10: 15 min — 2 portions | G10: =ROUND(Nutrition!I235,0)&" / "&ROUND(Nutrition!J235,0)&" / "&ROUND(Nutrition!K235,0) -> 38 / 36 / 52
A11: Samedi | B11: Portion 2 de : Saucisses-lentilles express (lentilles en conserve) | C11: ½ Auchan Torsades à la carbonara 900 g | D11: ≈ 900-1 000 | E11: Poêle / micro-ondes | F11: Sachet coupé en 2 (congélateur)
A12: Dimanche midi | B12: ½ Auchan Torsades à la carbonara 900 g | C12: → pizza de la semaine suivante
A14: LISTE DE COURSES CHRONODRIVE — formats entiers
A15: Produit exact (Chronodrive) | B15: Rayon | C15: Qté à acheter | D15: Prix unitaire € | E15: Total € | F15: Besoin semaine (2 portions x 5) | G15: Acheté | H15: Unité | I15: Reste après la semaine | J15: dont gâchis estimé € | K15: dont stock (se garde) € | L15: Sert aux recettes
A16: Auchan chorizo doux 24 tranches 120 g | B16: Charcuterie | C16: 1 | D16: 1.85 | E16: =C16*D16 -> 1.85 | F16: 120 | G16: 120 | H16: g | I16: 0 | J16: 0 | K16: 0 | L16: 9
A17: Auchan lardons fumés 2 x 100 g | B17: Charcuterie | C17: 1 | D17: 2.09 | E17: =C17*D17 -> 2.09 | F17: 180 | G17: 200 | H17: g | I17: 20 | J17: 0.1045 | K17: 0.1045 | L17: 15, 19
A18: Auchan Knacks 10 pièces 350 g | B18: Charcuterie | C18: 1 | D18: 1.75 | E18: =C18*D18 -> 1.75 | F18: 280 | G18: 350 | H18: g | I18: 70 | J18: 0.175 | K18: 0.175 | L18: 15
A19: Auchan bûche de chèvre fondant 180 g | B19: Crèmerie | C19: 1 | D19: 2.09 | E19: =C19*D19 -> 2.09 | F19: 100 | G19: 180 | H19: g | I19: 80 | J19: 0.46444444 | K19: 0.46444444 | L19: 19
A20: Auchan Essentiel crème fluide légère 15 % 20 cl | B20: Crèmerie | C20: 1 | D20: 0.69 | E20: =C20*D20 -> 0.69 | F20: 150 | G20: 200 | H20: ml | I20: 50 | J20: 0 | K20: 0.1725 | L20: 19
A21: Auchan Tavola grana padano râpé 60 g | B21: Crèmerie | C21: 1 | D21: 1.19 | E21: =C21*D21 -> 1.19 | F21: 30 | G21: 60 | H21: g | I21: 30 | J21: 0 | K21: 0.595 | L21: 24
A22: Casa Azzurra mozzarella 125 g | B22: Crèmerie | C22: 1 | D22: 1.15 | E22: =C22*D22 -> 1.15 | F22: 124 | G22: 125 | H22: g | I22: 1 | J22: 0.0092 | K22: 0 | L22: 24
A23: Carottes zéro résidu 750 g | B23: Fruits & légumes | C23: 1 | D23: 2.29 | E23: =C23*D23 -> 2.29 | F23: 300 | G23: 750 | H23: g | I23: 450 | J23: 0.687 | K23: 0.687 | L23: 15, 16
A24: Oignon jaune 1 kg | B24: Fruits & légumes | C24: 1 | D24: 2.69 | E24: =C24*D24 -> 2.69 | F24: 250 | G24: 1000 | H24: g | I24: 750 | J24: 0.4035 | K24: 1.614 | L24: 9, 15, 16, 19
A25: Poivron rouge 1 pièce | B25: Fruits & légumes | C25: 1 | D25: 0.99 | E25: =C25*D25 -> 0.99 | F25: 100 | G25: 150 | H25: g | I25: 50 | J25: 0.33 | K25: 0 | L25: 9
A26: Auchan filets de poulet blanc 260 g | B26: Viande | C26: 1 | D26: 3.89 | E26: =C26*D26 -> 3.89 | F26: 240 | G26: 260 | H26: g | I26: 20 | J26: 0.29923077 | K26: 0 | L26: 16
A27: Auchan lentilles préparées 530 g | B27: Épicerie | C27: 1 | D27: 1.29 | E27: =C27*D27 -> 1.29 | F27: 400 | G27: 530 | H27: g | I27: 130 | J27: 0.094924528 | K27: 0.22149057 | L27: 15
... A32: Auchan spaghetti 500 g | B32: Épicerie | C32: 1 | D32: 0.75 | E32: =C32*D32 -> 0.75 | F32: 490 | G32: 500 | H32: g | I32: 10 | J32: 0 | K32: 0.015 | L32: 19, 24
A33: TOTAL COURSES RECETTES | E33: =SUM(E16:E32) -> 27.13 | J33: =SUM(J16:J32) -> 2.6259318 | K33: =SUM(K16:K32) -> 5.8723765
A34: Auchan Torsades à la carbonara 900 g | B34: Surgelé (week-end) | C34: 1 | D34: 4.95 | E34: =C34*D34 -> 4.95 | L34: Samedi soir + dimanche midi
A35: Auchan Pizza bolognaise 390 g | B35: Surgelé (week-end) | C35: 1 | D35: 2.05 | E35: =C35*D35 -> 2.05 | L35: Dimanche soir
A36: TOTAL PANIER (recettes + week-end) | E36: =E33+E34+E35 -> 34.13
A38: PLACARD / BASES utilisées cette semaine — comptées au PRIX PLEIN du format
A39: Produit exact | B39: Rayon | C39: Qté | D39: Prix format € | E39: Total € | F39: Qté utilisée cette semaine | G39: Contenu format | H39: Unité | I39: Reste (stock) | K39: Valeur du reste € | L39: Sert aux recettes
A40: Beurre | B40: Placard | C40: 1 | D40: 2.45 | E40: =C40*D40 -> 2.45 | F40: 10 | G40: 250 | H40: g | I40: 240 | K40: =D40*I40/G40 -> 2.352 | L40: 15
A41: Bouillon cube | B41: Placard | C41: 1 | D41: 1.79 | E41: =C41*D41 -> 1.79 | F41: 16 | G41: 180 | H41: g | I41: 164 | K41: =D41*I41/G41 -> 1.6308889 | L41: 9, 16
A42: Huile de tournesol | B42: Placard | C42: 1 | D42: 2.15 | E42: =C42*D42 -> 2.15 | F42: 60 | G42: 1000 | H42: ml | I42: 940 | K42: =D42*I42/G42 -> 2.021 | L42: 9, 16, 24
A43: Miel liquide | B43: Placard | C43: 1 | D43: 2.15 | E43: =C43*D43 -> 2.15 | F43: 10 | G43: 250 | H43: g | I43: 240 | K43: =D43*I43/G43 -> 2.064 | L43: 19
A44: Origan Ducros 12 g | B44: Placard | C44: 1 | D44: 1.89 | E44: =C44*D44 -> 1.89 | F44: 1 | G44: 12 | H44: g | I44: 11 | K44: =D44*I44/G44 -> 1.7325 | L44: 19
A45: Ras el hanout La Conquête des Saveurs 240 g | B45: Placard | C45: 1 | D45: 3.99 | E45: =C45*D45 -> 3.99 | F45: 14 | G45: 240 | H45: g | I45: 226 | K45: =D45*I45/G45 -> 3.75725 | L45: 16
A46: Sel / poivre | B46: Placard | C46: 1 | D46: 0.5 | E46: =C46*D46 -> 0.5 | F46: 12 | G46: 100 | H46: g | I46: 88 | K46: =D46*I46/G46 -> 0.44 | L46: 9, 15, 16, 19, 24
A47: TOTAL placard (prix plein) | E47: =SUM(E40:E46) -> 14.92
A49: BUDGET
A50: Panier recettes + week-end | E50: =E36 -> 34.13
A51: + placard / bases au prix plein | E51: =E47 -> 14.92
A52: TOTAL PANIER CHRONODRIVE DE LA SEMAINE | E52: =E36+E47 -> 49.05
A53: Budget max | E53: 55
A54: Marge | E54: =E53-E52 -> 5.95
A55: Gâchis estimé (périssable non consommé) | E55: =J33 -> 2.6259318
A56: Gâchis en % du panier | E56: =J33/E36 -> 0.07693911
A57: Reste non périssable (stock) | E57: =K33 -> 5.8723765
A58: Coût par portion (14 repas) | E58: =(E36+E47)/14 -> 3.5035714
A59: Si le placard est déjà plein chez toi, le panier réel redescend à | E59: =E36 -> 34.13
A62: ÉTAPES DES 5 RECETTES DE LA SEMAINE (2 portions chacune)
A63: Lundi — 16. « Couscous » étudiant poulet, carottes, pois chiches — 30 min (annoncé) — mijotage 20-25 min
A64: Ingrédients (2 portions) | B64: Blanc de poulet : 240 g ; Carotte : 200 g ; Pois chiches cuits (boîte, égouttés) : 200 g ; Oignon : 60 g ; Ras el hanout (ou curry + cumin) : 14 g ; Cube de bouillon de légumes : 10 g ; Eau (pour le mijotage) : 200 ml ; Huile d'olive : 30 ml ; Semoule de couscous (sèche) : 200 g ; Eau bouillante (pour la semoule) : 240 ml ; Poivre : 1 g ; Sel : 1 g
A65: Étape 1 | B65: Couper 240 g de filet de poulet en gros dés. Émincer 60 g d'oignon. Éplucher 200 g de carotte, couper en rondelles puis en quarts.
A66: Étape 2 | B66: Chauffer 30 ml d'huile dans une poêle avec couvercle. Faire revenir l'oignon 3 min, ajouter le poulet et 14 g de ras el hanout (1 cs rase). Faire dorer le poulet sur chaque face, 4-5 min.
A67: Étape 3 | B67: Ajouter les carottes, mélanger. Émietter 1 cube de bouillon (10 g), verser 200 ml d'eau.
A68: Étape 4 | B68: Couvrir, laisser mijoter à feu doux jusqu'à ce que les carottes soient tendres : 20-25 min. Rajouter un peu d'eau si ça accroche. Saler, poivrer.
A69: Étape 5 | B69: Ajouter 200 g de pois chiches égouttés (¾ de boîte), poursuivre 3-5 min à découvert.
A70: Étape 6 | B70: Semoule : dans un saladier, verser 200 g de semoule, 1 pincée de sel, 10 ml d'huile. Verser 240 ml d'eau bouillante, couvrir d'une assiette 5 min, puis égrainer à la fourchette.
A71: Étape 7 | B71: Servir la moitié de la garniture et de sa sauce sur la moitié de la semoule. L'autre moitié en boîte (semoule et garniture ensemble) ; réchauffer 3 min au micro-ondes avec 2 cs d'eau.
A73: Mardi — 24. Pâtes sauce tomate-basilic, mozzarella fondante & parmesan — 15 min (3 + 12)
A74: Ingrédients (2 portions) | B74: Pâtes sèches (spaghetti ou courtes) : 250 g ; Sauce tomate-basilic (pot) : 420 ml ; Mozzarella (boule) : 124 g ; Parmesan râpé : 30 g ; Huile : 10 ml ; Sel : 2 g ; Poivre : 1 g
A75: Étape 1 | B75: Porter une grande casserole d'eau à ébullition, saler. Cuire 250 g de pâtes selon le paquet, moins 1 min (elles finissent dans la sauce).
A76: Étape 2 | B76: Dans une sauteuse, chauffer 10 ml d'huile à feu moyen. Verser le pot entier de sauce tomate-basilic (420 g), laisser mijoter 5 min à petits bouillons en remuant : la sauce se concentre et perd le goût de bocal. Option protéine : dorer 120 g de lardons ou de chorizo 3 min dans la sauteuse AVANT la sauce.
A77: Étape 3 | B77: Déchirer 1 boule de mozzarella (125 g) en morceaux.
A78: Étape 4 | B78: Égoutter les pâtes en gardant 1 louche d'eau. Les verser dans la sauce, mélanger 2 min à feu doux ; ajouter un peu d'eau de cuisson si ça accroche.
A79: Étape 5 | B79: Couper le feu. Répartir la mozzarella sur les pâtes, couvrir 2 min : elle fond et file sans cuire.
A80: Étape 6 | B80: Mélanger une seule fois, poivrer, parsemer 30 g de parmesan râpé. Servir la moitié.
A81: Étape 7 | B81: Portion du lendemain : en boîte au frigo, réchauffer 3 min à la poêle couverte ou 2 min au micro-ondes avec 1 cs d'eau (la mozzarella redevient filante).
A83: Mercredi — 9. Riz au chorizo et poivrons (façon paella express) — 30 min (10 + 20)
A84: Ingrédients (2 portions) | B84: Chorizo (doux ou fort) : 120 g ; Poivron vert : 50 g ; Poivron rouge : 50 g ; Oignon : 80 g ; Riz long cru : 180 g ; Cube de bouillon de volaille : 6 g ; Eau : 400 ml ; Huile : 20 ml ; Sel : 1 g ; Poivre : 1 g
A85: Étape 1 | B85: Couper 120 g de chorizo en rondelles (ou 120 g de tranches). Les faire frire 2 min dans une sauteuse sans matière grasse. Réserver le chorizo, garder le gras rouge dans la sauteuse.
A86: Étape 2 | B86: Émincer 80 g d'oignon et 100 g de poivron (rouge et/ou vert) en lanières.
A87: Étape 3 | B87: Dans le gras du chorizo + 20 ml d'huile, faire dorer l'oignon 3 min, puis ajouter les poivrons et faire revenir 5 min.
A88: Étape 4 | B88: Émietter ½ cube de bouillon (5 g), verser 400 ml d'eau. Porter à ébullition, verser 180 g de riz long. Mélanger, saler légèrement, poivrer.
A89: Étape 5 | B89: Couvrir, cuire à feu doux ≈ 15 min jusqu'à absorption complète (remuer une fois à mi-cuisson).
A90: Étape 6 | B90: 5 min avant la fin, remettre le chorizo (et son huile). Mélanger, laisser finir à couvert.
A91: Étape 7 | B91: Servir la moitié. L'autre moitié en boîte au frigo ; réchauffer 3 min à la poêle avec 2 cs d'eau.
A93: Jeudi — 19. Pâtes crémeuses au chèvre, miel et lardons — 15 min
A94: Ingrédients (2 portions) | B94: Pâtes sèches (torti, penne…) : 240 g ; Lardons fumés : 100 g ; Crème liquide (source : légère 4 %) : 150 ml ; Fromage de chèvre (bûche) : 100 g ; Échalote (ou oignon) : 30 g ; Miel liquide : 10 g ; Origan séché : 1 g ; Sel : 2 g ; Poivre : 1 g
A95: Étape 1 | B95: Porter une grande casserole d'eau à ébullition, saler. Cuire 240 g de pâtes courtes ou spaghetti (temps du paquet).
A96: Étape 2 | B96: Émincer 30 g d'oignon (ou échalote). Couper 100 g de bûche de chèvre en 6 rondelles.
A97: Étape 3 | B97: Chauffer une poêle bien chaude, mettre 100 g de lardons et l'oignon. Griller à feu moyen 4-5 min jusqu'à ce que les lardons soient dorés et l'oignon fondant.
A98: Étape 4 | B98: Ajouter 100 ml de crème fluide, mélanger, déposer les rondelles de chèvre. Baisser à feu doux, couvrir, laisser fondre 3-4 min.
A99: Étape 5 | B99: Quand le chèvre est fondu, saler, poivrer, ajouter 1 g d'origan, mélanger. Verser les pâtes et les 50 ml de crème restants dans la poêle, mélanger 1 min.
A100: Étape 6 | B100: Servir la moitié dans une assiette creuse, arroser d'un filet de miel (5 g par assiette). L'autre moitié en boîte sans le miel ; réchauffer 3 min à la poêle avec 2 cs d'eau, puis le miel.
A102: Vendredi — 15. Saucisses-lentilles express (lentilles en conserve) — 15 min
A103: Ingrédients (2 portions) | B103: Saucisses (Knacki ; ou 2 chipolatas) : 280 g ; Lentilles en conserve (poids égoutté) : 400 g ; Oignon : 80 g ; Carotte : 100 g ; Lardons fumés (ou allumettes de bacon) : 80 g ; Beurre ou huile : 10 g ; Poivre : 1 g ; Sel : 1 g
A104: Étape 1 | B104: Cuire 8 Knacki : plonger 3 min dans une casserole d'eau frémissante (ne pas faire bouillir, elles éclatent). Égoutter, réserver.
A105: Étape 2 | B105: Émincer 80 g d'oignon. Éplucher et couper 100 g de carotte en fines rondelles.
A106: Étape 3 | B106: Dans la casserole rincée, chauffer 10 g de beurre ou 10 ml d'huile. Faire suer l'oignon 3 min.
A107: Étape 4 | B107: Ajouter les carottes et 80 g de lardons. Faire revenir 5-10 min selon la tendreté voulue des carottes.
A108: Étape 5 | B108: Verser 400 g de lentilles en conserve (égouttées, en gardant 4 cs de jus). Laisser mijoter 5 min doucement en remuant.
A109: Étape 6 | B109: Ajouter les Knacki (entières ou en tronçons), réchauffer 2 min. Poivrer, saler seulement si besoin.
A110: Étape 7 | B110: Servir la moitié. L'autre moitié en boîte au frigo ; réchauffer 3 min à la casserole ou au micro-ondes.

Sheet S5
A1: Semaine 5 — total 50.62 € (marge 4.38 €) — retrait Chronodrive le dimanche
A3: PLANNING
A4: Jour | B4: Midi | C4: Soir | D4: kcal / portion (soir) | E4: À cuisiner ce jour | F4: Note | G4: Macros / portion (P / G / L en g)
A5: Dimanche (retrait) | B5: libre / reste | C5: Pizza : Auchan Les Italiennes 4 fromages 340 g | D5: ≈ 900 | E5: Four 12 min | F5: Retrait du drive le matin
A6: Lundi | B6: Portion 2 de la pizza / reste | C6: 13. Tortellini aux champignons, sauce crème-parmesan | D6: =ROUND(Nutrition!H204,0) -> 888 | E6: 20 min (8 + 12) — 2 portions | F6: Lait supprimé (eau de cuisson) ; parmesan = grana padano. | G6: =ROUND(Nutrition!I204,0)&" / "&ROUND(Nutrition!J204,0)&" / "&ROUND(Nutrition!K204,0) -> 33 / 93 / 41
A7: Mardi | B7: Portion 2 de : Tortellini aux champignons, sauce crème-parmesan | C7: 21. Risotto de coquillettes au jambon, petits pois et parmesan | D7: =ROUND(Nutrition!H339,0) -> 738 | E7: 25 min (5 + 20) — 2 portions | F7: Mascarpone → crème épaisse. | G7: =ROUND(Nutrition!I339,0)&" / "&ROUND(Nutrition!J339,0)&" / "&ROUND(Nutrition!K339,0) -> 39 / 103 / 18
A8: Mercredi | B8: Portion 2 de : Risotto de coquillettes au jambon, petits pois et parmesan | C8: 5. Pâtes à la « carbonara » à la française | D8: =ROUND(Nutrition!H71,0) -> 876 | E8: 20 min (5 + 15) — 2 portions | G8: =ROUND(Nutrition!I71,0)&" / "&ROUND(Nutrition!J71,0)&" / "&ROUND(Nutrition!K71,0) -> 30 / 100 / 39
A9: Jeudi | B9: Portion 2 de : Pâtes à la « carbonara » à la française | C9: 14. Risotto aux lardons et champignons | D9: =ROUND(Nutrition!H221,0) -> 943 | E9: 36 min (annoncé) — ≈ 30 min réel — 2 portions | G9: =ROUND(Nutrition!I221,0)&" / "&ROUND(Nutrition!J221,0)&" / "&ROUND(Nutrition!K221,0) -> 29 / 96 / 48
A10: Vendredi | B10: Portion 2 de : Risotto aux lardons et champignons | C10: 20. One pot pasta chorizo-basilic | D10: =ROUND(Nutrition!H321,0) -> 944 | E10: 30 min (annoncé) — ≈ 25 min — 2 portions | G10: =ROUND(Nutrition!I321,0)&" / "&ROUND(Nutrition!J321,0)&" / "&ROUND(Nutrition!K321,0) -> 37 / 101 / 43
A11: Samedi | B11: Portion 2 de : One pot pasta chorizo-basilic | C11: ½ Auchan Riz cantonais 900 g | D11: ≈ 900-1 000 | E11: Poêle / micro-ondes | F11: Sachet coupé en 2 (congélateur)
A12: Dimanche midi | B12: ½ Auchan Riz cantonais 900 g | C12: → pizza de la semaine suivante
A14: LISTE DE COURSES CHRONODRIVE — formats entiers
A15: Produit exact (Chronodrive) | B15: Rayon | C15: Qté à acheter | D15: Prix unitaire € | E15: Total € | F15: Besoin semaine (2 portions x 5) | G15: Acheté | H15: Unité | I15: Reste après la semaine | J15: dont gâchis estimé € | K15: dont stock (se garde) € | L15: Sert aux recettes
A16: Auchan Terroir chorizo doux 225 g | B16: Charcuterie | C16: 1 | D16: 2.59 | E16: =C16*D16 -> 2.59 | F16: 150 | G16: 225 | H16: g | I16: 75 | J16: 0.259 | K16: 0.60433333 | L16: 20
A17: Herta Le Bon Paris 4 tranches 140 g | B17: Charcuterie | C17: 1 | D17: 2.59 | E17: =C17*D17 -> 2.59 | F17: 140 | G17: 140 | H17: g | I17: 0 | J17: 0 | K17: 0 | L17: 21
A18: Auchan lardons fumés 2 x 100 g | B18: Charcuterie | C18: 2 | D18: 2.09 | E18: =C18*D18 -> 4.18 | F18: 270 | G18: 400 | H18: g | I18: 130 | J18: 0.67925 | K18: 0.67925 | L18: 5, 14
A19: Auchan crème épaisse légère 15 % 20 cl | B19: Crèmerie | C19: 1 | D19: 0.75 | E19: =C19*D19 -> 0.75 | F19: 170 | G19: 200 | H19: ml | I19: 30 | J19: 0.03375 | K19: 0.07875 | L19: 13, 21
A20: Auchan crème fluide légère 15 % 3 x 20 cl | B20: Crèmerie | C20: 1 | D20: 1.99 | E20: =C20*D20 -> 1.99 | F20: 410 | G20: 600 | H20: ml | I20: 190 | J20: 0 | K20: 0.63016667 | L20: 5, 14
A21: Auchan Tavola grana padano râpé 120 g | B21: Crèmerie | C21: 1 | D21: 1.95 | E21: =C21*D21 -> 1.95 | F21: 110 | G21: 120 | H21: g | I21: 10 | J21: 0 | K21: 0.1625 | L21: 13, 14, 20, 21
A22: Auchan œufs plein air x6 | B22: Crèmerie | C22: 1 | D22: 1.69 | E22: =C22*D22 -> 1.69 | F22: 36 | G22: 330 | H22: g | I22: 294 | J22: 0 | K22: 1.5056364 | L22: 5
A23: Auchan Tavola tortellini 3 fromages 250 g | B23: Frais | C23: 2 | D23: 2.05 | E23: =C23*D23 -> 4.1 | F23: 400 | G23: 500 | H23: g | I23: 100 | J23: 0.82 | K23: 0 | L23: 13
A24: Oignon jaune 1 kg | B24: Fruits & légumes | C24: 1 | D24: 2.69 | E24: =C24*D24 -> 2.69 | F24: 460 | G24: 1000 | H24: g | I24: 540 | J24: 0.29052 | K24: 1.16208 | L24: 5, 13, 14, 20, 21
A25: Tomates cerises 250 g | B25: Fruits & légumes | C25: 1 | D25: 0.99 | E25: =C25*D25 -> 0.99 | F25: 150 | G25: 250 | H25: g | I25: 100 | J25: 0.396 | K25: 0 | L25: 20
A26: Auchan champignons émincés boîte 230 g égoutté | B26: Épicerie | C26: 2 | D26: 1.29 | E26: =C26*D26 -> 2.58 | F26: 400 | G26: 460 | H26: g | I26: 60 | J26: 0.33652174 | K26: 0 | L26: 13, 14
A27: Auchan coquillettes 500 g | B27: Épicerie | C27: 1 | D27: 0.85 | E27: =C27*D27 -> 0.85 | F27: 250 | G27: 500 | H27: g | I27: 250 | J27: 0 | K27: 0.425 | L27: 21
... A30: Auchan spaghetti 500 g | B30: Épicerie | C30: 1 | D30: 0.75 | E30: =C30*D30 -> 0.75 | F30: 500 | G30: 500 | H30: g | I30: 0 | J30: 0 | K30: 0 | L30: 5, 20
A31: TOTAL COURSES RECETTES | E31: =SUM(E16:E30) -> 30.64 | J31: =SUM(J16:J30) -> 3.1223049 | K31: =SUM(K16:K30) -> 6.8326637
A32: Auchan Riz cantonais 900 g | B32: Surgelé (week-end) | C32: 1 | D32: 4.65 | E32: =C32*D32 -> 4.65 | L32: Samedi soir + dimanche midi
A33: Auchan Les Italiennes 4 fromages 340 g | B33: Surgelé (week-end) | C33: 1 | D33: 2.55 | E33: =C33*D33 -> 2.55 | L33: Dimanche soir
A34: TOTAL PANIER (recettes + week-end) | E34: =E31+E32+E33 -> 37.84
A36: PLACARD / BASES utilisées cette semaine — comptées au PRIX PLEIN du format
A37: Produit exact | B37: Rayon | C37: Qté | D37: Prix format € | E37: Total € | F37: Qté utilisée cette semaine | G37: Contenu format | H37: Unité | I37: Reste (stock) | K37: Valeur du reste € | L37: Sert aux recettes
A38: Ail semoule | B38: Placard | C38: 1 | D38: 1.29 | E38: =C38*D38 -> 1.29 | F38: 18 | G38: 55 | H38: g | I38: 37 | K38: =D38*I38/G38 -> 0.86781818 | L38: 13, 20, 21
A39: Basilic séché Ducros ≈ 12 g | B39: Placard | C39: 1 | D39: 1.8 | E39: =C39*D39 -> 1.8 | F39: 6 | G39: 12 | H39: g | I39: 6 | K39: =D39*I39/G39 -> 0.9 | L39: 20
A40: Beurre | B40: Placard | C40: 1 | D40: 2.45 | E40: =C40*D40 -> 2.45 | F40: 10 | G40: 250 | H40: g | I40: 240 | K40: =D40*I40/G40 -> 2.352 | L40: 13
A41: Bouillon cube | B41: Placard | C41: 1 | D41: 1.79 | E41: =C41*D41 -> 1.79 | F41: 20 | G41: 180 | H41: g | I41: 160 | K41: =D41*I41/G41 -> 1.5911111 | L41: 14, 21
A42: Farine T45 | B42: Placard | C42: 1 | D42: 0.95 | E42: =C42*D42 -> 0.95 | F42: 4 | G42: 1000 | H42: g | I42: 996 | K42: =D42*I42/G42 -> 0.9462 | L42: 13
A43: Huile de tournesol | B43: Placard | C43: 1 | D43: 2.15 | E43: =C43*D43 -> 2.15 | F43: 56 | G43: 1000 | H43: ml | I43: 944 | K43: =D43*I43/G43 -> 2.0296 | L43: 13, 14, 20, 21
A44: Moutarde de Dijon | B44: Placard | C44: 1 | D44: 1.85 | E44: =C44*D44 -> 1.85 | F44: 6 | G44: 430 | H44: g | I44: 424 | K44: =D44*I44/G44 -> 1.824186 | L44: 13
A45: Sel / poivre | B45: Placard | C45: 1 | D45: 0.5 | E45: =C45*D45 -> 0.5 | F45: 12 | G45: 100 | H45: g | I45: 88 | K45: =D45*I45/G45 -> 0.44 | L45: 5, 13, 14, 20, 21
A46: TOTAL placard (prix plein) | E46: =SUM(E38:E45) -> 12.78
A48: BUDGET
A49: Panier recettes + week-end | E49: =E34 -> 37.84
A50: + placard / bases au prix plein | E50: =E46 -> 12.78
A51: TOTAL PANIER CHRONODRIVE DE LA SEMAINE | E51: =E34+E46 -> 50.62
A52: Budget max | E52: 55
A53: Marge | E53: =E52-E51 -> 4.38
A54: Gâchis estimé (périssable non consommé) | E54: =J31 -> 3.1223049
A55: Gâchis en % du panier | E55: =J31/E34 -> 0.082513343
A56: Reste non périssable (stock) | E56: =K31 -> 6.8326637
A57: Coût par portion (14 repas) | E57: =(E34+E46)/14 -> 3.6157143
A58: Si le placard est déjà plein chez toi, le panier réel redescend à | E58: =E34 -> 37.84
A61: ÉTAPES DES 5 RECETTES DE LA SEMAINE (2 portions chacune)
A62: Lundi — 13. Tortellini aux champignons, sauce crème-parmesan — 20 min (8 + 12)
A63: Ingrédients (2 portions) | B63: Tortellini frais (fromage ou viande) : 400 g ; Champignons de Paris frais (ou boîte égouttée) : 150 g ; Oignon jaune : 60 g ; Ail : 6 g ; Crème fraîche épaisse : 120 g ; Beurre : 10 g ; Huile d'olive : 10 ml ; Parmesan râpé : 30 g ; Moutarde de Dijon : 6 g ; Farine (option, pour lier) : 4 g ; Sel : 2 g ; Poivre : 1 g
A64: Étape 1 | B64: Égoutter 150 g de champignons de boîte (ou nettoyer 150 g de frais avec un linge et les émincer). Émincer 60 g d'oignon, hacher ½ gousse d'ail (ou 1 cc de semoule).
A65: Étape 2 | B65: Dans une grande poêle, faire fondre 10 g de beurre avec 10 ml d'huile à feu moyen-vif. Faire suer l'oignon 3 min ; quand il est translucide, ajouter l'ail 30 s.
A66: Étape 3 | B66: Ajouter les champignons. Ne pas trop remuer : les laisser rendre leur eau puis dorer, 5-6 min. Saler légèrement.
A67: Étape 4 | B67: Baisser le feu. Option : saupoudrer 4 g de farine (1 cc) et remuer 1 min pour lier.
A68: Étape 5 | B68: Mélanger 120 g de crème épaisse avec 6 g de moutarde (1 cc). Verser dans la poêle, ajouter 2-3 cs d'eau si trop épais. Laisser mijoter doucement 2-3 min.
A69: Étape 6 | B69: Pendant ce temps, cuire 400 g de tortellini dans l'eau bouillante salée 2-3 min (temps du paquet). Garder 4 cs d'eau de cuisson avant d'égoutter.
A70: Étape 7 | B70: Verser les tortellini égouttés dans la poêle avec l'eau de cuisson, ajouter 30 g de grana padano râpé, mélanger 1 min pour lier. Poivrer.
A71: Étape 8 | B71: Servir la moitié. L'autre moitié en boîte ; réchauffer 3 min à la poêle avec 2 cs d'eau.
A73: Mardi — 21. Risotto de coquillettes au jambon, petits pois et parmesan — 25 min (5 + 20)
A74: Ingrédients (2 portions) | B74: Coquillettes sèches : 250 g ; Oignon : 100 g ; Ail : 6 g ; Petits pois surgelés : 100 g ; Jambon blanc : 140 g ; Cube de bouillon de volaille : 10 g ; Eau : 700 ml ; Parmesan râpé : 30 g ; Mascarpone (ou crème épaisse) : 50 g ; Huile : 10 ml ; Poivre : 1 g ; Sel : 0 g
A75: Étape 1 | B75: Éplucher et émincer 100 g d'oignon. Hacher 1 gousse d'ail (ou 6 g de semoule).
A76: Étape 2 | B76: Chauffer 10 ml d'huile dans une sauteuse, faire suer l'oignon et l'ail 5 min à feu moyen.
A77: Étape 3 | B77: Ajouter 250 g de coquillettes crues, mélanger 1 min pour les enrober. Émietter 1 cube de bouillon (10 g) par-dessus.
A78: Étape 4 | B78: Verser de l'eau chaude juste à hauteur des pâtes (≈ 400 ml), ajouter 140 g de jambon (4 tranches) haché grossièrement. Cuire à feu moyen en mélangeant souvent, en rajoutant de l'eau au fur et à mesure qu'elle est absorbée (comme un risotto), ≈ 10 min.
A79: Étape 5 | B79: Ajouter 100 g de petits pois (égouttés), remettre 5 cl d'eau, poursuivre 3-4 min : les pâtes doivent être cuites et crémeuses, plus de liquide libre.
A80: Étape 6 | B80: Hors du feu, ajouter 50 g de crème épaisse et 30 g de grana padano râpé. Poivrer (pas de sel). Mélanger.
A81: Étape 7 | B81: Servir la moitié aussitôt. L'autre moitié en boîte ; réchauffer 3 min à la poêle avec 3 cs d'eau.
A83: Mercredi — 5. Pâtes à la « carbonara » à la française — 20 min (5 + 15)
A84: Ingrédients (2 portions) | B84: Pâtes sèches (spaghetti, penne…) : 250 g ; Crème fraîche (liquide ou épaisse) : 250 ml ; Jaune d'œuf : 36 g ; Lardons fumés : 120 g ; Oignon : 100 g ; Sel : 2 g ; Poivre : 2 g
A85: Étape 1 | B85: Porter une grande casserole d'eau salée à ébullition. Cuire 250 g de spaghetti (temps du paquet, al dente).
A86: Étape 2 | B86: Émincer 100 g d'oignon (1 oignon). Le faire revenir 4 min dans une poêle sans matière grasse à feu moyen. Quand il est doré, ajouter 120 g de lardons et cuire 4 min jusqu'à coloration.
A87: Étape 3 | B87: Dans un bol, mélanger 250 ml de crème fluide, 2 jaunes d'œufs (garder les blancs pour une omelette), 1 pincée de sel et beaucoup de poivre.
A88: Étape 4 | B88: Retirer la poêle du feu et verser les lardons-oignon dans le bol de crème. Mélanger.
A89: Étape 5 | B89: Égoutter les pâtes (garder 1 louche d'eau de cuisson). Les remettre dans la casserole hors du feu, verser la crème aux lardons, mélanger 1 min. Si trop épais, détendre avec un peu d'eau de cuisson. Ne pas faire bouillir (les jaunes cuiraient).
A90: Étape 6 | B90: Servir la moitié aussitôt. L'autre moitié en boîte au frigo ; réchauffer à la poêle 3 min avec 2 cs d'eau.
A92: Jeudi — 14. Risotto aux lardons et champignons — 36 min (annoncé) — ≈ 30 min réel
A93: Ingrédients (2 portions) | B93: Riz spécial risotto (arborio / riz rond) : 220 g ; Lardons fumés : 150 g ; Champignons de Paris frais : 250 g ; Oignon : 100 g ; Crème liquide : 160 ml ; Cube de bouillon de volaille : 10 g ; Eau : 750 ml ; Huile d'olive : 20 ml ; Parmesan râpé (facultatif) : 30 g ; Poivre : 1 g ; Sel : 0 g
A94: Étape 1 | B94: Chauffer 750 ml d'eau dans une casserole avec 1 cube de bouillon (10 g). Garder à frémissement.
A95: Étape 2 | B95: Ciseler 100 g d'oignon. Égoutter 250 g de champignons de boîte (ou émincer 250 g de frais).
A96: Étape 3 | B96: Dans une poêle profonde ou une sauteuse, chauffer 10 ml d'huile, faire colorer les champignons 5 min, puis ajouter 150 g de lardons et cuire 4 min. Retirer l'excès de gras, réserver le tout.
A97: Étape 4 | B97: Dans la même sauteuse, chauffer 10 ml d'huile, faire suer l'oignon 3 min, puis ajouter 220 g de riz pour risotto et remuer 1-2 min jusqu'à ce que les grains soient nacrés.
A98: Étape 5 | B98: Ajouter une louche de bouillon chaud, mélanger à feu doux jusqu'à absorption. Recommencer louche par louche pendant 18-20 min, en remuant souvent, jusqu'à ce que le riz soit tendre et crémeux (goûter).
A99: Étape 6 | B99: Remettre les lardons et les champignons, mélanger.
A100: Étape 7 | B100: Hors du feu, ajouter 160 ml de crème fluide et 30 g de grana padano râpé. Poivrer ; ne pas saler (cube + lardons + fromage).
A101: Étape 8 | B101: Servir la moitié aussitôt. L'autre moitié en boîte ; réchauffer 3 min à la poêle avec 3-4 cs d'eau pour redonner du crémeux.
A103: Vendredi — 20. One pot pasta chorizo-basilic — 30 min (annoncé) — ≈ 25 min
A104: Ingrédients (2 portions) | B104: Pâtes sèches (spaghetti ou linguine) : 250 g ; Eau : 600 ml ; Tomates cerises : 150 g ; Oignon : 100 g ; Ail : 6 g ; Huile d'olive : 16 ml ; Chorizo : 150 g ; Basilic frais : 6 g ; Parmesan râpé (optionnel) : 20 g ; Sel : 2 g ; Poivre : 1 g
A105: Étape 1 | B105: Faire chauffer 600 ml d'eau dans une casserole large ou une sauteuse.
A106: Étape 2 | B106: Pendant ce temps : tailler 100 g d'oignon et 1 gousse d'ail (ou 6 g de semoule) en lamelles, couper 150 g de tomates cerises en 4, 150 g de chorizo en lamelles, ciseler 8-10 feuilles de basilic (ou 2 g de séché).
A107: Étape 3 | B107: Quand l'eau bout : ajouter 15 ml d'huile d'olive, 2 pincées de sel, du poivre, tous les ingrédients préparés (sauf le parmesan), puis 250 g de spaghetti.
A108: Étape 4 | B108: Laisser cuire ≈ 20 min à feu moyen en remuant régulièrement (surtout les 3 premières minutes pour séparer les pâtes). C'est prêt quand toute l'eau est absorbée et que la sauce nappe. Rajouter 5 cl d'eau chaude si ça accroche avant que les pâtes soient cuites.
A109: Étape 5 | B109: Saupoudrer 20 g de grana padano râpé. Servir la moitié ; l'autre moitié en boîte, réchauffer 3 min à la poêle avec 3 cs d'eau.

Sheet S6
A1: Semaine 6 — total 54.84 € (marge 0.16 €) — retrait Chronodrive le dimanche
A3: PLANNING
A4: Jour | B4: Midi | C4: Soir | D4: kcal / portion (soir) | E4: À cuisiner ce jour | F4: Note | G4: Macros / portion (P / G / L en g)
A5: Dimanche (retrait) | B5: libre / reste | C5: Pizza : Auchan Pizza chorizo-poivrons 390 g | D5: ≈ 900 | E5: Four 12 min | F5: Retrait du drive le matin
A6: Lundi | B6: Portion 2 de la pizza / reste | C6: 3. Croque-monsieur express | D6: =ROUND(Nutrition!H41,0) -> 766 | E6: 25 min (5 + 20) — 2 portions | G6: =ROUND(Nutrition!I41,0)&" / "&ROUND(Nutrition!J41,0)&" / "&ROUND(Nutrition!K41,0) -> 44 / 71 / 33
A7: Mardi | B7: Portion 2 de : Croque-monsieur express | C7: 8. Pâtes au pesto rosso et au poulet (+ parmesan) | D7: =ROUND(Nutrition!H119,0) -> 941 | E7: 20 min (5 + 15) — 2 portions | G7: =ROUND(Nutrition!I119,0)&" / "&ROUND(Nutrition!J119,0)&" / "&ROUND(Nutrition!K119,0) -> 51 / 97 / 38
A8: Mercredi | B8: Portion 2 de : Pâtes au pesto rosso et au poulet (+ parmesan) | C8: 12. Ravioli poêlés à la tomate et mozzarella | D8: =ROUND(Nutrition!H186,0) -> 908 | E8: 15 min — 2 portions | F8: Ravioles du Dauphiné (13,54 €/kg) → ravioli Auchan aux fromages (5,63 €/kg), même geste poêlé ; coulis → pulpe. | G8: =ROUND(Nutrition!I186,0)&" / "&ROUND(Nutrition!J186,0)&" / "&ROUND(Nutrition!K186,0) -> 41 / 94 / 40
A9: Jeudi | B9: Portion 2 de : Ravioli poêlés à la tomate et mozzarella | C9: 22. Frittata d'été aux courgettes et mozzarella filante (+ pain) | D9: =ROUND(Nutrition!H356,0) -> 716 | E9: 20 min — 2 portions | F9: Tomate → tomates cerises 125 g ; pain = ½ mini-baguette précuite x2 (80 g). | G9: =ROUND(Nutrition!I356,0)&" / "&ROUND(Nutrition!J356,0)&" / "&ROUND(Nutrition!K356,0) -> 36 / 45 / 42
A10: Vendredi | B10: Portion 2 de : Frittata d'été aux courgettes et mozzarella filante (+ pain) | C10: 1. Poulet au curry, lait de coco et noix de cajou + riz | D10: =ROUND(Nutrition!H15,0) -> 885 | E10: 25 min (10 + 15) — 2 portions | G10: =ROUND(Nutrition!I15,0)&" / "&ROUND(Nutrition!J15,0)&" / "&ROUND(Nutrition!K15,0) -> 42 / 75 / 46
A11: Samedi | B11: Portion 2 de : Poulet au curry, lait de coco et noix de cajou + riz | C11: ½ Auchan Paëlla poulet-crevettes-chorizo 900 g | D11: ≈ 900-1 000 | E11: Poêle / micro-ondes | F11: Sachet coupé en 2 (congélateur)
A12: Dimanche midi | B12: ½ Auchan Paëlla poulet-crevettes-chorizo 900 g | C12: → pizza de la semaine suivante
A14: LISTE DE COURSES CHRONODRIVE — formats entiers
A15: Produit exact (Chronodrive) | B15: Rayon | C15: Qté à acheter | D15: Prix unitaire € | E15: Total € | F15: Besoin semaine (2 portions x 5) | G15: Acheté | H15: Unité | I15: Reste après la semaine | J15: dont gâchis estimé € | K15: dont stock (se garde) € | L15: Sert aux recettes
A16: Herta Le Bon Paris 4 tranches 140 g | B16: Charcuterie | C16: 1 | D16: 2.59 | E16: =C16*D16 -> 2.59 | F16: 140 | G16: 140 | H16: g | I16: 0 | J16: 0 | K16: 0 | L16: 3
A17: Auchan crème épaisse légère 15 % 20 cl | B17: Crèmerie | C17: 1 | D17: 0.75 | E17: =C17*D17 -> 0.75 | F17: 150 | G17: 200 | H17: ml | I17: 50 | J17: 0.05625 | K17: 0.13125 | L17: 3, 8
A18: Auchan emmental râpé 3 x 70 g | B18: Crèmerie | C18: 1 | D18: 2.09 | E18: =C18*D18 -> 2.09 | F18: 180 | G18: 210 | H18: g | I18: 30 | J18: 0.059714286 | K18: 0.23885714 | L18: 3, 12
A19: Auchan Tavola grana padano râpé 60 g | B19: Crèmerie | C19: 1 | D19: 1.19 | E19: =C19*D19 -> 1.19 | F19: 60 | G19: 60 | H19: g | I19: 0 | J19: 0 | K19: 0 | L19: 8
A20: Casa Azzurra mozzarella 125 g | B20: Crèmerie | C20: 1 | D20: 1.15 | E20: =C20*D20 -> 1.15 | F20: 124 | G20: 125 | H20: g | I20: 1 | J20: 0.0092 | K20: 0 | L20: 22
A21: Auchan œufs plein air x6 | B21: Crèmerie | C21: 1 | D21: 1.69 | E21: =C21*D21 -> 1.69 | F21: 220 | G21: 330 | H21: g | I21: 110 | J21: 0 | K21: 0.56333333 | L21: 22
A22: Auchan ravioli aux fromages 300 g | B22: Frais | C22: 2 | D22: 1.69 | E22: =C22*D22 -> 3.38 | F22: 500 | G22: 600 | H22: g | I22: 100 | J22: 0.56333333 | K22: 0 | L22: 12
A23: Citron jaune 1 pièce | B23: Fruits & légumes | C23: 1 | D23: 0.85 | E23: =C23*D23 -> 0.85 | F23: 50 | G23: 100 | H23: g | I23: 50 | J23: 0.2125 | K23: 0.2125 | L23: 22
A24: Courgette 1 pièce | B24: Fruits & légumes | C24: 2 | D24: 0.99 | E24: =C24*D24 -> 1.98 | F24: 350 | G24: 500 | H24: g | I24: 150 | J24: 0.594 | K24: 0 | L24: 22
A25: Tomates cerises 250 g | B25: Fruits & légumes | C25: 2 | D25: 0.99 | E25: =C25*D25 -> 1.98 | F25: 370 | G25: 500 | H25: g | I25: 130 | J25: 0.5148 | K25: 0 | L25: 12, 22
A26: Auchan filets de poulet blanc 260 g | B26: Viande | C26: 2 | D26: 3.89 | E26: =C26*D26 -> 7.78 | F26: 460 | G26: 520 | H26: g | I26: 60 | J26: 0.89769231 | K26: 0 | L26: 1, 8
A27: Auchan Recette d'Asie lait de coco 20 cl | B27: Épicerie | C27: 1 | D27: 0.95 | E27: =C27*D27 -> 0.95 | F27: 200 | G27: 200 | H27: ml | I27: 0 | J27: 0 | K27: 0 | L27: 1
... A33: Auchan spaghetti 500 g | B33: Épicerie | C33: 1 | D33: 0.75 | E33: =C33*D33 -> 0.75 | F33: 250 | G33: 500 | H33: g | I33: 250 | J33: 0 | K33: 0.375 | L33: 8
A34: TOTAL COURSES RECETTES | E34: =SUM(E16:E33) -> 34.38 | J34: =SUM(J16:J33) -> 3.7117794 | K34: =SUM(K16:K33) -> 4.5979572
A35: Auchan Paëlla poulet-crevettes-chorizo 900 g | B35: Surgelé (week-end) | C35: 1 | D35: 4.95 | E35: =C35*D35 -> 4.95 | L35: Samedi soir + dimanche midi
A36: Auchan Pizza chorizo-poivrons 390 g | B36: Surgelé (week-end) | C36: 1 | D36: 3.09 | E36: =C36*D36 -> 3.09 | L36: Dimanche soir
A37: TOTAL PANIER (recettes + week-end) | E37: =E34+E35+E36 -> 42.42
A39: PLACARD / BASES utilisées cette semaine — comptées au PRIX PLEIN du format
A40: Produit exact | B40: Rayon | C40: Qté | D40: Prix format € | E40: Total € | F40: Qté utilisée cette semaine | G40: Contenu format | H40: Unité | I40: Reste (stock) | K40: Valeur du reste € | L40: Sert aux recettes
A41: Ail semoule | B41: Placard | C41: 1 | D41: 1.29 | E41: =C41*D41 -> 1.29 | F41: 6 | G41: 55 | H41: g | I41: 49 | K41: =D41*I41/G41 -> 1.1492727 | L41: 22
A42: Basilic séché Ducros ≈ 12 g | B42: Placard | C42: 1 | D42: 1.8 | E42: =C42*D42 -> 1.8 | F42: 4 | G42: 12 | H42: g | I42: 8 | K42: =D42*I42/G42 -> 1.2 | L42: 12
A43: Curry en poudre Ducros 47 g | B43: Placard | C43: 1 | D43: 2.15 | E43: =C43*D43 -> 2.15 | F43: 4 | G43: 47 | H43: g | I43: 43 | K43: =D43*I43/G43 -> 1.9670213 | L43: 1
A44: Farine T45 | B44: Placard | C44: 1 | D44: 0.95 | E44: =C44*D44 -> 0.95 | F44: 10 | G44: 1000 | H44: g | I44: 990 | K44: =D44*I44/G44 -> 0.9405 | L44: 1
A45: Huile de tournesol | B45: Placard | C45: 1 | D45: 2.15 | E45: =C45*D45 -> 2.15 | F45: 86 | G45: 1000 | H45: ml | I45: 914 | K45: =D45*I45/G45 -> 1.9651 | L45: 1, 8, 12, 22
A46: Origan Ducros 12 g | B46: Placard | C46: 1 | D46: 1.89 | E46: =C46*D46 -> 1.89 | F46: 1 | G46: 12 | H46: g | I46: 11 | K46: =D46*I46/G46 -> 1.7325 | L46: 22
A47: Sauce soja | B47: Placard | C47: 1 | D47: 1.69 | E47: =C47*D47 -> 1.69 | F47: 10 | G47: 150 | H47: ml | I47: 140 | K47: =D47*I47/G47 -> 1.5773333 | L47: 1
A48: Sel / poivre | B48: Placard | C48: 1 | D48: 0.5 | E48: =C48*D48 -> 0.5 | F48: 12 | G48: 100 | H48: g | I48: 88 | K48: =D48*I48/G48 -> 0.44 | L48: 1, 3, 8, 12, 22
A49: TOTAL placard (prix plein) | E49: =SUM(E41:E48) -> 12.42
A51: BUDGET
A52: Panier recettes + week-end | E52: =E37 -> 42.42
A53: + placard / bases au prix plein | E53: =E49 -> 12.42
A54: TOTAL PANIER CHRONODRIVE DE LA SEMAINE | E54: =E37+E49 -> 54.84
A55: Budget max | E55: 55
A56: Marge | E56: =E55-E54 -> 0.16
A57: Gâchis estimé (périssable non consommé) | E57: =J34 -> 3.7117794
A58: Gâchis en % du panier | E58: =J34/E37 -> 0.087500692
A59: Reste non périssable (stock) | E59: =K34 -> 4.5979572
A60: Coût par portion (14 repas) | E60: =(E37+E49)/14 -> 3.9171429
A61: Si le placard est déjà plein chez toi, le panier réel redescend à | E61: =E37 -> 42.42
A64: ÉTAPES DES 5 RECETTES DE LA SEMAINE (2 portions chacune)
A65: Lundi — 3. Croque-monsieur express — 25 min (5 + 20)
A66: Ingrédients (2 portions) | B66: Pain de mie (tranches carrées) : 320 g ; Crème fraîche épaisse : 120 g ; Gruyère / emmental râpé : 100 g ; Jambon blanc : 140 g ; Sel : 1 g ; Poivre : 1 g
A67: Étape 1 | B67: Préchauffer le four à 210 °C (thermostat 7). Sans four : prévoir une grande poêle avec couvercle.
A68: Étape 2 | B68: Dans un bol, mélanger 120 g de crème fraîche épaisse (6 cs) et 100 g d'emmental râpé. Saler une pincée, poivrer.
A69: Étape 3 | B69: Poser 4 tranches de pain de mie. Étaler le mélange crème-fromage sur chacune. Poser 1 tranche de jambon pliée (140 g au total = 4 tranches) sur chaque tranche de pain.
A70: Étape 4 | B70: Refermer chaque croque avec une 5e-8e tranche de pain, elle aussi tartinée du mélange côté intérieur. Étaler le reste du mélange sur le dessus des 4 croques.
A71: Étape 5 | B71: Four : 20 min à mi-hauteur, jusqu'à ce que le dessus soit doré. Poêle : 1 noix de beurre, feu moyen, couvercle, 4 min par face.
A72: Étape 6 | B72: Manger 2 croques chauds. Les 2 autres : les monter mais ne les cuire que le lendemain midi (8 min à la poêle couverte), c'est bien meilleur que réchauffé.
A74: Mardi — 8. Pâtes au pesto rosso et au poulet (+ parmesan) — 20 min (5 + 15)
A75: Ingrédients (2 portions) | B75: Farfalle (ou autres pâtes courtes) : 250 g ; Filet de poulet : 200 g ; Crème fraîche : 30 ml ; Pesto rosso (pot) : 100 ml ; Parmesan râpé : 60 g ; Huile : 10 ml ; Sel : 2 g ; Poivre : 1 g
A76: Étape 1 | B76: Porter une grande casserole d'eau salée à ébullition. Cuire 250 g de spaghetti ou farfalle (temps du paquet).
A77: Étape 2 | B77: Couper 200 g de filet de poulet en lanières fines. Saler, poivrer.
A78: Étape 3 | B78: 5 min avant la fin des pâtes : chauffer 10 ml d'huile dans une poêle, faire dorer le poulet 4-5 min à feu vif.
A79: Étape 4 | B79: Baisser le feu, ajouter 30 ml de crème (2 cs) et 100 ml de pesto rosso (½ pot). Mélanger, réchauffer 1 min.
A80: Étape 5 | B80: Égoutter les pâtes, les verser dans la poêle, mélanger, cuire encore 3 min à feu doux.
A81: Étape 6 | B81: Servir la moitié avec 30 g de grana padano râpé par-dessus (ton ajout). L'autre moitié en boîte ; ajouter le fromage seulement au moment de manger le lendemain.
A83: Mercredi — 12. Ravioli poêlés à la tomate et mozzarella — 15 min
A84: Ingrédients (2 portions) | B84: Ravioli frais aux fromages (remplace les ravioles) : 500 g ; Tomates cerises : 120 g ; Coulis de tomate : 160 ml ; Mozzarella râpée (ou emmental) : 80 g ; Basilic frais : 4 g ; Eau : 60 ml ; Huile d'olive : 16 ml ; Sel : 1 g ; Poivre : 1 g
A85: Étape 1 | B85: Effeuiller 4-5 feuilles de basilic (ou prévoir 2 g de basilic séché pour la fin). Couper 120 g de tomates cerises en deux.
A86: Étape 2 | B86: Chauffer 15 ml d'huile dans une grande poêle à feu moyen. Y verser 500 g de raviolis frais aux fromages CRUS (sans les cuire à l'eau : ils se séparent à la cuisson) avec les tomates cerises. Cuire 6-7 min en remuant régulièrement jusqu'à ce que les raviolis dorent ; baisser le feu si ça colore trop.
A87: Étape 3 | B87: Verser 160 g de pulpe de tomate et 60 ml d'eau. Saler, poivrer. Couvrir et cuire 5 min à feu doux : les raviolis finissent de cuire dans la sauce.
A88: Étape 4 | B88: Ôter le couvercle, parsemer 80 g de mozzarella (déchirée ou râpée). Couvrir de nouveau 2-3 min à feu doux pour la faire fondre.
A89: Étape 5 | B89: Servir la moitié parsemée de basilic. L'autre moitié en boîte au frigo ; réchauffer 3 min à la poêle couverte avec 1 cs d'eau.
A91: Jeudi — 22. Frittata d'été aux courgettes et mozzarella filante (+ pain) — 20 min
A92: Ingrédients (2 portions) | B92: Œufs : 220 g ; Courgette : 350 g ; Tomates cerises : 250 g ; Mozzarella (boule) : 124 g ; Ail : 6 g ; Citron (zeste) : 50 g ; Origan séché : 1 g ; Huile d'olive : 30 ml ; Pain (baguette ou pain de mie) : 160 g ; Sel : 1 g ; Poivre : 1 g
A93: Étape 1 | B93: Laver 350 g de courgette (1 grosse ou 2 petites), couper en fines rondelles. Couper 250 g de tomates cerises en deux. Hacher 1 gousse d'ail (ou 6 g de semoule).
A94: Étape 2 | B94: Dans une poêle de 24-26 cm avec couvercle, chauffer 30 ml d'huile à feu moyen-vif. Faire revenir les courgettes et l'ail 8 min en remuant, jusqu'à ce qu'elles soient tendres et dorées.
A95: Étape 3 | B95: Ajouter les tomates cerises et 1 g d'origan, faire dorer 2 min.
A96: Étape 4 | B96: Dans un saladier, battre 4 œufs avec 1 pincée de sel et du poivre.
A97: Étape 5 | B97: Baisser à feu doux, verser les œufs sur les légumes, répartir. Couvrir, cuire 8 min : le dessus doit être pris mais moelleux.
A98: Étape 6 | B98: En fin de cuisson, zester ½ citron sur la frittata (râpe fine).
A99: Étape 7 | B99: Faire glisser la frittata sur une assiette, déchirer 125 g de mozzarella dessus pour qu'elle fonde à la chaleur. Arroser d'un filet d'huile.
A100: Étape 8 | B100: Servir la moitié avec 1 mini-baguette (80 g, 8 min au grille-pain ou 5 min à la poêle couverte). L'autre moitié en boîte au frigo, se mange froide ou 1 min au micro-ondes, avec la 2e mini-baguette.
A102: Vendredi — 1. Poulet au curry, lait de coco et noix de cajou + riz — 25 min (10 + 15)
A103: Ingrédients (2 portions) | B103: Filet de poulet : 260 g ; Lait de coco : 200 ml ; Curry en poudre : 4 g ; Sauce soja : 10 ml ; Noix de cajou grillées salées : 40 g ; Maïzena : 10 g ; Huile : 30 ml ; Riz long cru : 160 g ; Sel : 2 g ; Poivre : 1 g
A104: Étape 1 | B104: Riz : verser 160 g de riz long dans une casserole avec 240 ml d'eau et 1 pincée de sel. Porter à ébullition, couvrir, baisser à feu doux, cuire 11 min sans soulever le couvercle, puis couper le feu et laisser reposer 5 min à couvert.
A105: Étape 2 | B105: Concasser 40 g de noix de cajou (fond d'un verre dans une assiette creuse) : moitié poudre, moitié petits morceaux.
A106: Étape 3 | B106: Couper 260 g de filet de poulet en cubes de 1-2 cm. Les mettre dans un bol avec 10 g de farine (2 cc) et mélanger pour les enrober.
A107: Étape 4 | B107: Chauffer 30 ml d'huile (2 cs) dans une sauteuse à feu moyen-vif. Ajouter 4 g de curry (2 cc) et laisser chauffer 30 s jusqu'à ce que ça sente.
A108: Étape 5 | B108: Ajouter le poulet, faire dorer 5 min en remuant.
A109: Étape 6 | B109: Verser 10 ml de sauce soja (2 cc) puis 200 ml de lait de coco (1 brique). Mélanger, baisser à feu doux, laisser cuire 10 min : la sauce épaissit grâce à la farine.
A110: Étape 7 | B110: 5 min avant la fin, ajouter les noix de cajou. Saler légèrement, poivrer.
A111: Étape 8 | B111: Servir la moitié sur la moitié du riz. Laisser refroidir l'autre moitié (riz et sauce séparés) avant de mettre en boîte au frigo pour le lendemain midi.

Sheet S7
A1: Semaine 7 — total 66.70 € (marge -11.70 €) — retrait Chronodrive le dimanche
A3: PLANNING
A4: Jour | B4: Midi | C4: Soir | D4: kcal / portion (soir) | E4: À cuisiner ce jour | F4: Note | G4: Macros / portion (P / G / L en g)
A5: Dimanche (retrait) | B5: libre / reste | C5: Pizza : Ristorante margherita 355 g | D5: ≈ 900 | E5: Four 12 min | F5: Retrait du drive le matin
A6: Lundi | B6: Portion 2 de la pizza / reste | C6: 11. Raviolis frais à la sauce tomate-crème (poivron, épices) | D6: =ROUND(Nutrition!H171,0) -> 949 | E6: 25 min (10 + 15) — 2 portions | F6: Coulis/pulpe → pulpe concassée Auchan. | G6: =ROUND(Nutrition!I171,0)&" / "&ROUND(Nutrition!J171,0)&" / "&ROUND(Nutrition!K171,0) -> 37 / 102 / 43
A7: Mardi | B7: Portion 2 de : Raviolis frais à la sauce tomate-crème (poivron, épices) | C7: 13. Tortellini aux champignons, sauce crème-parmesan | D7: =ROUND(Nutrition!H204,0) -> 888 | E7: 20 min (8 + 12) — 2 portions | F7: Lait supprimé (eau de cuisson) ; parmesan = grana padano. | G7: =ROUND(Nutrition!I204,0)&" / "&ROUND(Nutrition!J204,0)&" / "&ROUND(Nutrition!K204,0) -> 33 / 93 / 41
A8: Mercredi | B8: Portion 2 de : Tortellini aux champignons, sauce crème-parmesan | C8: 18. Chakchouka au chèvre frais & pains pita | D8: =ROUND(Nutrition!H289,0) -> 741 | E8: 20 min en cuisine (30 min à table) — 2 portions | F8: Pita → pain kebab La Boulangère (2 x 80 g) ; chèvre frais 40 g. | G8: =ROUND(Nutrition!I289,0)&" / "&ROUND(Nutrition!J289,0)&" / "&ROUND(Nutrition!K289,0) -> 33 / 82 / 30
A9: Jeudi | B9: Portion 2 de : Chakchouka au chèvre frais & pains pita | C9: 14. Risotto aux lardons et champignons | D9: =ROUND(Nutrition!H221,0) -> 943 | E9: 36 min (annoncé) — ≈ 30 min réel — 2 portions | G9: =ROUND(Nutrition!I221,0)&" / "&ROUND(Nutrition!J221,0)&" / "&ROUND(Nutrition!K221,0) -> 29 / 96 / 48
A10: Vendredi | B10: Portion 2 de : Risotto aux lardons et champignons | C10: 20. One pot pasta chorizo-basilic | D10: =ROUND(Nutrition!H321,0) -> 944 | E10: 30 min (annoncé) — ≈ 25 min — 2 portions | G10: =ROUND(Nutrition!I321,0)&" / "&ROUND(Nutrition!J321,0)&" / "&ROUND(Nutrition!K321,0) -> 37 / 101 / 43
A11: Samedi | B11: Portion 2 de : One pot pasta chorizo-basilic | C11: ½ Bonduelle Poêlée gnocchi-épinards 750 g | D11: ≈ 900-1 000 | E11: Poêle / micro-ondes | F11: Sachet coupé en 2 (congélateur)
A12: Dimanche midi | B12: ½ Bonduelle Poêlée gnocchi-épinards 750 g | C12: → pizza de la semaine suivante
A14: LISTE DE COURSES CHRONODRIVE — formats entiers
A15: Produit exact (Chronodrive) | B15: Rayon | C15: Qté à acheter | D15: Prix unitaire € | E15: Total € | F15: Besoin semaine (2 portions x 5) | G15: Acheté | H15: Unité | I15: Reste après la semaine | J15: dont gâchis estimé € | K15: dont stock (se garde) € | L15: Sert aux recettes
A16: Auchan Terroir chorizo doux 225 g | B16: Charcuterie | C16: 1 | D16: 2.59 | E16: =C16*D16 -> 2.59 | F16: 150 | G16: 225 | H16: g | I16: 75 | J16: 0.259 | K16: 0.60433333 | L16: 20
A17: Auchan lardons fumés 2 x 100 g | B17: Charcuterie | C17: 1 | D17: 2.09 | E17: =C17*D17 -> 2.09 | F17: 150 | G17: 200 | H17: g | I17: 50 | J17: 0.26125 | K17: 0.26125 | L17: 14
A18: Auchan fromage de chèvre frais 200 g | B18: Crèmerie | C18: 1 | D18: 2.09 | E18: =C18*D18 -> 2.09 | F18: 80 | G18: 200 | H18: g | I18: 120 | J18: 0.8778 | K18: 0.3762 | L18: 18
A19: Auchan crème épaisse légère 15 % 20 cl | B19: Crèmerie | C19: 1 | D19: 0.75 | E19: =C19*D19 -> 0.75 | F19: 120 | G19: 200 | H19: ml | I19: 80 | J19: 0.09 | K19: 0.21 | L19: 13
A20: Auchan Essentiel crème fluide légère 15 % 20 cl | B20: Crèmerie | C20: 2 | D20: 0.69 | E20: =C20*D20 -> 1.38 | F20: 260 | G20: 400 | H20: ml | I20: 140 | J20: 0 | K20: 0.483 | L20: 11, 14
A21: Auchan Tavola grana padano râpé 120 g | B21: Crèmerie | C21: 1 | D21: 1.95 | E21: =C21*D21 -> 1.95 | F21: 110 | G21: 120 | H21: g | I21: 10 | J21: 0 | K21: 0.1625 | L21: 11, 13, 14, 20
A22: Auchan œufs plein air x6 | B22: Crèmerie | C22: 1 | D22: 1.69 | E22: =C22*D22 -> 1.69 | F22: 220 | G22: 330 | H22: g | I22: 110 | J22: 0 | K22: 0.56333333 | L22: 18
A23: Auchan ravioli aux fromages 300 g | B23: Frais | C23: 2 | D23: 1.69 | E23: =C23*D23 -> 3.38 | F23: 500 | G23: 600 | H23: g | I23: 100 | J23: 0.56333333 | K23: 0 | L23: 11
A24: Auchan Tavola tortellini 3 fromages 250 g | B24: Frais | C24: 2 | D24: 2.05 | E24: =C24*D24 -> 4.1 | F24: 400 | G24: 500 | H24: g | I24: 100 | J24: 0.82 | K24: 0 | L24: 13
A25: Oignon jaune 1 kg | B25: Fruits & légumes | C25: 1 | D25: 2.69 | E25: =C25*D25 -> 2.69 | F25: 420 | G25: 1000 | H25: g | I25: 580 | J25: 0.31204 | K25: 1.24816 | L25: 11, 13, 14, 18, 20
A26: Poivron rouge 1 pièce | B26: Fruits & légumes | C26: 2 | D26: 0.99 | E26: =C26*D26 -> 1.98 | F26: 230 | G26: 300 | H26: g | I26: 70 | J26: 0.462 | K26: 0 | L26: 11, 18
A27: Tomates cerises 250 g | B27: Fruits & légumes | C27: 1 | D27: 0.99 | E27: =C27*D27 -> 0.99 | F27: 150 | G27: 250 | H27: g | I27: 100 | J27: 0.396 | K27: 0 | L27: 20
... A32: Auchan spaghetti 500 g | B32: Épicerie | C32: 1 | D32: 0.75 | E32: =C32*D32 -> 0.75 | F32: 250 | G32: 500 | H32: g | I32: 250 | J32: 0 | K32: 0.375 | L32: 20
A33: TOTAL COURSES RECETTES | E33: =SUM(E16:E32) -> 34.04 | J33: =SUM(J16:J32) -> 4.6653826 | K33: =SUM(K16:K32) -> 5.2749642
A34: Bonduelle Poêlée gnocchi-épinards 750 g | B34: Surgelé (week-end) | C34: 1 | D34: 3.95 | E34: =C34*D34 -> 3.95 | L34: Samedi soir + dimanche midi
A35: Ristorante margherita 355 g | B35: Surgelé (week-end) | C35: 1 | D35: 3.09 | E35: =C35*D35 -> 3.09 | L35: Dimanche soir
A36: TOTAL PANIER (recettes + week-end) | E36: =E33+E34+E35 -> 41.08
A38: PLACARD / BASES utilisées cette semaine — comptées au PRIX PLEIN du format
A39: Produit exact | B39: Rayon | C39: Qté | D39: Prix format € | E39: Total € | F39: Qté utilisée cette semaine | G39: Contenu format | H39: Unité | I39: Reste (stock) | K39: Valeur du reste € | L39: Sert aux recettes
A40: Ail semoule | B40: Placard | C40: 1 | D40: 1.29 | E40: =C40*D40 -> 1.29 | F40: 18 | G40: 55 | H40: g | I40: 37 | K40: =D40*I40/G40 -> 0.86781818 | L40: 11, 13, 20
A41: Basilic séché Ducros ≈ 12 g | B41: Placard | C41: 1 | D41: 1.8 | E41: =C41*D41 -> 1.8 | F41: 8 | G41: 12 | H41: g | I41: 4 | K41: =D41*I41/G41 -> 0.6 | L41: 11, 20
A42: Beurre | B42: Placard | C42: 1 | D42: 2.45 | E42: =C42*D42 -> 2.45 | F42: 10 | G42: 250 | H42: g | I42: 240 | K42: =D42*I42/G42 -> 2.352 | L42: 13
A43: Bouillon cube | B43: Placard | C43: 1 | D43: 1.79 | E43: =C43*D43 -> 1.79 | F43: 10 | G43: 180 | H43: g | I43: 170 | K43: =D43*I43/G43 -> 1.6905556 | L43: 14
A44: Coriandre moulue Ducros ≈ 30 g | B44: Placard | C44: 1 | D44: 1.99 | E44: =C44*D44 -> 1.99 | F44: 3 | G44: 30 | H44: g | I44: 27 | K44: =D44*I44/G44 -> 1.791 | L44: 11, 18
A45: Farine T45 | B45: Placard | C45: 1 | D45: 0.95 | E45: =C45*D45 -> 0.95 | F45: 4 | G45: 1000 | H45: g | I45: 996 | K45: =D45*I45/G45 -> 0.9462 | L45: 13
A46: Huile de tournesol | B46: Placard | C46: 1 | D46: 2.15 | E46: =C46*D46 -> 2.15 | F46: 82 | G46: 1000 | H46: ml | I46: 918 | K46: =D46*I46/G46 -> 1.9737 | L46: 11, 13, 14, 18, 20
A47: Laurier Ducros ≈ 5 g | B47: Placard | C47: 1 | D47: 1.99 | E47: =C47*D47 -> 1.99 | F47: 1 | G47: 5 | H47: g | I47: 4 | K47: =D47*I47/G47 -> 1.592 | L47: 11
A48: Moutarde de Dijon | B48: Placard | C48: 1 | D48: 1.85 | E48: =C48*D48 -> 1.85 | F48: 6 | G48: 430 | H48: g | I48: 424 | K48: =D48*I48/G48 -> 1.824186 | L48: 13
A49: Origan Ducros 12 g | B49: Placard | C49: 1 | D49: 1.89 | E49: =C49*D49 -> 1.89 | F49: 1 | G49: 12 | H49: g | I49: 11 | K49: =D49*I49/G49 -> 1.7325 | L49: 18
A50: Paprika doux Ducros 40 g | B50: Placard | C50: 1 | D50: 1.99 | E50: =C50*D50 -> 1.99 | F50: 2 | G50: 40 | H50: g | I50: 38 | K50: =D50*I50/G50 -> 1.8905 | L50: 11
A51: Persillade Ducros ≈ 20 g | B51: Placard | C51: 1 | D51: 1.9 | E51: =C51*D51 -> 1.9 | F51: 2 | G51: 20 | H51: g | I51: 18 | K51: =D51*I51/G51 -> 1.71 | L51: 11
... A54: Thym Ducros ≈ 15 g | B54: Placard | C54: 1 | D54: 1.99 | E54: =C54*D54 -> 1.99 | F54: 1 | G54: 15 | H54: g | I54: 14 | K54: =D54*I54/G54 -> 1.8573333 | L54: 11
A55: TOTAL placard (prix plein) | E55: =SUM(E40:E54) -> 25.62
A57: BUDGET
A58: Panier recettes + week-end | E58: =E36 -> 41.08
A59: + placard / bases au prix plein | E59: =E55 -> 25.62
A60: TOTAL PANIER CHRONODRIVE DE LA SEMAINE | E60: =E36+E55 -> 66.7
A61: Budget max | E61: 55
A62: Marge | E62: =E61-E60 -> -11.7
A63: Gâchis estimé (périssable non consommé) | E63: =J33 -> 4.6653826
A64: Gâchis en % du panier | E64: =J33/E36 -> 0.11356822
A65: Reste non périssable (stock) | E65: =K33 -> 5.2749642
A66: Coût par portion (14 repas) | E66: =(E36+E55)/14 -> 4.7642857
A67: Si le placard est déjà plein chez toi, le panier réel redescend à | E67: =E36 -> 41.08
A70: ÉTAPES DES 5 RECETTES DE LA SEMAINE (2 portions chacune)
A71: Lundi — 11. Raviolis frais à la sauce tomate-crème (poivron, épices) — 25 min (10 + 15)
A72: Ingrédients (2 portions) | B72: Raviolis frais (3 fromages ou ricotta-épinards) : 500 g ; Oignon (ou échalote) : 60 g ; Huile d'olive : 20 ml ; Poivron vert (ou rouge) : 80 g ; Pulpe de tomate (boîte) : 200 g ; Ail : 6 g ; Persil (frais ou séché) : 2 g ; Paprika doux : 2 g ; Coriandre en poudre : 2 g ; Basilic (frais ou séché) : 2 g ; Thym : 1 g ; Laurier : 1 g ; Crème liquide entière : 100 ml ; Eau : 60 ml ; Parmesan râpé (finition) : 30 g ; Sel : 2 g ; Poivre : 1 g
A73: Étape 1 | B73: Porter une casserole d'eau salée à ébullition. Cuire 500 g de raviolis frais (2 barquettes de 250 g, ou 1 de 300 g + un peu) 2-3 min selon le paquet. Égoutter, réserver.
A74: Étape 2 | B74: Éplucher 60 g d'oignon et le couper en petits dés. Laver 80 g de poivron (½) et le couper en fines lamelles.
A75: Étape 3 | B75: Chauffer 20 ml d'huile dans une poêle. Faire revenir l'oignon 3 min ; dès qu'il colore, ajouter le poivron et laisser dorer 4 min en remuant.
A76: Étape 4 | B76: Verser 200 g de pulpe de tomate (½ boîte de 400 g) et 1 cc d'ail semoule (6 g). Ajouter 2 g de paprika, 2 g de coriandre en poudre, 2 g de basilic séché, 2 g de persillade, 1 pincée de thym, 1 feuille de laurier. Saler, poivrer. Laisser revenir 1 min.
A77: Étape 5 | B77: Verser 60 ml d'eau, laisser mijoter 5 bonnes minutes à feu doux.
A78: Étape 6 | B78: Ajouter 100 ml de crème fluide, laisser épaissir 1 min. Retirer le laurier.
A79: Étape 7 | B79: Déposer les raviolis dans la sauce, bien les enrober 1 min à feu doux.
A80: Étape 8 | B80: Servir la moitié avec 15 g de grana padano râpé. L'autre moitié en boîte ; réchauffer 2 min au micro-ondes ou 3 min à la poêle.
A82: Mardi — 13. Tortellini aux champignons, sauce crème-parmesan — 20 min (8 + 12)
A83: Ingrédients (2 portions) | B83: Tortellini frais (fromage ou viande) : 400 g ; Champignons de Paris frais (ou boîte égouttée) : 150 g ; Oignon jaune : 60 g ; Ail : 6 g ; Crème fraîche épaisse : 120 g ; Beurre : 10 g ; Huile d'olive : 10 ml ; Parmesan râpé : 30 g ; Moutarde de Dijon : 6 g ; Farine (option, pour lier) : 4 g ; Sel : 2 g ; Poivre : 1 g
A84: Étape 1 | B84: Égoutter 150 g de champignons de boîte (ou nettoyer 150 g de frais avec un linge et les émincer). Émincer 60 g d'oignon, hacher ½ gousse d'ail (ou 1 cc de semoule).
A85: Étape 2 | B85: Dans une grande poêle, faire fondre 10 g de beurre avec 10 ml d'huile à feu moyen-vif. Faire suer l'oignon 3 min ; quand il est translucide, ajouter l'ail 30 s.
A86: Étape 3 | B86: Ajouter les champignons. Ne pas trop remuer : les laisser rendre leur eau puis dorer, 5-6 min. Saler légèrement.
A87: Étape 4 | B87: Baisser le feu. Option : saupoudrer 4 g de farine (1 cc) et remuer 1 min pour lier.
A88: Étape 5 | B88: Mélanger 120 g de crème épaisse avec 6 g de moutarde (1 cc). Verser dans la poêle, ajouter 2-3 cs d'eau si trop épais. Laisser mijoter doucement 2-3 min.
A89: Étape 6 | B89: Pendant ce temps, cuire 400 g de tortellini dans l'eau bouillante salée 2-3 min (temps du paquet). Garder 4 cs d'eau de cuisson avant d'égoutter.
A90: Étape 7 | B90: Verser les tortellini égouttés dans la poêle avec l'eau de cuisson, ajouter 30 g de grana padano râpé, mélanger 1 min pour lier. Poivrer.
A91: Étape 8 | B91: Servir la moitié. L'autre moitié en boîte ; réchauffer 3 min à la poêle avec 2 cs d'eau.
A93: Mercredi — 18. Chakchouka au chèvre frais & pains pita — 20 min en cuisine (30 min à table)
A94: Ingrédients (2 portions) | B94: Œufs : 220 g ; Fromage de chèvre frais (ou feta) : 80 g ; Pains pita : 260 g ; Poivron rouge : 150 g ; Tomates pelées en boîte (avec jus) : 200 g ; Oignon jaune : 100 g ; Origan séché : 1 g ; Coriandre en poudre : 1 g ; Huile d'olive : 16 ml ; Sucre : 1 g ; Sel : 1 g ; Poivre : 1 g
A95: Étape 1 | B95: Émincer 100 g d'oignon. Couper 150 g de poivron rouge (1 poivron) en petits dés.
A96: Étape 2 | B96: Chauffer 15 ml d'huile dans une grande poêle avec couvercle à feu moyen. Faire suer l'oignon et le poivron 8 min en remuant. Saler, poivrer.
A97: Étape 3 | B97: Ajouter 200 g de pulpe de tomate (½ boîte), 1 g d'origan, 1 g de coriandre en poudre et 1 pincée de sucre. Mélanger, laisser mijoter à demi-couvert 10 min jusqu'à une sauce onctueuse.
A98: Étape 4 | B98: Former 4 petits puits dans la sauce à la cuillère. Casser 1 œuf dans chaque creux (4 œufs). Couvrir, cuire 5 min à feu doux : blanc opaque, jaune coulant.
A99: Étape 5 | B99: Pendant ce temps, réchauffer 2 pains kebab (ou pitas) au grille-pain, ou 1 min par face à la poêle sèche. Couper 80 g de chèvre frais en morceaux.
A100: Étape 6 | B100: Émietter le chèvre frais sur la chakchouka chaude. Servir la moitié (2 œufs) avec 2 pains pour saucer.
A101: Étape 7 | B101: Pour le lendemain : la moitié restante en boîte (les œufs se réchauffent 1 min au micro-ondes, le jaune ne sera plus coulant) — ou, mieux, ne cuire que 2 œufs le soir et pocher les 2 autres le lendemain midi dans la sauce réchauffée 3 min à la poêle. 2 pains supplémentaires.
A103: Jeudi — 14. Risotto aux lardons et champignons — 36 min (annoncé) — ≈ 30 min réel
A104: Ingrédients (2 portions) | B104: Riz spécial risotto (arborio / riz rond) : 220 g ; Lardons fumés : 150 g ; Champignons de Paris frais : 250 g ; Oignon : 100 g ; Crème liquide : 160 ml ; Cube de bouillon de volaille : 10 g ; Eau : 750 ml ; Huile d'olive : 20 ml ; Parmesan râpé (facultatif) : 30 g ; Poivre : 1 g ; Sel : 0 g
A105: Étape 1 | B105: Chauffer 750 ml d'eau dans une casserole avec 1 cube de bouillon (10 g). Garder à frémissement.
A106: Étape 2 | B106: Ciseler 100 g d'oignon. Égoutter 250 g de champignons de boîte (ou émincer 250 g de frais).
A107: Étape 3 | B107: Dans une poêle profonde ou une sauteuse, chauffer 10 ml d'huile, faire colorer les champignons 5 min, puis ajouter 150 g de lardons et cuire 4 min. Retirer l'excès de gras, réserver le tout.
A108: Étape 4 | B108: Dans la même sauteuse, chauffer 10 ml d'huile, faire suer l'oignon 3 min, puis ajouter 220 g de riz pour risotto et remuer 1-2 min jusqu'à ce que les grains soient nacrés.
A109: Étape 5 | B109: Ajouter une louche de bouillon chaud, mélanger à feu doux jusqu'à absorption. Recommencer louche par louche pendant 18-20 min, en remuant souvent, jusqu'à ce que le riz soit tendre et crémeux (goûter).
A110: Étape 6 | B110: Remettre les lardons et les champignons, mélanger.
A111: Étape 7 | B111: Hors du feu, ajouter 160 ml de crème fluide et 30 g de grana padano râpé. Poivrer ; ne pas saler (cube + lardons + fromage).
A112: Étape 8 | B112: Servir la moitié aussitôt. L'autre moitié en boîte ; réchauffer 3 min à la poêle avec 3-4 cs d'eau pour redonner du crémeux.
A114: Vendredi — 20. One pot pasta chorizo-basilic — 30 min (annoncé) — ≈ 25 min
A115: Ingrédients (2 portions) | B115: Pâtes sèches (spaghetti ou linguine) : 250 g ; Eau : 600 ml ; Tomates cerises : 150 g ; Oignon : 100 g ; Ail : 6 g ; Huile d'olive : 16 ml ; Chorizo : 150 g ; Basilic frais : 6 g ; Parmesan râpé (optionnel) : 20 g ; Sel : 2 g ; Poivre : 1 g
A116: Étape 1 | B116: Faire chauffer 600 ml d'eau dans une casserole large ou une sauteuse.
...

Sheet S8
A1: Semaine 8 — total 53.51 € (marge 1.49 €) — retrait Chronodrive le dimanche
A3: PLANNING
A4: Jour | B4: Midi | C4: Soir | D4: kcal / portion (soir) | E4: À cuisiner ce jour | F4: Note | G4: Macros / portion (P / G / L en g)
A5: Dimanche (retrait) | B5: libre / reste | C5: Pizza : Auchan Pizza poulet barbecue 390 g | D5: ≈ 900 | E5: Four 12 min | F5: Retrait du drive le matin
A6: Lundi | B6: Portion 2 de la pizza / reste | C6: 4. Hachis parmentier rapide (purée en flocons) | D6: =ROUND(Nutrition!H58,0) -> 737 | E6: 30 min (10 + 20) — 2 portions | F6: Lait → eau + crème pour la purée. | G6: =ROUND(Nutrition!I58,0)&" / "&ROUND(Nutrition!J58,0)&" / "&ROUND(Nutrition!K58,0) -> 40 / 58 / 39
A7: Mardi | B7: Portion 2 de : Hachis parmentier rapide (purée en flocons) | C7: 2. Gnocchis aux épinards, crème et lardons | D7: =ROUND(Nutrition!H29,0) -> 826 | E7: 12 min (5 + 7) — 2 portions | G7: =ROUND(Nutrition!I29,0)&" / "&ROUND(Nutrition!J29,0)&" / "&ROUND(Nutrition!K29,0) -> 29 / 87 / 41
A8: Mercredi | B8: Portion 2 de : Gnocchis aux épinards, crème et lardons | C8: 8. Pâtes au pesto rosso et au poulet (+ parmesan) | D8: =ROUND(Nutrition!H119,0) -> 941 | E8: 20 min (5 + 15) — 2 portions | G8: =ROUND(Nutrition!I119,0)&" / "&ROUND(Nutrition!J119,0)&" / "&ROUND(Nutrition!K119,0) -> 51 / 97 / 38
A9: Jeudi | B9: Portion 2 de : Pâtes au pesto rosso et au poulet (+ parmesan) | C9: 23. Pâtes pesto caprese (boule de mozzarella, tomates cerises) | D9: =ROUND(Nutrition!H369,0) -> 1050 | E9: 15 min (5 + 10) — 2 portions | F9: Version sans cuisson à part les pâtes ; 1 boule de mozzarella entière par portion (ton choix) ; lardons de la source supprimés. | G9: =ROUND(Nutrition!I369,0)&" / "&ROUND(Nutrition!J369,0)&" / "&ROUND(Nutrition!K369,0) -> 46 / 99 / 50
A10: Vendredi | B10: Portion 2 de : Pâtes pesto caprese (boule de mozzarella, tomates cerises) | C10: 7. Quesadillas chorizo-emmental & avocat (version éco) | D10: =ROUND(Nutrition!H105,0) -> 959 | E10: 20 min — 2 portions | F10: Version éco : cheddar + gouda → 60 g d'emmental ; ½ avocat (75 g) ; cuisson poêle. | G10: =ROUND(Nutrition!I105,0)&" / "&ROUND(Nutrition!J105,0)&" / "&ROUND(Nutrition!K105,0) -> 37 / 45 / 69
A11: Samedi | B11: Portion 2 de : Quesadillas chorizo-emmental & avocat (version éco) | C11: ½ Auchan Poêlée campagnarde 900 g | D11: ≈ 900-1 000 | E11: Poêle / micro-ondes | F11: Sachet coupé en 2 (congélateur)
A12: Dimanche midi | B12: ½ Auchan Poêlée campagnarde 900 g | C12: → pizza de la semaine suivante
A14: LISTE DE COURSES CHRONODRIVE — formats entiers
A15: Produit exact (Chronodrive) | B15: Rayon | C15: Qté à acheter | D15: Prix unitaire € | E15: Total € | F15: Besoin semaine (2 portions x 5) | G15: Acheté | H15: Unité | I15: Reste après la semaine | J15: dont gâchis estimé € | K15: dont stock (se garde) € | L15: Sert aux recettes
A16: Auchan chorizo doux 24 tranches 120 g | B16: Charcuterie | C16: 1 | D16: 1.85 | E16: =C16*D16 -> 1.85 | F16: 100 | G16: 120 | H16: g | I16: 20 | J16: 0.0925 | K16: 0.21583333 | L16: 7
A17: Auchan lardons fumés 2 x 100 g | B17: Charcuterie | C17: 1 | D17: 2.09 | E17: =C17*D17 -> 2.09 | F17: 120 | G17: 200 | H17: g | I17: 80 | J17: 0.418 | K17: 0.418 | L17: 2
A18: Auchan crème épaisse légère 15 % 20 cl | B18: Crèmerie | C18: 1 | D18: 0.75 | E18: =C18*D18 -> 0.75 | F18: 130 | G18: 200 | H18: ml | I18: 70 | J18: 0.07875 | K18: 0.18375 | L18: 7, 8
A19: Auchan Essentiel crème fluide légère 15 % 20 cl | B19: Crèmerie | C19: 1 | D19: 0.69 | E19: =C19*D19 -> 0.69 | F19: 200 | G19: 200 | H19: ml | I19: 0 | J19: 0 | K19: 0 | L19: 2
A20: Auchan emmental râpé 3 x 70 g | B20: Crèmerie | C20: 1 | D20: 2.09 | E20: =C20*D20 -> 2.09 | F20: 210 | G20: 210 | H20: g | I20: 0 | J20: 0 | K20: 0 | L20: 2, 4, 7
A21: Auchan Tavola grana padano râpé 120 g | B21: Crèmerie | C21: 1 | D21: 1.95 | E21: =C21*D21 -> 1.95 | F21: 90 | G21: 120 | H21: g | I21: 30 | J21: 0 | K21: 0.4875 | L21: 8, 23
A22: Casa Azzurra mozzarella 125 g | B22: Crèmerie | C22: 2 | D22: 1.15 | E22: =C22*D22 -> 2.3 | F22: 250 | G22: 250 | H22: g | I22: 0 | J22: 0 | K22: 0 | L22: 23
A23: Auchan gnocchi de pomme de terre à poêler 500 g | B23: Frais | C23: 1 | D23: 1.85 | E23: =C23*D23 -> 1.85 | F23: 500 | G23: 500 | H23: g | I23: 0 | J23: 0 | K23: 0 | L23: 2
A24: Avocat 1 pièce | B24: Fruits & légumes | C24: 1 | D24: 1.59 | E24: =C24*D24 -> 1.59 | F24: 150 | G24: 150 | H24: g | I24: 0 | J24: 0 | K24: 0 | L24: 7
A25: Oignon jaune 1 kg | B25: Fruits & légumes | C25: 1 | D25: 2.69 | E25: =C25*D25 -> 2.69 | F25: 240 | G25: 1000 | H25: g | I25: 760 | J25: 0.40888 | K25: 1.63552 | L25: 2, 4
A26: Bonduelle pousses d'épinard 100 g | B26: Fruits & légumes | C26: 1 | D26: 1.95 | E26: =C26*D26 -> 1.95 | F26: 100 | G26: 100 | H26: g | I26: 0 | J26: 0 | K26: 0 | L26: 2
A27: Tomates cerises 250 g | B27: Fruits & légumes | C27: 1 | D27: 0.99 | E27: =C27*D27 -> 0.99 | F27: 250 | G27: 250 | H27: g | I27: 0 | J27: 0 | K27: 0 | L27: 23
... A35: Auchan tortillas de blé 8 pièces 320 g | B35: Épicerie | C35: 1 | D35: 2.05 | E35: =C35*D35 -> 2.05 | F35: 160 | G35: 320 | H35: g | I35: 160 | J35: 0.5125 | K35: 0.5125 | L35: 7
A36: TOTAL COURSES RECETTES | E36: =SUM(E16:E35) -> 39.93 | J36: =SUM(J16:J35) -> 4.9297466 | K36: =SUM(K16:K35) -> 6.6022277
A37: Auchan Poêlée campagnarde 900 g | B37: Surgelé (week-end) | C37: 1 | D37: 4.95 | E37: =C37*D37 -> 4.95 | L37: Samedi soir + dimanche midi
A38: Auchan Pizza poulet barbecue 390 g | B38: Surgelé (week-end) | C38: 1 | D38: 2.99 | E38: =C38*D38 -> 2.99 | L38: Dimanche soir
A39: TOTAL PANIER (recettes + week-end) | E39: =E36+E37+E38 -> 47.87
A41: PLACARD / BASES utilisées cette semaine — comptées au PRIX PLEIN du format
A42: Produit exact | B42: Rayon | C42: Qté | D42: Prix format € | E42: Total € | F42: Qté utilisée cette semaine | G42: Contenu format | H42: Unité | I42: Reste (stock) | K42: Valeur du reste € | L42: Sert aux recettes
A43: Huile de tournesol | B43: Placard | C43: 1 | D43: 2.15 | E43: =C43*D43 -> 2.15 | F43: 44 | G43: 1000 | H43: ml | I43: 956 | K43: =D43*I43/G43 -> 2.0554 | L43: 4, 7, 8
A44: Persillade Ducros ≈ 20 g | B44: Placard | C44: 1 | D44: 1.9 | E44: =C44*D44 -> 1.9 | F44: 4 | G44: 20 | H44: g | I44: 16 | K44: =D44*I44/G44 -> 1.52 | L44: 4
A45: Sel / poivre | B45: Placard | C45: 1 | D45: 0.5 | E45: =C45*D45 -> 0.5 | F45: 14 | G45: 100 | H45: g | I45: 86 | K45: =D45*I45/G45 -> 0.43 | L45: 2, 4, 7, 8, 23
A46: Vinaigre de cidre | B46: Placard | C46: 1 | D46: 1.09 | E46: =C46*D46 -> 1.09 | F46: 4 | G46: 750 | H46: ml | I46: 746 | K46: =D46*I46/G46 -> 1.0841867 | L46: 7
A47: TOTAL placard (prix plein) | E47: =SUM(E43:E46) -> 5.64
A49: BUDGET
A50: Panier recettes + week-end | E50: =E39 -> 47.87
A51: + placard / bases au prix plein | E51: =E47 -> 5.64
A52: TOTAL PANIER CHRONODRIVE DE LA SEMAINE | E52: =E39+E47 -> 53.51
A53: Budget max | E53: 55
A54: Marge | E54: =E53-E52 -> 1.49
A55: Gâchis estimé (périssable non consommé) | E55: =J36 -> 4.9297466
A56: Gâchis en % du panier | E56: =J36/E39 -> 0.10298196
A57: Reste non périssable (stock) | E57: =K36 -> 6.6022277
A58: Coût par portion (14 repas) | E58: =(E39+E47)/14 -> 3.8221429
A59: Si le placard est déjà plein chez toi, le panier réel redescend à | E59: =E39 -> 47.87
A62: ÉTAPES DES 5 RECETTES DE LA SEMAINE (2 portions chacune)
A63: Lundi — 4. Hachis parmentier rapide (purée en flocons) — 30 min (10 + 20)
A64: Ingrédients (2 portions) | B64: Steak haché / viande hachée de bœuf : 300 g ; Oignon : 140 g ; Tomate : 80 g ; Huile d'olive : 20 ml ; Purée en flocons (sèche) : 120 g ; Lait : 200 ml ; Eau : 400 ml ; Fromage râpé : 50 g ; Persillade (ail + persil séchés) : 4 g ; Sel : 2 g ; Poivre : 1 g
A65: Étape 1 | B65: Éplucher et émincer finement 140 g d'oignon (1 gros). Faire revenir dans 10 ml d'huile à feu moyen 5 min.
A66: Étape 2 | B66: Ajouter 300 g de haché bovin, l'émietter à la spatule, cuire 6-7 min jusqu'à ce qu'il soit bien cuit.
A67: Étape 3 | B67: Ajouter 80 g de pulpe de tomate (ou 1 petite tomate pelée en dés), 4 g de persillade, sel, poivre. Mélanger 2 min. Réserver.
A68: Étape 4 | B68: Purée : porter 400 ml d'eau + 100 ml de crème épaisse (ou 200 ml de lait si tu en as) à ébullition avec 1 pincée de sel. Hors du feu, verser 120 g de flocons de purée (1 sachet de 125 g) en pluie et fouetter 1 min. Ajouter 20 g de beurre.
A69: Étape 5 | B69: Dans un plat allant au four (ou dans la poêle si tu n'as pas de four) : étaler la viande au fond, couvrir de purée, tasser.
A70: Étape 6 | B70: Parsemer de 50 g d'emmental râpé, tasser légèrement.
A71: Étape 7 | B71: Four à 180 °C : 10 min, jusqu'à ce que le fromage gratine. Sans four : couvercle sur la poêle, 5 min à feu doux pour faire fondre.
A72: Étape 8 | B72: Servir la moitié. L'autre moitié en boîte au frigo, réchauffer 3 min au micro-ondes ou 15 min au four.
A74: Mardi — 2. Gnocchis aux épinards, crème et lardons — 12 min (5 + 7)
A75: Ingrédients (2 portions) | B75: Gnocchis (frais, à poêler ou à pocher) : 500 g ; Oignon : 100 g ; Lardons fumés : 120 g ; Parmesan râpé (ou emmental) : 40 g ; Crème liquide : 200 ml ; Pousses d'épinards : 100 g ; Sel : 2 g ; Poivre : 1 g
A76: Étape 1 | B76: Porter une casserole d'eau salée à ébullition. Y plonger 500 g de gnocchis 2-3 min : dès qu'ils remontent à la surface, égoutter et réserver.
A77: Étape 2 | B77: Émincer 100 g d'oignon (1 oignon) en petits dés.
A78: Étape 3 | B78: Dans une grande poêle, faire revenir l'oignon avec 120 g de lardons 3 min à feu moyen, sans matière grasse, jusqu'à coloration.
A79: Étape 4 | B79: Verser 200 ml de crème fluide (1 brique) et 40 g de grana padano râpé. Laisser réduire d'un quart, 3-4 min à petits bouillons.
A80: Étape 5 | B80: Ajouter 100 g de pousses d'épinard et les gnocchis. Mélanger, laisser mijoter 4 min : les épinards tombent, la sauce nappe.
A81: Étape 6 | B81: Poivrer généreusement, saler très peu (lardons + fromage salent déjà). Servir la moitié ; l'autre moitié en boîte au frigo, réchauffer 3 min à la poêle avec 1 cs d'eau.
A83: Mercredi — 8. Pâtes au pesto rosso et au poulet (+ parmesan) — 20 min (5 + 15)
A84: Ingrédients (2 portions) | B84: Farfalle (ou autres pâtes courtes) : 250 g ; Filet de poulet : 200 g ; Crème fraîche : 30 ml ; Pesto rosso (pot) : 100 ml ; Parmesan râpé : 60 g ; Huile : 10 ml ; Sel : 2 g ; Poivre : 1 g
A85: Étape 1 | B85: Porter une grande casserole d'eau salée à ébullition. Cuire 250 g de spaghetti ou farfalle (temps du paquet).
A86: Étape 2 | B86: Couper 200 g de filet de poulet en lanières fines. Saler, poivrer.
A87: Étape 3 | B87: 5 min avant la fin des pâtes : chauffer 10 ml d'huile dans une poêle, faire dorer le poulet 4-5 min à feu vif.
A88: Étape 4 | B88: Baisser le feu, ajouter 30 ml de crème (2 cs) et 100 ml de pesto rosso (½ pot). Mélanger, réchauffer 1 min.
A89: Étape 5 | B89: Égoutter les pâtes, les verser dans la poêle, mélanger, cuire encore 3 min à feu doux.
A90: Étape 6 | B90: Servir la moitié avec 30 g de grana padano râpé par-dessus (ton ajout). L'autre moitié en boîte ; ajouter le fromage seulement au moment de manger le lendemain.
A92: Jeudi — 23. Pâtes pesto caprese (boule de mozzarella, tomates cerises) — 15 min (5 + 10)
A93: Ingrédients (2 portions) | B93: Pâtes sèches (spaghetti ou courtes) : 250 g ; Pesto vert (pot) : 100 g ; Tomates cerises : 250 g ; Mozzarella (boule) : 250 g ; Parmesan râpé : 30 g ; Sel : 2 g ; Poivre : 1 g
A94: Étape 1 | B94: Porter une grande casserole d'eau à ébullition, saler. Cuire 250 g de pâtes selon le paquet (al dente).
A95: Étape 2 | B95: Pendant la cuisson : couper 250 g de tomates cerises en deux. Égoutter 2 boules de mozzarella (125 g chacune) et les déchirer à la main en morceaux de la taille d'une noix (pas au couteau : les bords irréguliers fondent mieux).
A96: Étape 3 | B96: Juste avant d'égoutter, prélever 1 louche d'eau de cuisson (≈ 100 ml). Égoutter les pâtes et les remettre aussitôt dans la casserole chaude, hors du feu.
A97: Étape 4 | B97: Ajouter 100 g de pesto vert et la moitié de l'eau de cuisson. Mélanger vigoureusement 30 s : le pesto devient une sauce crémeuse qui enrobe. Rajouter de l'eau si c'est sec.
A98: Étape 5 | B98: Ajouter les tomates et la mozzarella, mélanger 20 s seulement : la chaleur des pâtes tiédit les tomates et fait filer la mozzarella sans la cuire.
A99: Étape 6 | B99: Poivrer, parsemer 30 g de parmesan râpé. Servir la moitié aussitôt.
A100: Étape 7 | B100: Portion du lendemain : en boîte au frigo. Se mange froide (salade de pâtes de luxe) ou 2 min au micro-ondes avec 1 cs d'eau ; dans ce cas garder la 2e boule entière et la déchirer dessus après réchauffage.
A102: Vendredi — 7. Quesadillas chorizo-emmental & avocat (version éco) — 20 min
A103: Ingrédients (2 portions) | B103: Dés de chorizo : 100 g ; Tortillas de blé : 160 g ; Emmental râpé (remplace cheddar + gouda) : 120 g ; Avocat : 150 g ; Crème fraîche épaisse : 100 g ; Huile d'olive : 14 ml ; Vinaigre (balsamique blanc, riz ou cidre) : 4 ml ; Sel : 1 g ; Poivre : 1 g
A104: Étape 1 | B104: Couper 100 g de chorizo en petits dés (ou utiliser 100 g de chorizo en tranches coupées en 4).
A105: Étape 2 | B105: Chauffer une poêle à sec à feu moyen-vif. Griller le chorizo 3-4 min jusqu'à ce qu'il soit légèrement doré et rende son gras. Réserver.
A106: Étape 3 | B106: Poser 4 tortillas. Sur une moitié de chaque tortilla, répartir 120 g d'emmental râpé et le chorizo. Replier en deux et presser.
A107: Étape 4 | B107: Cuisson à la poêle (pas besoin de four) : avec 15 ml d'huile, feu moyen, 3 min par face en appuyant avec une spatule, jusqu'à ce que ce soit doré et que le fromage file. Faire en 2 fois.
A108: Étape 5 | B108: Guacamole express : couper 1 avocat en deux, retirer le noyau, prélever la chair à la cuillère, l'écraser à la fourchette avec 5 ml de vinaigre (1 cc), sel, poivre.
A109: Étape 6 | B109: Couper chaque quesadilla en 3 triangles. Servir 2 quesadillas avec la moitié du guacamole et 50 g de crème épaisse. Les 2 autres quesadillas se réchauffent 2 min à la poêle le lendemain ; le guacamole restant : filmer au contact avec un filet de citron ou de vinaigre.

Sheet S9
A1: Semaine 9 — total 69.24 € (marge -14.24 €) — retrait Chronodrive le dimanche
A3: PLANNING
A4: Jour | B4: Midi | C4: Soir | D4: kcal / portion (soir) | E4: À cuisiner ce jour | F4: Note | G4: Macros / portion (P / G / L en g)
A5: Dimanche (retrait) | B5: libre / reste | C5: Pizza : Auchan Pizza royale jambon-fromage-olives 400 g | D5: ≈ 900 | E5: Four 12 min | F5: Retrait du drive le matin
A6: Lundi | B6: Portion 2 de la pizza / reste | C6: 6. Poulet à la crème et aux champignons + spaghetti | D6: =ROUND(Nutrition!H90,0) -> 771 | E6: 35 min adaptées (10 + 25) — 2 portions | F6: Tagliatelles → spaghetti (même rôle, 3 x moins cher). Filet ou cuisse : filet. | G6: =ROUND(Nutrition!I90,0)&" / "&ROUND(Nutrition!J90,0)&" / "&ROUND(Nutrition!K90,0) -> 51 / 84 / 24
A7: Mardi | B7: Portion 2 de : Poulet à la crème et aux champignons + spaghetti | C7: 11. Raviolis frais à la sauce tomate-crème (poivron, épices) | D7: =ROUND(Nutrition!H171,0) -> 949 | E7: 25 min (10 + 15) — 2 portions | F7: Coulis/pulpe → pulpe concassée Auchan. | G7: =ROUND(Nutrition!I171,0)&" / "&ROUND(Nutrition!J171,0)&" / "&ROUND(Nutrition!K171,0) -> 37 / 102 / 43
A8: Mercredi | B8: Portion 2 de : Raviolis frais à la sauce tomate-crème (poivron, épices) | C8: 17. Poulet basquaise et son riz | D8: =ROUND(Nutrition!H271,0) -> 729 | E8: 30 min — 2 portions | F8: Tomates fraîches → pulpe concassée 200 g. | G8: =ROUND(Nutrition!I271,0)&" / "&ROUND(Nutrition!J271,0)&" / "&ROUND(Nutrition!K271,0) -> 44 / 86 / 22
A9: Jeudi | B9: Portion 2 de : Poulet basquaise et son riz | C9: 18. Chakchouka au chèvre frais & pains pita | D9: =ROUND(Nutrition!H289,0) -> 741 | E9: 20 min en cuisine (30 min à table) — 2 portions | F9: Pita → pain kebab La Boulangère (2 x 80 g) ; chèvre frais 40 g. | G9: =ROUND(Nutrition!I289,0)&" / "&ROUND(Nutrition!J289,0)&" / "&ROUND(Nutrition!K289,0) -> 33 / 82 / 30
A10: Vendredi | B10: Portion 2 de : Chakchouka au chèvre frais & pains pita | C10: 19. Pâtes crémeuses au chèvre, miel et lardons | D10: =ROUND(Nutrition!H304,0) -> 863 | E10: 15 min — 2 portions | G10: =ROUND(Nutrition!I304,0)&" / "&ROUND(Nutrition!J304,0)&" / "&ROUND(Nutrition!K304,0) -> 33 / 96 / 38
A11: Samedi | B11: Portion 2 de : Pâtes crémeuses au chèvre, miel et lardons | C11: ½ Bonduelle Poêlée gnocchi-tomate 750 g | D11: ≈ 900-1 000 | E11: Poêle / micro-ondes | F11: Sachet coupé en 2 (congélateur)
A12: Dimanche midi | B12: ½ Bonduelle Poêlée gnocchi-tomate 750 g | C12: → pizza de la semaine suivante
A14: LISTE DE COURSES CHRONODRIVE — formats entiers
A15: Produit exact (Chronodrive) | B15: Rayon | C15: Qté à acheter | D15: Prix unitaire € | E15: Total € | F15: Besoin semaine (2 portions x 5) | G15: Acheté | H15: Unité | I15: Reste après la semaine | J15: dont gâchis estimé € | K15: dont stock (se garde) € | L15: Sert aux recettes
A16: Auchan lardons fumés 2 x 100 g | B16: Charcuterie | C16: 1 | D16: 2.09 | E16: =C16*D16 -> 2.09 | F16: 100 | G16: 200 | H16: g | I16: 100 | J16: 0.5225 | K16: 0.5225 | L16: 19
A17: Auchan bûche de chèvre fondant 180 g | B17: Crèmerie | C17: 1 | D17: 2.09 | E17: =C17*D17 -> 2.09 | F17: 100 | G17: 180 | H17: g | I17: 80 | J17: 0.46444444 | K17: 0.46444444 | L17: 19
A18: Auchan fromage de chèvre frais 200 g | B18: Crèmerie | C18: 1 | D18: 2.09 | E18: =C18*D18 -> 2.09 | F18: 80 | G18: 200 | H18: g | I18: 120 | J18: 0.8778 | K18: 0.3762 | L18: 18
A19: Auchan crème épaisse légère 15 % 20 cl | B19: Crèmerie | C19: 1 | D19: 0.75 | E19: =C19*D19 -> 0.75 | F19: 120 | G19: 200 | H19: ml | I19: 80 | J19: 0.09 | K19: 0.21 | L19: 6
A20: Auchan Essentiel crème fluide légère 15 % 20 cl | B20: Crèmerie | C20: 2 | D20: 0.69 | E20: =C20*D20 -> 1.38 | F20: 250 | G20: 400 | H20: ml | I20: 150 | J20: 0 | K20: 0.5175 | L20: 11, 19
A21: Auchan Tavola grana padano râpé 60 g | B21: Crèmerie | C21: 1 | D21: 1.19 | E21: =C21*D21 -> 1.19 | F21: 30 | G21: 60 | H21: g | I21: 30 | J21: 0 | K21: 0.595 | L21: 11
A22: Auchan œufs plein air x6 | B22: Crèmerie | C22: 1 | D22: 1.69 | E22: =C22*D22 -> 1.69 | F22: 220 | G22: 330 | H22: g | I22: 110 | J22: 0 | K22: 0.56333333 | L22: 18
A23: Auchan ravioli aux fromages 300 g | B23: Frais | C23: 2 | D23: 1.69 | E23: =C23*D23 -> 3.38 | F23: 500 | G23: 600 | H23: g | I23: 100 | J23: 0.56333333 | K23: 0 | L23: 11
A24: Oignon jaune 1 kg | B24: Fruits & légumes | C24: 1 | D24: 2.69 | E24: =C24*D24 -> 2.69 | F24: 310 | G24: 1000 | H24: g | I24: 690 | J24: 0.37122 | K24: 1.48488 | L24: 6, 11, 17, 18, 19
A25: Poivron rouge 1 pièce | B25: Fruits & légumes | C25: 3 | D25: 0.99 | E25: =C25*D25 -> 2.97 | F25: 350 | G25: 450 | H25: g | I25: 100 | J25: 0.66 | K25: 0 | L25: 11, 17, 18
A26: DUC filets de poulet blanc 720 g | B26: Viande | C26: 1 | D26: 8.99 | E26: =C26*D26 -> 8.99 | F26: 600 | G26: 720 | H26: g | I26: 120 | J26: 1.4983333 | K26: 0 | L26: 6, 17
A27: Auchan champignons émincés boîte 230 g égoutté | B27: Épicerie | C27: 1 | D27: 1.29 | E27: =C27*D27 -> 1.29 | F27: 120 | G27: 230 | H27: g | I27: 110 | J27: 0.61695652 | K27: 0 | L27: 6
... A31: Auchan spaghetti 500 g | B31: Épicerie | C31: 1 | D31: 0.75 | E31: =C31*D31 -> 0.75 | F31: 440 | G31: 500 | H31: g | I31: 60 | J31: 0 | K31: 0.09 | L31: 6, 19
A32: TOTAL COURSES RECETTES | E32: =SUM(E16:E31) -> 37.18 | J32: =SUM(J16:J31) -> 6.1870251 | K32: =SUM(K16:K31) -> 6.5531786
A33: Bonduelle Poêlée gnocchi-tomate 750 g | B33: Surgelé (week-end) | C33: 1 | D33: 3.99 | E33: =C33*D33 -> 3.99 | L33: Samedi soir + dimanche midi
A34: Auchan Pizza royale jambon-fromage-olives 400 g | B34: Surgelé (week-end) | C34: 1 | D34: 2.15 | E34: =C34*D34 -> 2.15 | L34: Dimanche soir
A35: TOTAL PANIER (recettes + week-end) | E35: =E32+E33+E34 -> 43.32
A37: PLACARD / BASES utilisées cette semaine — comptées au PRIX PLEIN du format
A38: Produit exact | B38: Rayon | C38: Qté | D38: Prix format € | E38: Total € | F38: Qté utilisée cette semaine | G38: Contenu format | H38: Unité | I38: Reste (stock) | K38: Valeur du reste € | L38: Sert aux recettes
A39: Ail semoule | B39: Placard | C39: 1 | D39: 1.29 | E39: =C39*D39 -> 1.29 | F39: 18 | G39: 55 | H39: g | I39: 37 | K39: =D39*I39/G39 -> 0.86781818 | L39: 6, 11, 17
A40: Basilic séché Ducros ≈ 12 g | B40: Placard | C40: 1 | D40: 1.8 | E40: =C40*D40 -> 1.8 | F40: 2 | G40: 12 | H40: g | I40: 10 | K40: =D40*I40/G40 -> 1.5 | L40: 11
A41: Beurre | B41: Placard | C41: 1 | D41: 2.45 | E41: =C41*D41 -> 2.45 | F41: 20 | G41: 250 | H41: g | I41: 230 | K41: =D41*I41/G41 -> 2.254 | L41: 17
A42: Bouillon cube | B42: Placard | C42: 1 | D42: 1.79 | E42: =C42*D42 -> 1.79 | F42: 10 | G42: 180 | H42: g | I42: 170 | K42: =D42*I42/G42 -> 1.6905556 | L42: 6
A43: Coriandre moulue Ducros ≈ 30 g | B43: Placard | C43: 1 | D43: 1.99 | E43: =C43*D43 -> 1.99 | F43: 3 | G43: 30 | H43: g | I43: 27 | K43: =D43*I43/G43 -> 1.791 | L43: 11, 18
A44: Farine T45 | B44: Placard | C44: 1 | D44: 0.95 | E44: =C44*D44 -> 0.95 | F44: 10 | G44: 1000 | H44: g | I44: 990 | K44: =D44*I44/G44 -> 0.9405 | L44: 6
A45: Huile de tournesol | B45: Placard | C45: 1 | D45: 2.15 | E45: =C45*D45 -> 2.15 | F45: 76 | G45: 1000 | H45: ml | I45: 924 | K45: =D45*I45/G45 -> 1.9866 | L45: 6, 11, 17, 18
A46: Laurier Ducros ≈ 5 g | B46: Placard | C46: 1 | D46: 1.99 | E46: =C46*D46 -> 1.99 | F46: 1 | G46: 5 | H46: g | I46: 4 | K46: =D46*I46/G46 -> 1.592 | L46: 11
A47: Miel liquide | B47: Placard | C47: 1 | D47: 2.15 | E47: =C47*D47 -> 2.15 | F47: 10 | G47: 250 | H47: g | I47: 240 | K47: =D47*I47/G47 -> 2.064 | L47: 19
A48: Origan Ducros 12 g | B48: Placard | C48: 1 | D48: 1.89 | E48: =C48*D48 -> 1.89 | F48: 2 | G48: 12 | H48: g | I48: 10 | K48: =D48*I48/G48 -> 1.575 | L48: 18, 19
A49: Paprika doux Ducros 40 g | B49: Placard | C49: 1 | D49: 1.99 | E49: =C49*D49 -> 1.99 | F49: 4 | G49: 40 | H49: g | I49: 36 | K49: =D49*I49/G49 -> 1.791 | L49: 11, 17
A50: Persillade Ducros ≈ 20 g | B50: Placard | C50: 1 | D50: 1.9 | E50: =C50*D50 -> 1.9 | F50: 4 | G50: 20 | H50: g | I50: 16 | K50: =D50*I50/G50 -> 1.52 | L50: 6, 11
... A53: Thym Ducros ≈ 15 g | B53: Placard | C53: 1 | D53: 1.99 | E53: =C53*D53 -> 1.99 | F53: 1 | G53: 15 | H53: g | I53: 14 | K53: =D53*I53/G53 -> 1.8573333 | L53: 11
A54: TOTAL placard (prix plein) | E54: =SUM(E39:E53) -> 25.92
A56: BUDGET
A57: Panier recettes + week-end | E57: =E35 -> 43.32
A58: + placard / bases au prix plein | E58: =E54 -> 25.92
A59: TOTAL PANIER CHRONODRIVE DE LA SEMAINE | E59: =E35+E54 -> 69.24
A60: Budget max | E60: 55
A61: Marge | E61: =E60-E59 -> -14.24
A62: Gâchis estimé (périssable non consommé) | E62: =J32 -> 6.1870251
A63: Gâchis en % du panier | E63: =J32/E35 -> 0.14282145
A64: Reste non périssable (stock) | E64: =K32 -> 6.5531786
A65: Coût par portion (14 repas) | E65: =(E35+E54)/14 -> 4.9457143
A66: Si le placard est déjà plein chez toi, le panier réel redescend à | E66: =E35 -> 43.32
A69: ÉTAPES DES 5 RECETTES DE LA SEMAINE (2 portions chacune)
A70: Lundi — 6. Poulet à la crème et aux champignons + spaghetti — 35 min adaptées (10 + 25)
A71: Ingrédients (2 portions) | B71: Cuisse de poulet (ou 150 g de filet) : 300 g ; Oignon : 60 g ; Ail : 6 g ; Crème fraîche épaisse : 120 g ; Champignons de Paris en boîte (égouttés, jus gardé) : 120 g ; Farine : 10 g ; Fond de volaille déshydraté (ou ½ cube) : 10 g ; Persil (frais ou séché) : 2 g ; Eau : 200 ml ; Huile : 20 ml ; Spaghetti (remplace les tagliatelles) : 200 g ; Sel : 2 g ; Poivre : 1 g
A72: Étape 1 | B72: Couper 300 g de filet de poulet en cubes de 3 cm. Émincer 60 g d'oignon, hacher ½ gousse d'ail (ou 1 cc d'ail semoule). Égoutter 120 g de champignons de boîte en GARDANT le jus.
A73: Étape 2 | B73: Chauffer 20 ml d'huile dans une sauteuse. Faire dorer le poulet 8 min sur toutes les faces.
A74: Étape 3 | B74: Ajouter l'oignon, l'ail, 2 g de persillade et ½ cube de bouillon émietté (5 g). Mélanger, cuire jusqu'à ce que l'oignon soit translucide (3 min).
A75: Étape 4 | B75: Ajouter les champignons AVEC leur jus, l'autre ½ cube et 200 ml d'eau. Couvrir, laisser mijoter 10 min.
A76: Étape 5 | B76: Pendant ce temps, cuire 200 g de spaghetti dans l'eau bouillante salée (temps du paquet).
A77: Étape 6 | B77: Dans un bol, mélanger 120 g de crème épaisse et 10 g de farine (2 cc). Verser dans la sauteuse, mélanger.
A78: Étape 7 | B78: Laisser mijoter 10 min à feu doux à découvert jusqu'à ce que la sauce nappe la cuillère. Saler, poivrer.
A79: Étape 8 | B79: Servir la moitié du poulet-sauce sur la moitié des spaghetti. L'autre moitié en boîte (pâtes et sauce ensemble c'est OK), frigo, réchauffer 3 min avec 1 cs d'eau.
A81: Mardi — 11. Raviolis frais à la sauce tomate-crème (poivron, épices) — 25 min (10 + 15)
A82: Ingrédients (2 portions) | B82: Raviolis frais (3 fromages ou ricotta-épinards) : 500 g ; Oignon (ou échalote) : 60 g ; Huile d'olive : 20 ml ; Poivron vert (ou rouge) : 80 g ; Pulpe de tomate (boîte) : 200 g ; Ail : 6 g ; Persil (frais ou séché) : 2 g ; Paprika doux : 2 g ; Coriandre en poudre : 2 g ; Basilic (frais ou séché) : 2 g ; Thym : 1 g ; Laurier : 1 g ; Crème liquide entière : 100 ml ; Eau : 60 ml ; Parmesan râpé (finition) : 30 g ; Sel : 2 g ; Poivre : 1 g
A83: Étape 1 | B83: Porter une casserole d'eau salée à ébullition. Cuire 500 g de raviolis frais (2 barquettes de 250 g, ou 1 de 300 g + un peu) 2-3 min selon le paquet. Égoutter, réserver.
A84: Étape 2 | B84: Éplucher 60 g d'oignon et le couper en petits dés. Laver 80 g de poivron (½) et le couper en fines lamelles.
A85: Étape 3 | B85: Chauffer 20 ml d'huile dans une poêle. Faire revenir l'oignon 3 min ; dès qu'il colore, ajouter le poivron et laisser dorer 4 min en remuant.
A86: Étape 4 | B86: Verser 200 g de pulpe de tomate (½ boîte de 400 g) et 1 cc d'ail semoule (6 g). Ajouter 2 g de paprika, 2 g de coriandre en poudre, 2 g de basilic séché, 2 g de persillade, 1 pincée de thym, 1 feuille de laurier. Saler, poivrer. Laisser revenir 1 min.
A87: Étape 5 | B87: Verser 60 ml d'eau, laisser mijoter 5 bonnes minutes à feu doux.
A88: Étape 6 | B88: Ajouter 100 ml de crème fluide, laisser épaissir 1 min. Retirer le laurier.
A89: Étape 7 | B89: Déposer les raviolis dans la sauce, bien les enrober 1 min à feu doux.
A90: Étape 8 | B90: Servir la moitié avec 15 g de grana padano râpé. L'autre moitié en boîte ; réchauffer 2 min au micro-ondes ou 3 min à la poêle.
A92: Mercredi — 17. Poulet basquaise et son riz — 30 min
A93: Ingrédients (2 portions) | B93: Poulet (filet, aiguillettes ou cuisse désossée) : 300 g ; Pulpe de tomate concassée (remplace les tomates) : 400 g ; Poivron rouge : 80 g ; Poivron vert : 40 g ; Oignon : 60 g ; Ail : 6 g ; Piment d'Espelette (ou paprika + pincée de piment) : 2 g ; Riz long cru : 180 g ; Beurre : 20 g ; Huile d'olive : 20 ml ; Sel : 2 g ; Poivre : 1 g
A94: Étape 1 | B94: Émincer 60 g d'oignon et 120 g de poivron (rouge et/ou vert) en petits morceaux. Hacher ½ gousse d'ail (ou 1 cc de semoule).
A95: Étape 2 | B95: Chauffer 10 ml d'huile dans une poêle avec couvercle. Faire revenir oignon et poivron 3 min, ajouter 400 g de pulpe de tomate (1 boîte) et l'ail. Saler, poivrer, ajouter 2 g de piment d'Espelette ou de paprika.
A96: Étape 3 | B96: Couvrir, cuire à feu doux 15 min jusqu'à obtenir une compotée épaisse.
A97: Étape 4 | B97: Pendant ce temps, riz : 180 g de riz long dans 270 ml d'eau salée, couvert, 11 min à feu doux, puis 5 min de repos. Ajouter 20 g de beurre.
A98: Étape 5 | B98: Couper 300 g de filet de poulet en morceaux. Dans une seconde poêle très chaude avec 10 ml d'huile, les faire dorer 6-8 min jusqu'à belle coloration.
A99: Étape 6 | B99: Ajouter le poulet à la compotée, mélanger 2 min pour l'enrober et finir la cuisson. Rectifier sel/poivre/piment.
A100: Étape 7 | B100: Servir la moitié de la basquaise sur la moitié du riz. L'autre moitié en boîte (riz et sauce séparés de préférence) ; réchauffer 3 min au micro-ondes.
A102: Jeudi — 18. Chakchouka au chèvre frais & pains pita — 20 min en cuisine (30 min à table)
A103: Ingrédients (2 portions) | B103: Œufs : 220 g ; Fromage de chèvre frais (ou feta) : 80 g ; Pains pita : 260 g ; Poivron rouge : 150 g ; Tomates pelées en boîte (avec jus) : 200 g ; Oignon jaune : 100 g ; Origan séché : 1 g ; Coriandre en poudre : 1 g ; Huile d'olive : 16 ml ; Sucre : 1 g ; Sel : 1 g ; Poivre : 1 g
A104: Étape 1 | B104: Émincer 100 g d'oignon. Couper 150 g de poivron rouge (1 poivron) en petits dés.
A105: Étape 2 | B105: Chauffer 15 ml d'huile dans une grande poêle avec couvercle à feu moyen. Faire suer l'oignon et le poivron 8 min en remuant. Saler, poivrer.
A106: Étape 3 | B106: Ajouter 200 g de pulpe de tomate (½ boîte), 1 g d'origan, 1 g de coriandre en poudre et 1 pincée de sucre. Mélanger, laisser mijoter à demi-couvert 10 min jusqu'à une sauce onctueuse.
A107: Étape 4 | B107: Former 4 petits puits dans la sauce à la cuillère. Casser 1 œuf dans chaque creux (4 œufs). Couvrir, cuire 5 min à feu doux : blanc opaque, jaune coulant.
A108: Étape 5 | B108: Pendant ce temps, réchauffer 2 pains kebab (ou pitas) au grille-pain, ou 1 min par face à la poêle sèche. Couper 80 g de chèvre frais en morceaux.
A109: Étape 6 | B109: Émietter le chèvre frais sur la chakchouka chaude. Servir la moitié (2 œufs) avec 2 pains pour saucer.
A110: Étape 7 | B110: Pour le lendemain : la moitié restante en boîte (les œufs se réchauffent 1 min au micro-ondes, le jaune ne sera plus coulant) — ou, mieux, ne cuire que 2 œufs le soir et pocher les 2 autres le lendemain midi dans la sauce réchauffée 3 min à la poêle. 2 pains supplémentaires.
A112: Vendredi — 19. Pâtes crémeuses au chèvre, miel et lardons — 15 min
A113: Ingrédients (2 portions) | B113: Pâtes sèches (torti, penne…) : 240 g ; Lardons fumés : 100 g ; Crème liquide (source : légère 4 %) : 150 ml ; Fromage de chèvre (bûche) : 100 g ; Échalote (ou oignon) : 30 g ; Miel liquide : 10 g ; Origan séché : 1 g ; Sel : 2 g ; Poivre : 1 g
A114: Étape 1 | B114: Porter une grande casserole d'eau à ébullition, saler. Cuire 240 g de pâtes courtes ou spaghetti (temps du paquet).
A115: Étape 2 | B115: Émincer 30 g d'oignon (ou échalote). Couper 100 g de bûche de chèvre en 6 rondelles.
...

Sheet Options week-end
A1: Rayon préparé / surgelé Chronodrive Compiègne (02/09/2026) — hors Sodebo — à permuter librement, tant que la semaine reste ≤ 55 €
A3: Type | B3: Produit | C3: Poids | D3: Prix € | E3: Prix / kg | F3: Repas couverts | G3: Prix / repas €
A4: Plat cuisiné surgelé | B4: Auchan Poulet basquaise et riz 900 g | C4: 900 | D4: 4.75 | E4: 5.2777778 | F4: 2 | G4: 2.375
A5: Plat cuisiné surgelé | B5: Auchan Penne poulet-champignons 900 g | C5: 900 | D5: 4.65 | E5: 5.1666667 | F5: 2 | G5: 2.325
A6: Plat cuisiné surgelé | B6: Marie Lasagnes à la bolognaise 1 kg | C6: 1000 | D6: 5.79 | E6: 5.79 | F6: 2 | G6: 2.895
A7: Plat cuisiné surgelé | B7: Auchan Torsades à la carbonara 900 g | C7: 900 | D7: 4.95 | E7: 5.5 | F7: 2 | G7: 2.475
A8: Plat cuisiné surgelé | B8: Auchan Riz cantonais 900 g | C8: 900 | D8: 4.65 | E8: 5.1666667 | F8: 2 | G8: 2.325
A9: Plat cuisiné surgelé | B9: Auchan Paëlla poulet-crevettes-chorizo 900 g | C9: 900 | D9: 4.95 | E9: 5.5 | F9: 2 | G9: 2.475
A10: Plat cuisiné surgelé | B10: Bonduelle Poêlée gnocchi-épinards 750 g | C10: 750 | D10: 3.95 | E10: 5.2666667 | F10: 2 | G10: 1.975
A11: Plat cuisiné surgelé | B11: Auchan Poêlée campagnarde 900 g | C11: 900 | D11: 4.95 | E11: 5.5 | F11: 2 | G11: 2.475
A12: Plat cuisiné surgelé | B12: Bonduelle Poêlée gnocchi-tomate 750 g | C12: 750 | D12: 3.99 | E12: 5.32 | F12: 2 | G12: 1.995
A13: Plat cuisiné surgelé | B13: Bonduelle Poêlée fusilli courgettes-fromage 750 g | C13: 750 | D13: 3.99 | E13: 5.32 | F13: 2 | G13: 1.995
A14: Plat cuisiné surgelé | B14: Marie Fusilli poulet-champignons 900 g | C14: 900 | D14: 5.09 | E14: 5.6555556 | F14: 2 | G14: 2.545
A15: Plat cuisiné surgelé | B15: Marie Risotto au poulet 900 g | C15: 900 | D15: 5.29 | E15: 5.8777778 | F15: 2 | G15: 2.645
... A30: Pizza | B30: Auchan Kit pizza rectangulaire 600 g à garnir | C30: 600 | D30: 2.79 | E30: 4.65 | F30: 1 | G30: 2.79

Sheet Méthode
A1: Génération : les 26 334 combinaisons de 5 recettes parmi 22 ont été évaluées ; 16 378 respectent la variété (≥ 4 protéines et ≥ 4 féculents différents, jamais deux fois la même base, pas R11 + R12 ensemble) et le budget (≤ 55 € avec un week-end au pire à 7,60 €).
A2: Coût d'une semaine = somme des formats ENTIERS achetés (meilleure combinaison de formats par produit : prix mini puis reste mini) + placard/bases au PRIX PLEIN du format (huile, chaque épice, farine, moutarde, miel, cubes, soja, ail, sel, sucre, vinaigre, beurre : comptés comme si tu devais les racheter) + plat 900 g + pizza. La sélection des 8 semaines a été faite avec le placard au pro-rata ; le passage au prix plein n'a pas changé la sélection, seuls les totaux ont été recalculés.
A3: Score d'une semaine = coût + 2 x gâchis + 0,3 x stock. Gâchis = valeur du reste des produits périssables (viande, charcuterie, fromages frais, pâtes fraîches, légumes, pain), pondérée par leur durée de vie ; stock = reste des produits secs/conserves (riz, pâtes, boîtes, UHT), que tu gères à la main.
A4: Sélection : 8 semaines par ordre de score, avec chaque recette au maximum 2 fois sur les 8 et aucune recette commune à deux semaines consécutives. 9e semaine impossible sans passer une recette à 3 utilisations (4, 6, 17 et 18 ne sont utilisées qu'une fois : hachis, poulet-crème, basquaise, chakchouka).
A5: Ordre dans la semaine : les recettes à viande/poisson frais et DLC courte (échine, haché, jambon, pâtes fraîches) sont placées lundi-mardi, les recettes 100 % placard (carbonara, one-pot, saucisses-lentilles, risotto) en fin de semaine.
A6: Week-end : rotation sur 8 plats 900 g et 8 pizzas différents (hors Sodebo) ; 2 articles au congélateur maximum. Tu peux permuter avec n'importe quelle ligne de l'onglet Options week-end tant que le total reste ≤ 55 €.
A7: Substitutions v3 appliquées partout (onglet Recettes v3) : échine à la place du filet mignon, ravioli Auchan à la place des ravioles, spaghetti à la place des tagliatelles, pulpe à la place des tomates/coulis, emmental à la place de cheddar/gouda, crème épaisse à la place du mascarpone et du lait, olives supprimées.
A8: Semaine 0 (une fois) : placard épices ≈ 17 € + huile 2,15 € + farine 0,95 € + moutarde 1,85 € + miel 2,15 € + cubes 1,79 € + soja 1,69 € + ail semoule 1,29 € + vinaigre 1,09 € + beurre 2,45 € ≈ 32 €, hors budget hebdo.
A10: Mise à jour du 12/10/2026 : ajout de R23 (pâtes pesto caprese, 1 boule de mozzarella par portion) et R24 (pâtes sauce tomate-basilic, mozzarella fondante, parmesan). 24 recettes → 9 semaines (chaque recette ≤ 2 fois, jamais deux semaines de suite, R23 et R24 jamais ensemble, max 2 recettes de pâtes par semaine). S1 est conservée telle quelle (panier déjà constitué).
A11: Pesto vert et sauce tomate-basilic : prix Chronodrive non relevés (pesto rosso Auchan 1,99 € pris comme référence ; sauce 420 g estimée 1,29 €). Relevés Carrefour hypermarché Bomerée du 12/10 : pesto verde Classic' 190 g 1,49 €, sauce tomates-basilic Classic' 420 g 1,39 €, mozzarella Galbani 125 g 1,19 €, Simpl 200 g 0,69 €, tomates cerises 400 g 1,25 €, pâtes Simpl 500 g 0,47 €, parmesan Parmareggio 60 g 2,85 €, râpé Spécial Pasta 200 g 1,99 €.
